Workbook

Sheet 00_Anleitung
B2: VALERI – Wirtschaftlichkeitsbewertung von Effizienzmaßnahmen
B3: V7
B5: Aufbau der Datei
B6: 00_Anleitung | C6: Dieses Blatt.
B7: 01_Übersicht | C7: Vergleich aller Maßnahmen. Blattnamen in Spalte B eintragen, die Kennzahlen zieht das Blatt selbst.
B8: Allgemeine Unternehmensdaten | C8: Preise, Zinssätze, Einspeisevergütung. Gilt für alle Maßnahmen. Einmal je Projekt setzen.
B9: Vorlage Maßnahme | C9: Leeres Maßnahmenblatt. Für jede neue Maßnahme kopieren und umbenennen.
B10: Beispiel Nr. 78 … | C10: Vollständig ausgefülltes Beispiel einer realen Maßnahme – inklusive Cashflow-Diagramm und Plausibilitätskontrolle.
B11: Bestätigung | C11: Formular .
B13: So gehen Sie vor
B14: → | C14: Blatt „Allgemeine Unternehmensdaten“ ausfüllen – Preise und Zinssätze gelten projektweit.
B15: → | C15: Blatt „Vorlage Maßnahme“ mit Rechtsklick kopieren und nach der Maßnahme benennen.
B16: → | C16: Im neuen Blatt die gelben Felder ausfüllen: Kopf, Verbräuche, Betriebszeit, Investition.
B17: → | C17: Plausibilitätskontrolle ab Zeile 65 prüfen – dort darf kein FEHLER stehen.
B18: → | C18: Ergebnis in Zeile 85/86 ablesen und den Blattnamen in „01_Übersicht“ eintragen.
B20: Die drei Szenarien
B21: Spaltenlogik | C21: Überall gilt: Spalte D = Worst Case, E = Erwarteter Fall, F = Best Case. Beim Ist-Verbrauch zusätzlich G/H/I für den Soll-Verbrauch in derselben Reihenfolge.
B22: Ausnahme Zinssatz | C22: Im Blatt „Allgemeine Unternehmensdaten“ ist der Zinssatz-Block bewusst gespiegelt (E = Best Case), weil ein niedriger Zinssatz für die Maßnahme günstig ist. Die Prüfzelle E26 meldet, wenn der wahrscheinliche Wert ausserhalb von Best und Worst liegt.
B24: Zwei Stolperfallen
B25: Erstes Betriebsjahr | C25: Zeile 18 erwartet einen **Index**, keine Jahreszahl. 0 = die Maßnahme wirkt ab dem ersten Betrachtungsjahr, 1 = ab dem zweiten. Eine Kalenderjahreszahl wie 2026 blockiert die gesamte Rechnung – es entstehen keine Cashflows und der Kapitalwert bleibt bei minus Investition.
B26: Einsparung nur aus einer Quelle | C26: Die Einsparung kommt entweder aus dem Soll-Verbrauch (Zeile 11/12/13, Spalten G/H/I) oder aus dem Prozentwert (Zeile 23/26/27) – nie aus beidem. Die jeweils andere Darstellung muss eine Formel bleiben, sonst stehen widersprüchliche Werte im Blatt.
B28: Rechenweg
B29: Zeitachse | C29: Ab Spalte S läuft der Index 0, 1, 2 … Drei Blöcke nebeneinander: S–BT erwarteter Fall, BW–DX Worst Case, EA–GB Best Case.
B30: Cashflow je Jahr | C30: Nutzen (Zeilen 23–38) minus Lasten (Zeilen 39–55), jeweils mit Preisänderung hochgerechnet und mit dem WACC diskontiert.
B31: Kapitalwert | C31: Zeile 62 summiert die diskontierten Jahreswerte auf; der Endwert steht in Zeile 86.
B32: Amortisation | C32: Zeile 85 sucht den Vorzeichenwechsel in Zeile 62. „–“ bedeutet: kein Vorzeichenwechsel innerhalb der Nutzungszeit, oder die Maßnahme trägt sich schon im ersten Jahr.
B33: Diagramm | C33: Unter dem Ergebnis (Zeilen 87–89): kumulierter diskontierter Cashflow je Szenario. Schnittpunkt einer Linie mit der Nulllinie = Amortisationszeit; endet die Linie unter null, trägt sich die Maßnahme in diesem Szenario nicht. Datenquelle sind die Zeilen 62–64 ab Spalte S.
B35: Was gegenüber V6 geändert wurde
B36: • | C36: Betriebszeit korrigiert: „letztes Betriebsjahr“ ist jetzt erstes + Nutzungszeit − 1. Bisher lief die Maßnahme ein Jahr zu lang.
B37: • | C37: Zeile 45 (Abzahlung) auf 0 gesetzt und als Alternative zu Zeile 44 gekennzeichnet. In V6 waren beide aktiv – die Investition wurde doppelt gezählt.
B38: • | C38: Blattname „Allgemeine Unternehemensdaten“ (Schreibfehler) berichtigt; alle 3.121 Verweise mitgezogen.
B39: • | C39: Selbstbezüge der Art 'Maßnahme 1 '!T20 entfernt. Kopierte Blätter rechneten sonst weiter mit der Zeitachse der Vorlage.
B40: • | C40: Gaspreis-Einheit von €/m³ auf €/kWh berichtigt – das Maßnahmenblatt erfasst kWh.
B41: • | C41: Einzelne verirrte Werte bereinigt (K33, K41, L41).
B42: • | C42: Neu: Statusauswahl, Plausibilitätskontrolle, Übersichtsblatt, dieses Anleitungsblatt, Beispielmaßnahme.
B44: Neu in V7.1 (06.08.2026)
B45: • | C45: Diagramm: kumulierter diskontierter Cashflow je Szenario mit Titel, Legende und Achsenbeschriftung – jetzt unterhalb des Ergebnisses (Zeilen 87–89), damit die Plausibilitätskontrolle sichtbar bleibt. Im Beispiel ergänzt (fehlte dort komplett).
B46: • | C46: Plausibilitätskontrolle im Beispiel repariert: Die Prüfformeln waren um 81 Zeilen verschoben und meldeten falsche FEHLER. Neue Prüfung in beiden Blättern: Gas-/Flex-Einsparung nur aus einer Quelle (Zeile 73).
B47: • | C47: Tippfehler in Beschriftungen, Unternehmensdaten und Berichtstexten bereinigt (Einsparung, Entsorgung, Mehrverbrauch, Amortisationszeit, Lebensdauer, Eigenkapital u. a.); Einheit des flexiblen Kostenfaktors: Verbrauch in m³/Jahr.
B48: • | C48: Vorlage: Investitions-Streuung wieder als Formel (Worst = 1,3 × Erw., Best = 0,75 × Erw.); 01_Übersicht zeigt negative Kapitalwerte rot; Beispielbericht um nicht monetisierbare Wirkungen ergänzt.
B50: Offener Punkt aus der Prüfung
B51: Zinssatz in MVO-2026-V3 | C51: In der Auswertung MVO-2026-V3 steht der Eigenkapitalzins des erwarteten Falls auf 9,5 %, während Best 1 % und Worst 5 % beträgt. Der wahrscheinliche Wert liegt damit ausserhalb der Spanne und der erwartete Fall wird härter diskontiert als der Worst Case. Bei der Photovoltaik ist der Kapitalwert im Worst Case dadurch höher als im erwarteten Fall. Diese Vorlage nutzt die Werte aus V6 (1 % / 3,5 % / 5 %); die Prüfzelle E26 der Unternehmensdaten meldet solche Fälle künftig.

Sheet 01_Übersicht
B2: Übersicht aller bewerteten Maßnahmen
B3: Blattnamen in Spalte B eintragen – die Kennzahlen werden automatisch gezogen.
B5: Blattname (eintragen) | C5: Bezeichnung | D5: Status | E5: Investition [€] | F5: Kapitalwert Worst [€] | G5: Kapitalwert Erw. [€] | H5: Kapitalwert Best [€] | I5: Amort. Worst [a] | J5: Amort. Erw. [a] | K5: Amort. Best [a] | L5: Rang
B6: Beispiel Nr. 78 Druckluft | C6: =IF($B6="","",IFERROR(INDIRECT("'"&$B6&"'!"&"D2"),"")) -> Nr. 78: Optimierung Druckluftverbrauch – intelligente Druckluftsteuerung | D6: =IF($B6="","",IFERROR(INDIRECT("'"&$B6&"'!"&"D3"),"")) -> Realisiert | E6: =IF($B6="","",IFERROR(INDIRECT("'"&$B6&"'!"&"E44"),"")) -> 34000 | F6: =IF($B6="","",IFERROR(INDIRECT("'"&$B6&"'!"&"F86"),"")) -> -1530.2689 | G6: =IF($B6="","",IFERROR(INDIRECT("'"&$B6&"'!"&"G86"),"")) -> 41169.853 | H6: =IF($B6="","",IFERROR(INDIRECT("'"&$B6&"'!"&"H86"),"")) -> 99140.318 | I6: =IF($B6="","",IFERROR(INDIRECT("'"&$B6&"'!"&"F85"),"")) -> - | J6: =IF($B6="","",IFERROR(INDIRECT("'"&$B6&"'!"&"G85"),"")) -> 3.4049907 | K6: =IF($B6="","",IFERROR(INDIRECT("'"&$B6&"'!"&"H85"),"")) -> 1.9337344 | L6: =IF(OR($B6="",NOT(ISNUMBER($G6))),"",SUMPRODUCT((ISNUMBER($G$6:$G$20))*($G$6:$G$20>$G6))+1) -> 1
C7: =IF($B7="","",IFERROR(INDIRECT("'"&$B7&"'!"&"D2"),"")) | D7: =IF($B7="","",IFERROR(INDIRECT("'"&$B7&"'!"&"D3"),"")) | E7: =IF($B7="","",IFERROR(INDIRECT("'"&$B7&"'!"&"E44"),"")) | F7: =IF($B7="","",IFERROR(INDIRECT("'"&$B7&"'!"&"F86"),"")) | G7: =IF($B7="","",IFERROR(INDIRECT("'"&$B7&"'!"&"G86"),"")) | H7: =IF($B7="","",IFERROR(INDIRECT("'"&$B7&"'!"&"H86"),"")) | I7: =IF($B7="","",IFERROR(INDIRECT("'"&$B7&"'!"&"F85"),"")) | J7: =IF($B7="","",IFERROR(INDIRECT("'"&$B7&"'!"&"G85"),"")) | K7: =IF($B7="","",IFERROR(INDIRECT("'"&$B7&"'!"&"H85"),"")) | L7: =IF(OR($B7="",NOT(ISNUMBER($G7))),"",SUMPRODUCT((ISNUMBER($G$6:$G$20))*($G$6:$G$20>$G7))+1)
C8: =IF($B8="","",IFERROR(INDIRECT("'"&$B8&"'!"&"D2"),"")) | D8: =IF($B8="","",IFERROR(INDIRECT("'"&$B8&"'!"&"D3"),"")) | E8: =IF($B8="","",IFERROR(INDIRECT("'"&$B8&"'!"&"E44"),"")) | F8: =IF($B8="","",IFERROR(INDIRECT("'"&$B8&"'!"&"F86"),"")) | G8: =IF($B8="","",IFERROR(INDIRECT("'"&$B8&"'!"&"G86"),"")) | H8: =IF($B8="","",IFERROR(INDIRECT("'"&$B8&"'!"&"H86"),"")) | I8: =IF($B8="","",IFERROR(INDIRECT("'"&$B8&"'!"&"F85"),"")) | J8: =IF($B8="","",IFERROR(INDIRECT("'"&$B8&"'!"&"G85"),"")) | K8: =IF($B8="","",IFERROR(INDIRECT("'"&$B8&"'!"&"H85"),"")) | L8: =IF(OR($B8="",NOT(ISNUMBER($G8))),"",SUMPRODUCT((ISNUMBER($G$6:$G$20))*($G$6:$G$20>$G8))+1)
C9: =IF($B9="","",IFERROR(INDIRECT("'"&$B9&"'!"&"D2"),"")) | D9: =IF($B9="","",IFERROR(INDIRECT("'"&$B9&"'!"&"D3"),"")) | E9: =IF($B9="","",IFERROR(INDIRECT("'"&$B9&"'!"&"E44"),"")) | F9: =IF($B9="","",IFERROR(INDIRECT("'"&$B9&"'!"&"F86"),"")) | G9: =IF($B9="","",IFERROR(INDIRECT("'"&$B9&"'!"&"G86"),"")) | H9: =IF($B9="","",IFERROR(INDIRECT("'"&$B9&"'!"&"H86"),"")) | I9: =IF($B9="","",IFERROR(INDIRECT("'"&$B9&"'!"&"F85"),"")) | J9: =IF($B9="","",IFERROR(INDIRECT("'"&$B9&"'!"&"G85"),"")) | K9: =IF($B9="","",IFERROR(INDIRECT("'"&$B9&"'!"&"H85"),"")) | L9: =IF(OR($B9="",NOT(ISNUMBER($G9))),"",SUMPRODUCT((ISNUMBER($G$6:$G$20))*($G$6:$G$20>$G9))+1)
C10: =IF($B10="","",IFERROR(INDIRECT("'"&$B10&"'!"&"D2"),"")) | D10: =IF($B10="","",IFERROR(INDIRECT("'"&$B10&"'!"&"D3"),"")) | E10: =IF($B10="","",IFERROR(INDIRECT("'"&$B10&"'!"&"E44"),"")) | F10: =IF($B10="","",IFERROR(INDIRECT("'"&$B10&"'!"&"F86"),"")) | G10: =IF($B10="","",IFERROR(INDIRECT("'"&$B10&"'!"&"G86"),"")) | H10: =IF($B10="","",IFERROR(INDIRECT("'"&$B10&"'!"&"H86"),"")) | I10: =IF($B10="","",IFERROR(INDIRECT("'"&$B10&"'!"&"F85"),"")) | J10: =IF($B10="","",IFERROR(INDIRECT("'"&$B10&"'!"&"G85"),"")) | K10: =IF($B10="","",IFERROR(INDIRECT("'"&$B10&"'!"&"H85"),"")) | L10: =IF(OR($B10="",NOT(ISNUMBER($G10))),"",SUMPRODUCT((ISNUMBER($G$6:$G$20))*($G$6:$G$20>$G10))+1)
C11: =IF($B11="","",IFERROR(INDIRECT("'"&$B11&"'!"&"D2"),"")) | D11: =IF($B11="","",IFERROR(INDIRECT("'"&$B11&"'!"&"D3"),"")) | E11: =IF($B11="","",IFERROR(INDIRECT("'"&$B11&"'!"&"E44"),"")) | F11: =IF($B11="","",IFERROR(INDIRECT("'"&$B11&"'!"&"F86"),"")) | G11: =IF($B11="","",IFERROR(INDIRECT("'"&$B11&"'!"&"G86"),"")) | H11: =IF($B11="","",IFERROR(INDIRECT("'"&$B11&"'!"&"H86"),"")) | I11: =IF($B11="","",IFERROR(INDIRECT("'"&$B11&"'!"&"F85"),"")) | J11: =IF($B11="","",IFERROR(INDIRECT("'"&$B11&"'!"&"G85"),"")) | K11: =IF($B11="","",IFERROR(INDIRECT("'"&$B11&"'!"&"H85"),"")) | L11: =IF(OR($B11="",NOT(ISNUMBER($G11))),"",SUMPRODUCT((ISNUMBER($G$6:$G$20))*($G$6:$G$20>$G11))+1)
C12: =IF($B12="","",IFERROR(INDIRECT("'"&$B12&"'!"&"D2"),"")) | D12: =IF($B12="","",IFERROR(INDIRECT("'"&$B12&"'!"&"D3"),"")) | E12: =IF($B12="","",IFERROR(INDIRECT("'"&$B12&"'!"&"E44"),"")) | F12: =IF($B12="","",IFERROR(INDIRECT("'"&$B12&"'!"&"F86"),"")) | G12: =IF($B12="","",IFERROR(INDIRECT("'"&$B12&"'!"&"G86"),"")) | H12: =IF($B12="","",IFERROR(INDIRECT("'"&$B12&"'!"&"H86"),"")) | I12: =IF($B12="","",IFERROR(INDIRECT("'"&$B12&"'!"&"F85"),"")) | J12: =IF($B12="","",IFERROR(INDIRECT("'"&$B12&"'!"&"G85"),"")) | K12: =IF($B12="","",IFERROR(INDIRECT("'"&$B12&"'!"&"H85"),"")) | L12: =IF(OR($B12="",NOT(ISNUMBER($G12))),"",SUMPRODUCT((ISNUMBER($G$6:$G$20))*($G$6:$G$20>$G12))+1)
C13: =IF($B13="","",IFERROR(INDIRECT("'"&$B13&"'!"&"D2"),"")) | D13: =IF($B13="","",IFERROR(INDIRECT("'"&$B13&"'!"&"D3"),"")) | E13: =IF($B13="","",IFERROR(INDIRECT("'"&$B13&"'!"&"E44"),"")) | F13: =IF($B13="","",IFERROR(INDIRECT("'"&$B13&"'!"&"F86"),"")) | G13: =IF($B13="","",IFERROR(INDIRECT("'"&$B13&"'!"&"G86"),"")) | H13: =IF($B13="","",IFERROR(INDIRECT("'"&$B13&"'!"&"H86"),"")) | I13: =IF($B13="","",IFERROR(INDIRECT("'"&$B13&"'!"&"F85"),"")) | J13: =IF($B13="","",IFERROR(INDIRECT("'"&$B13&"'!"&"G85"),"")) | K13: =IF($B13="","",IFERROR(INDIRECT("'"&$B13&"'!"&"H85"),"")) | L13: =IF(OR($B13="",NOT(ISNUMBER($G13))),"",SUMPRODUCT((ISNUMBER($G$6:$G$20))*($G$6:$G$20>$G13))+1)
C14: =IF($B14="","",IFERROR(INDIRECT("'"&$B14&"'!"&"D2"),"")) | D14: =IF($B14="","",IFERROR(INDIRECT("'"&$B14&"'!"&"D3"),"")) | E14: =IF($B14="","",IFERROR(INDIRECT("'"&$B14&"'!"&"E44"),"")) | F14: =IF($B14="","",IFERROR(INDIRECT("'"&$B14&"'!"&"F86"),"")) | G14: =IF($B14="","",IFERROR(INDIRECT("'"&$B14&"'!"&"G86"),"")) | H14: =IF($B14="","",IFERROR(INDIRECT("'"&$B14&"'!"&"H86"),"")) | I14: =IF($B14="","",IFERROR(INDIRECT("'"&$B14&"'!"&"F85"),"")) | J14: =IF($B14="","",IFERROR(INDIRECT("'"&$B14&"'!"&"G85"),"")) | K14: =IF($B14="","",IFERROR(INDIRECT("'"&$B14&"'!"&"H85"),"")) | L14: =IF(OR($B14="",NOT(ISNUMBER($G14))),"",SUMPRODUCT((ISNUMBER($G$6:$G$20))*($G$6:$G$20>$G14))+1)
C15: =IF($B15="","",IFERROR(INDIRECT("'"&$B15&"'!"&"D2"),"")) | D15: =IF($B15="","",IFERROR(INDIRECT("'"&$B15&"'!"&"D3"),"")) | E15: =IF($B15="","",IFERROR(INDIRECT("'"&$B15&"'!"&"E44"),"")) | F15: =IF($B15="","",IFERROR(INDIRECT("'"&$B15&"'!"&"F86"),"")) | G15: =IF($B15="","",IFERROR(INDIRECT("'"&$B15&"'!"&"G86"),"")) | H15: =IF($B15="","",IFERROR(INDIRECT("'"&$B15&"'!"&"H86"),"")) | I15: =IF($B15="","",IFERROR(INDIRECT("'"&$B15&"'!"&"F85"),"")) | J15: =IF($B15="","",IFERROR(INDIRECT("'"&$B15&"'!"&"G85"),"")) | K15: =IF($B15="","",IFERROR(INDIRECT("'"&$B15&"'!"&"H85"),"")) | L15: =IF(OR($B15="",NOT(ISNUMBER($G15))),"",SUMPRODUCT((ISNUMBER($G$6:$G$20))*($G$6:$G$20>$G15))+1)
C16: =IF($B16="","",IFERROR(INDIRECT("'"&$B16&"'!"&"D2"),"")) | D16: =IF($B16="","",IFERROR(INDIRECT("'"&$B16&"'!"&"D3"),"")) | E16: =IF($B16="","",IFERROR(INDIRECT("'"&$B16&"'!"&"E44"),"")) | F16: =IF($B16="","",IFERROR(INDIRECT("'"&$B16&"'!"&"F86"),"")) | G16: =IF($B16="","",IFERROR(INDIRECT("'"&$B16&"'!"&"G86"),"")) | H16: =IF($B16="","",IFERROR(INDIRECT("'"&$B16&"'!"&"H86"),"")) | I16: =IF($B16="","",IFERROR(INDIRECT("'"&$B16&"'!"&"F85"),"")) | J16: =IF($B16="","",IFERROR(INDIRECT("'"&$B16&"'!"&"G85"),"")) | K16: =IF($B16="","",IFERROR(INDIRECT("'"&$B16&"'!"&"H85"),"")) | L16: =IF(OR($B16="",NOT(ISNUMBER($G16))),"",SUMPRODUCT((ISNUMBER($G$6:$G$20))*($G$6:$G$20>$G16))+1)
C17: =IF($B17="","",IFERROR(INDIRECT("'"&$B17&"'!"&"D2"),"")) | D17: =IF($B17="","",IFERROR(INDIRECT("'"&$B17&"'!"&"D3"),"")) | E17: =IF($B17="","",IFERROR(INDIRECT("'"&$B17&"'!"&"E44"),"")) | F17: =IF($B17="","",IFERROR(INDIRECT("'"&$B17&"'!"&"F86"),"")) | G17: =IF($B17="","",IFERROR(INDIRECT("'"&$B17&"'!"&"G86"),"")) | H17: =IF($B17="","",IFERROR(INDIRECT("'"&$B17&"'!"&"H86"),"")) | I17: =IF($B17="","",IFERROR(INDIRECT("'"&$B17&"'!"&"F85"),"")) | J17: =IF($B17="","",IFERROR(INDIRECT("'"&$B17&"'!"&"G85"),"")) | K17: =IF($B17="","",IFERROR(INDIRECT("'"&$B17&"'!"&"H85"),"")) | L17: =IF(OR($B17="",NOT(ISNUMBER($G17))),"",SUMPRODUCT((ISNUMBER($G$6:$G$20))*($G$6:$G$20>$G17))+1)
C18: =IF($B18="","",IFERROR(INDIRECT("'"&$B18&"'!"&"D2"),"")) | D18: =IF($B18="","",IFERROR(INDIRECT("'"&$B18&"'!"&"D3"),"")) | E18: =IF($B18="","",IFERROR(INDIRECT("'"&$B18&"'!"&"E44"),"")) | F18: =IF($B18="","",IFERROR(INDIRECT("'"&$B18&"'!"&"F86"),"")) | G18: =IF($B18="","",IFERROR(INDIRECT("'"&$B18&"'!"&"G86"),"")) | H18: =IF($B18="","",IFERROR(INDIRECT("'"&$B18&"'!"&"H86"),"")) | I18: =IF($B18="","",IFERROR(INDIRECT("'"&$B18&"'!"&"F85"),"")) | J18: =IF($B18="","",IFERROR(INDIRECT("'"&$B18&"'!"&"G85"),"")) | K18: =IF($B18="","",IFERROR(INDIRECT("'"&$B18&"'!"&"H85"),"")) | L18: =IF(OR($B18="",NOT(ISNUMBER($G18))),"",SUMPRODUCT((ISNUMBER($G$6:$G$20))*($G$6:$G$20>$G18))+1)
... C20: =IF($B20="","",IFERROR(INDIRECT("'"&$B20&"'!"&"D2"),"")) | D20: =IF($B20="","",IFERROR(INDIRECT("'"&$B20&"'!"&"D3"),"")) | E20: =IF($B20="","",IFERROR(INDIRECT("'"&$B20&"'!"&"E44"),"")) | F20: =IF($B20="","",IFERROR(INDIRECT("'"&$B20&"'!"&"F86"),"")) | G20: =IF($B20="","",IFERROR(INDIRECT("'"&$B20&"'!"&"G86"),"")) | H20: =IF($B20="","",IFERROR(INDIRECT("'"&$B20&"'!"&"H86"),"")) | I20: =IF($B20="","",IFERROR(INDIRECT("'"&$B20&"'!"&"F85"),"")) | J20: =IF($B20="","",IFERROR(INDIRECT("'"&$B20&"'!"&"G85"),"")) | K20: =IF($B20="","",IFERROR(INDIRECT("'"&$B20&"'!"&"H85"),"")) | L20: =IF(OR($B20="",NOT(ISNUMBER($G20))),"",SUMPRODUCT((ISNUMBER($G$6:$G$20))*($G$6:$G$20>$G20))+1)
B22: Summe Investition | E22: =SUM(E6:E20) -> 34000 | F22: =SUM(F6:F20) -> -1530.2689 | G22: =SUM(G6:G20) -> 41169.853 | H22: =SUM(H6:H20) -> 99140.318
B24: Rang 1 = höchster Kapitalwert im erwarteten Fall. „–“ bei der Amortisation bedeutet: innerhalb der Nutzungszeit wird der Kapitalwert nie positiv, oder die Maßnahme amortisiert sich bereits innerhalb des ersten Jahres.

Sheet Allgemeine Unternehmensdaten
C2: Allgemeine Unternehmensdaten
C5: Strompreis
D6: Einheit | E6: Worst Case | F6: Erwarteter Fall | G6: Best Case
C7: Preis | D7: €/kWh | E7: 0.172 | F7: 0.218 | G7: 0.25 | H7: Hoher Strompreis ist für die Investition der best Case
C8: Preissteigerung | D8: % | E8: 0.04 | F8: 0.03 | G8: 0.02
C11: Gaspreis
D12: Einheit | E12: Worst Case | F12: Erwarteter Fall | G12: Best Case
C13: Preis | D13: €/kWh | E13: 0.06 | F13: 0.08 | G13: 0.1
C14: Preissteigerung | D14: % | E14: 0.04 | F14: 0.03 | G14: 0.02
C19: Zinssatz
E20: Best Case | F20: Wahrscheinl. | G20: Worst Case | H20: niedriger Zinssatz für die Investition der Best Case | I20: ACHTUNG: In diesem Block ist die Reihenfolge gespiegelt (E = Best Case), weil ein niedriger Zinssatz für die Maßnahme günstig ist. In allen anderen Blöcken gilt E = Worst Case.
C21: Eigenkapitalanteil Seq (= Ceq / Cinvest) | E21: 0
C22: Fremdkapitalanteil Sdebt (= Cdebt / Cinvest) | E22: =1-E21 -> 1
C23: req = Zinssatz für Eigenkapital | E23: 0.01 | F23: 0.035 | G23: 0.05
C24: rdebt = Zinssatz des Fremdkapitals | E24: 0.03 | F24: 0.04 | G24: 0.06
C25: r = gewichtete durchschnittliche Kapitalkosten WACC (= Seq ⋅ req + Sdebt ⋅ rdebt) | E25: =E21*E23+E22*E24 -> 0.03 | F25: =E21*F23+E22*F24 -> 0.04 | G25: =E21*G23+E22*G24 -> 0.06
C26: Prüfung: liegt der wahrscheinliche WACC zwischen Best und Worst? | E26: =IF(OR(E25="",F25="",G25=""),"",IF(AND(F25>=MIN(E25,G25),F25<=MAX(E25,G25)),"in Ordnung","FEHLER: Wahrscheinl. liegt ausserhalb von Best/Worst")) -> in Ordnung
C27: Prüfung: Eigen- + Fremdkapitalanteil = 100 %? | E27: =IF(ABS(E21+E22-1)<0.0001,"in Ordnung","FEHLER: Anteile ergeben nicht 100 %") -> in Ordnung
C28: Flexibler Kostenfaktor (z.B. Druckluft)
C29: Faktor | E29: Preis | F29: Einheit
C30: Flexibler Kostenfaktor | E30: 0.003 | F30: €/m³
C32: Strom Einspeisung | E32: Worst Case | F32: Erw. Fall | G32: Best Case | H32: Hohe Einspeisevergütung für die Investition der Best Case
C33: Einspeisevergütung €/kWh | E33: 0.06 | F33: 0.06 | G33: 0.06
C34: Schwankung in % | E34: 0.03 | F34: 0.02 | G34: 0.01
C36: Strom kalk. Eigennutzung | E36: Worst Case | F36: Erw. Fall | G36: Best Case
C37: kalk. Vergütung €/kWh | E37: =E7 -> 0.172 | F37: =F7 -> 0.218 | G37: =G7 -> 0.25
C38: Schwankung in % | E38: =E8 -> 0.04 | F38: =F8 -> 0.03 | G38: =G8 -> 0.02

Sheet Vorlage Maßnahme
B2: Bezeichnung des Projekts: | D2: Titel
B3: Status | D3: Zu prüfen | FW3: BITTE WÄHLEN | FY3: ja (standard)
B4: Beschreibung: | D4: Beschreibung | FW4: Geplant | FY4: nein
FW5: In Umsetzung
B6: Preisschw. für rel. Güter und Dienstleistungen % | D6: Worst Case | E6: Erw. Fall | F6: Best Case | FW6: Abgelehnt
D7: 0.02 | E7: 0.03 | F7: 0.05 | FW7: Zu Prüfen
FW8: Realisiert
D9: Ist | G9: Soll (oder Einsparung in % angeben)
D10: Worst Case | E10: Erw. Fall | F10: Best Case | G10: Worst Case | H10: Erw. Fall | I10: Best Case
B11: Stromverbrauch kWh/Jahr | D11: =0.9*E11 -> 90000 | E11: 100000 | F11: =1.1*E11 -> 110000 | G11: =0.9*H11 -> 72000 | H11: 80000 | I11: =1.1*H11 -> 88000
B12: Gasverbrauch kWh/Jahr | D12: =0.9*E12 -> 0 | E12: 0 | F12: =1.1*E12 -> 0 | G12: 0 | H12: 0 | I12: 0
B13: ='Allgemeine Unternehmensdaten'!C30&"-Verbrauch in "&SUBSTITUTE('Allgemeine Unternehmensdaten'!F30,"€/","")&"/Jahr" -> Flexibler Kostenfaktor-Verbrauch in m³/Jahr | D13: =0.9*E13 -> 0 | E13: 0 | F13: =1.1*E13 -> 0 | G13: 0 | H13: 0 | I13: 0
D17: Worst Case | E17: Erw. Fall | F17: Best Case
B18: Erstes Betriebsjahr | D18: 0 | E18: 0 | F18: 0 | G18: Index, KEINE Jahreszahl: 0 = ab dem ersten Betrachtungsjahr
B19: Nutzungszeit | D19: 5 | E19: 5 | F19: 5 | R19: Erw. Fall Erw. Fall Erw. Fall Erw. Fall Erw. Fall Erw. Fall Erw. Fall Erw. Fall Erw. Fall Erw. Fall Erw. Fall Erw. Fall Erw. Fall Erw. Fall Erw. Fall Erw. Fall Erw. Fall Erw. Fall Erw. Fall Erw. Fall Erw. Fall Erw. Fall Erw. Fall Erw. Fall Erw. Fall Erw. Fall Erw. Fall Erw. Fall | BV19: Worst Case Worst Case Worst Case Worst Case Worst Case Worst Case Worst Case Worst Case Worst Case Worst Case Worst Case Worst Case Worst Case Worst Case Worst Case Worst Case Worst Case Worst Case Worst Case Worst Case Worst Case Worst Case Worst Case Worst Case Worst Case Worst Case Worst Case Worst Case Worst Case Worst Case | DZ19: Best Case Best Case Best Case Best Case Best Case Best Case Best Case Best Case Best Case Best Case Best Case Best Case Best Case Best Case Best Case Best Case Best Case Best Case Best Case Best Case Best Case Best Case Best Case Best Case Best Case Best Case Best Case Best Case Best Case Best Case Best Case Best Case Best Case Best Case Best Case Best Case Best Case Best Case Best Case
B20: letztes Betriebsjahr | D20: =D18+D19-1 -> 4 | E20: =E18+E19-1 -> 4 | F20: =F18+F19-1 -> 4 | L20: Gekoppelte Preisänder.? | N20: ja (standard) | R20: Periode | S20: 0 | T20: 1 | U20: 2 | V20: 3 | W20: 4 | X20: 5 | Y20: 6 | Z20: 7 | AA20: 8 | AB20: 9 | AC20: 10 | AD20: 11 | AE20: 12 | AF20: 13 | AG20: 14 | AH20: 15 | AI20: 16 | AJ20: 17 | AK20: 18 | AL20: 19 | AM20: 20 | AN20: 21 | AO20: 22 | AP20: 23 | AQ20: 24 | AR20: 25 | AS20: 26 | AT20: 27 | AU20: 28 | AV20: 29 | AW20: 30 | AX20: 31 | AY20: 32 | AZ20: 33 | BA20: 34 | BB20: 35 | BC20: 36 | BD20: 37 | BE20: 38 | BF20: 39 | BG20: 40 | BH20: 41 | BI20: 42 | BJ20: 43 | BK20: 44 | BL20: 45 | BM20: 46 | BN20: 47 | BO20: 48 | BP20: 49 | BQ20: 50 | BR20: 51 | BS20: 52 | BT20: 53 | BV20: Periode | BW20: 0 | BX20: 1 | BY20: 2 | BZ20: 3 | CA20: 4 | CB20: 5 | CC20: 6 | CD20: 7 | CE20: 8 | CF20: 9 | CG20: 10 | CH20: 11 | CI20: 12 | CJ20: 13 | CK20: 14 | CL20: 15 | CM20: 16 | CN20: 17 | CO20: 18 | CP20: 19 | CQ20: 20 | CR20: 21 | CS20: 22 | CT20: 23 | CU20: 24 | CV20: 25 | CW20: 26 | CX20: 27 | CY20: 28 | CZ20: 29 | DA20: 30 | DB20: 31 | DC20: 32 | DD20: 33 | DE20: 34 | DF20: 35 | DG20: 36 | DH20: 37 | DI20: 38 | DJ20: 39 | DK20: 40 | DL20: 41 | DM20: 42 | DN20: 43 | DO20: 44 | DP20: 45 | DQ20: 46 | DR20: 47 | DS20: 48 | DT20: 49 | DU20: 50 | DV20: 51 | DW20: 52 | DX20: 53 | DZ20: Periode | EA20: 0 | EB20: 1 | EC20: 2 | ED20: 3 | EE20: 4 | EF20: 5 | EG20: 6 | EH20: 7 | EI20: 8 | EJ20: 9 | EK20: 10 | EL20: 11 | EM20: 12 | EN20: 13 | EO20: 14 | EP20: 15 | EQ20: 16 | ER20: 17 | ES20: 18 | ET20: 19 | EU20: 20 | EV20: 21 | EW20: 22 | EX20: 23 | EY20: 24 | EZ20: 25 | FA20: 26 | FB20: 27 | FC20: 28 | FD20: 29 | FE20: 30 | FF20: 31 | FG20: 32 | FH20: 33 | FI20: 34 | FJ20: 35 | FK20: 36 | FL20: 37 | FM20: 38 | FN20: 39 | FO20: 40 | FP20: 41 | FQ20: 42 | FR20: 43 | FS20: 44 | FT20: 45 | FU20: 46 | FV20: 47 | FW20: 48 | FX20: 49 | FY20: 50 | FZ20: 51 | GA20: 52 | GB20: 53
G21: 99=>Anfang/Ende Betriebszeit | I21: Degradation | L21: Preisänderung | R21: Berücksichtigung | S21: =IF($E$20>=S20,1,0) -> 1 | T21: =IF($E$20>=T20,1,0) -> 1 | U21: =IF($E$20>=U20,1,0) -> 1 | V21: =IF($E$20>=V20,1,0) -> 1 | W21: =IF($E$20>=W20,1,0) -> 1 | X21: =IF($E$20>=X20,1,0) -> 0 | Y21: =IF($E$20>=Y20,1,0) -> 0 | Z21: =IF($E$20>=Z20,1,0) -> 0 | ... BT21: =IF($E$20>=BT20,1,0) -> 0 | BV21: Berücksichtigung | BW21: =IF($D$20>=BW20,1,0) -> 1 | BX21: =IF($D$20>=BX20,1,0) -> 1 | BY21: =IF($D$20>=BY20,1,0) -> 1 | BZ21: =IF($D$20>=BZ20,1,0) -> 1 | CA21: =IF($D$20>=CA20,1,0) -> 1 | CB21: =IF($D$20>=CB20,1,0) -> 0 | CC21: =IF($D$20>=CC20,1,0) -> 0 | CD21: =IF($D$20>=CD20,1,0) -> 0 | ... DX21: =IF($D$20>=DX20,1,0) -> 0 | DZ21: Berücksichtigung | EA21: =IF($F$20>=EA20,1,0) -> 1 | EB21: =IF($F$20>=EB20,1,0) -> 1 | EC21: =IF($F$20>=EC20,1,0) -> 1 | ED21: =IF($F$20>=ED20,1,0) -> 1 | EE21: =IF($F$20>=EE20,1,0) -> 1 | EF21: =IF($F$20>=EF20,1,0) -> 0 | EG21: =IF($F$20>=EG20,1,0) -> 0 | EH21: =IF($F$20>=EH20,1,0) -> 0 | ... GB21: =IF($F$20>=GB20,1,0) -> 0
D22: Worst Case | E22: Erw. Fall | F22: Best Case | G22: Start - Jahr | H22: End - Jahr | I22: Worst Case | J22: Erw. Fall | K22: Best Case | L22: Worst Case | M22: Erw. Fall | N22: Best Case | R22: Betrieb | S22: =IF(AND(S20>=$E$18,S20<=$E$20),1,0) -> 1 | T22: =IF(AND(T20>=$E$18,T20<=$E$20),1,0) -> 1 | U22: =IF(AND(U20>=$E$18,U20<=$E$20),1,0) -> 1 | V22: =IF(AND(V20>=$E$18,V20<=$E$20),1,0) -> 1 | W22: =IF(AND(W20>=$E$18,W20<=$E$20),1,0) -> 1 | X22: =IF(AND(X20>=$E$18,X20<=$E$20),1,0) -> 0 | Y22: =IF(AND(Y20>=$E$18,Y20<=$E$20),1,0) -> 0 | Z22: =IF(AND(Z20>=$E$18,Z20<=$E$20),1,0) -> 0 | ... BT22: =IF(AND(BT20>=$E$18,BT20<=$E$20),1,0) -> 0 | BV22: Betrieb | BW22: =IF(AND(BW20>=$D$18,BW20<=$D$20),1,0) -> 1 | BX22: =IF(AND(BX20>=$D$18,BX20<=$D$20),1,0) -> 1 | BY22: =IF(AND(BY20>=$D$18,BY20<=$D$20),1,0) -> 1 | BZ22: =IF(AND(BZ20>=$D$18,BZ20<=$D$20),1,0) -> 1 | CA22: =IF(AND(CA20>=$D$18,CA20<=$D$20),1,0) -> 1 | CB22: =IF(AND(CB20>=$D$18,CB20<=$D$20),1,0) -> 0 | CC22: =IF(AND(CC20>=$D$18,CC20<=$D$20),1,0) -> 0 | CD22: =IF(AND(CD20>=$D$18,CD20<=$D$20),1,0) -> 0 | ... DX22: =IF(AND(DX20>=$D$18,DX20<=$D$20),1,0) -> 0 | DZ22: Betrieb | EA22: =IF(AND(EA20>=$F$18,EA20<=$F$20),1,0) -> 1 | EB22: =IF(AND(EB20>=$F$18,EB20<=$F$20),1,0) -> 1 | EC22: =IF(AND(EC20>=$F$18,EC20<=$F$20),1,0) -> 1 | ED22: =IF(AND(ED20>=$F$18,ED20<=$F$20),1,0) -> 1 | EE22: =IF(AND(EE20>=$F$18,EE20<=$F$20),1,0) -> 1 | EF22: =IF(AND(EF20>=$F$18,EF20<=$F$20),1,0) -> 0 | EG22: =IF(AND(EG20>=$F$18,EG20<=$F$20),1,0) -> 0 | EH22: =IF(AND(EH20>=$F$18,EH20<=$F$20),1,0) -> 0 | ... GB22: =IF(AND(GB20>=$F$18,GB20<=$F$20),1,0) -> 0
B23: Nutzen | C23: Einsparung Strom in % | D23: =IF(D11>G11,IFERROR((D11-G11)/D11,0),0) -> 0.2 | E23: =IF(E11>H11,IFERROR((E11-H11)/E11,0),0) -> 0.2 | F23: =IF(F11>I11,IFERROR((F11-I11)/F11,0),0) -> 0.2 | G23: 99 | H23: 99 | I23: =J23*2 -> 0 | J23: 0 | K23: =J23*0.5 -> 0 | L23: ='Allgemeine Unternehmensdaten'!$E$8 -> 0.04 | M23: ='Allgemeine Unternehmensdaten'!$F$8 -> 0.03 | N23: ='Allgemeine Unternehmensdaten'!$G$8 -> 0.02 | R23: Einspaarung Strom EUR | S23: ='Allgemeine Unternehmensdaten'!$F$7*S22*$E11*$E23*($M23+1)^(S20)/((1+$J23)^(S$20)) -> 4360 | T23: ='Allgemeine Unternehmensdaten'!$F$7*T22*$E11*$E23*($M23+1)^(T20)/((1+$J23)^(T$20)) -> 4490.8 | U23: ='Allgemeine Unternehmensdaten'!$F$7*U22*$E11*$E23*($M23+1)^(U20)/((1+$J23)^(U$20)) -> 4625.524 | V23: ='Allgemeine Unternehmensdaten'!$F$7*V22*$E11*$E23*($M23+1)^(V20)/((1+$J23)^(V$20)) -> 4764.2897 | W23: ='Allgemeine Unternehmensdaten'!$F$7*W22*$E11*$E23*($M23+1)^(W20)/((1+$J23)^(W$20)) -> 4907.2184 | X23: ='Allgemeine Unternehmensdaten'!$F$7*X22*$E11*$E23*($M23+1)^(X20)/((1+$J23)^(X$20)) -> 0 | Y23: ='Allgemeine Unternehmensdaten'!$F$7*Y22*$E11*$E23*($M23+1)^(Y20)/((1+$J23)^(Y$20)) -> 0 | Z23: ='Allgemeine Unternehmensdaten'!$F$7*Z22*$E11*$E23*($M23+1)^(Z20)/((1+$J23)^(Z$20)) -> 0 | ... BT23: ='Allgemeine Unternehmensdaten'!$F$7*BT22*$E11*$E23*($M23+1)^(BT20)/((1+$J23)^(BT$20)) -> 0 | BV23: Einspaarung Strom EUR | BW23: ='Allgemeine Unternehmensdaten'!$E$7*BW22*$D11*$D23*($L23+1)^(BW20)/((1+$I23)^(BW$20)) -> 3096 | BX23: ='Allgemeine Unternehmensdaten'!$E$7*BX22*$D11*$D23*($L23+1)^(BX20)/((1+$I23)^(BX$20)) -> 3219.84 | BY23: ='Allgemeine Unternehmensdaten'!$E$7*BY22*$D11*$D23*($L23+1)^(BY20)/((1+$I23)^(BY$20)) -> 3348.6336 | BZ23: ='Allgemeine Unternehmensdaten'!$E$7*BZ22*$D11*$D23*($L23+1)^(BZ20)/((1+$I23)^(BZ$20)) -> 3482.5789 | CA23: ='Allgemeine Unternehmensdaten'!$E$7*CA22*$D11*$D23*($L23+1)^(CA20)/((1+$I23)^(CA$20)) -> 3621.8821 | CB23: ='Allgemeine Unternehmensdaten'!$E$7*CB22*$D11*$D23*($L23+1)^(CB20)/((1+$I23)^(CB$20)) -> 0 | CC23: ='Allgemeine Unternehmensdaten'!$E$7*CC22*$D11*$D23*($L23+1)^(CC20)/((1+$I23)^(CC$20)) -> 0 | CD23: ='Allgemeine Unternehmensdaten'!$E$7*CD22*$D11*$D23*($L23+1)^(CD20)/((1+$I23)^(CD$20)) -> 0 | ... DX23: ='Allgemeine Unternehmensdaten'!$E$7*DX22*$D11*$D23*($L23+1)^(DX20)/((1+$I23)^(DX$20)) -> 0 | DZ23: Einspaarung Strom EUR | EA23: ='Allgemeine Unternehmensdaten'!$G$7*EA22*$F11*$F23*($N23+1)^(EA20)/((1+$K23)^(EA$20)) -> 5500 | EB23: ='Allgemeine Unternehmensdaten'!$G$7*EB22*$F11*$F23*($N23+1)^(EB20)/((1+$K23)^(EB$20)) -> 5610 | EC23: ='Allgemeine Unternehmensdaten'!$G$7*EC22*$F11*$F23*($N23+1)^(EC20)/((1+$K23)^(EC$20)) -> 5722.2 | ED23: ='Allgemeine Unternehmensdaten'!$G$7*ED22*$F11*$F23*($N23+1)^(ED20)/((1+$K23)^(ED$20)) -> 5836.644 | EE23: ='Allgemeine Unternehmensdaten'!$G$7*EE22*$F11*$F23*($N23+1)^(EE20)/((1+$K23)^(EE$20)) -> 5953.3769 | EF23: ='Allgemeine Unternehmensdaten'!$G$7*EF22*$F11*$F23*($N23+1)^(EF20)/((1+$K23)^(EF$20)) -> 0 | EG23: ='Allgemeine Unternehmensdaten'!$G$7*EG22*$F11*$F23*($N23+1)^(EG20)/((1+$K23)^(EG$20)) -> 0 | EH23: ='Allgemeine Unternehmensdaten'!$G$7*EH22*$F11*$F23*($N23+1)^(EH20)/((1+$K23)^(EH$20)) -> 0 | ... GB23: ='Allgemeine Unternehmensdaten'!$G$7*GB22*$F11*$F23*($N23+1)^(GB20)/((1+$K23)^(GB$20)) -> 0
C24: Eigennutzung Strom in kWh/Jahr | G24: 99 | H24: 99 | I24: 0 | J24: 0 | K24: 0 | L24: ='Allgemeine Unternehmensdaten'!E8 -> 0.04 | M24: ='Allgemeine Unternehmensdaten'!F8 -> 0.03 | N24: ='Allgemeine Unternehmensdaten'!G8 -> 0.02 | R24: =$C$24 -> Eigennutzung Strom in kWh/Jahr | S24: =S$22*$E24*'Allgemeine Unternehmensdaten'!$F$37*(1+$M24)^(S$20)/((1+$J24)^(S$20)) -> 0 | T24: =T$22*$E24*'Allgemeine Unternehmensdaten'!$F$37*(1+$M24)^(T$20)/((1+$J24)^(T$20)) -> 0 | U24: =U$22*$E24*'Allgemeine Unternehmensdaten'!$F$37*(1+$M24)^(U$20)/((1+$J24)^(U$20)) -> 0 | V24: =V$22*$E24*'Allgemeine Unternehmensdaten'!$F$37*(1+$M24)^(V$20)/((1+$J24)^(V$20)) -> 0 | W24: =W$22*$E24*'Allgemeine Unternehmensdaten'!$F$37*(1+$M24)^(W$20)/((1+$J24)^(W$20)) -> 0 | X24: =X$22*$E24*'Allgemeine Unternehmensdaten'!$F$37*(1+$M24)^(X$20)/((1+$J24)^(X$20)) -> 0 | Y24: =Y$22*$E24*'Allgemeine Unternehmensdaten'!$F$37*(1+$M24)^(Y$20)/((1+$J24)^(Y$20)) -> 0 | Z24: =Z$22*$E24*'Allgemeine Unternehmensdaten'!$F$37*(1+$M24)^(Z$20)/((1+$J24)^(Z$20)) -> 0 | ... BT24: =BT$22*$E24*'Allgemeine Unternehmensdaten'!$F$37*(1+$M24)^(BT$20)/((1+$J24)^(BT$20)) -> 0 | BV24: =$C$24 -> Eigennutzung Strom in kWh/Jahr | BW24: =BW$22*$D24*'Allgemeine Unternehmensdaten'!$E$37*(1+$L24)^(BW$20)/((1+$I24)^(BW$20)) -> 0 | BX24: =BX$22*$D24*'Allgemeine Unternehmensdaten'!$E$37*(1+$L24)^(BX$20)/((1+$I24)^(BX$20)) -> 0 | BY24: =BY$22*$D24*'Allgemeine Unternehmensdaten'!$E$37*(1+$L24)^(BY$20)/((1+$I24)^(BY$20)) -> 0 | BZ24: =BZ$22*$D24*'Allgemeine Unternehmensdaten'!$E$37*(1+$L24)^(BZ$20)/((1+$I24)^(BZ$20)) -> 0 | CA24: =CA$22*$D24*'Allgemeine Unternehmensdaten'!$E$37*(1+$L24)^(CA$20)/((1+$I24)^(CA$20)) -> 0 | CB24: =CB$22*$D24*'Allgemeine Unternehmensdaten'!$E$37*(1+$L24)^(CB$20)/((1+$I24)^(CB$20)) -> 0 | CC24: =CC$22*$D24*'Allgemeine Unternehmensdaten'!$E$37*(1+$L24)^(CC$20)/((1+$I24)^(CC$20)) -> 0 | CD24: =CD$22*$D24*'Allgemeine Unternehmensdaten'!$E$37*(1+$L24)^(CD$20)/((1+$I24)^(CD$20)) -> 0 | ... DX24: =DX$22*$D24*'Allgemeine Unternehmensdaten'!$E$37*(1+$L24)^(DX$20)/((1+$I24)^(DX$20)) -> 0 | DZ24: =$C$24 -> Eigennutzung Strom in kWh/Jahr | EA24: =EA$22*$F24*'Allgemeine Unternehmensdaten'!$G$37*(1+$N24)^(EA$20)/((1+$K24)^(EA$20)) -> 0 | EB24: =EB$22*$F24*'Allgemeine Unternehmensdaten'!$G$37*(1+$N24)^(EB$20)/((1+$K24)^(EB$20)) -> 0 | EC24: =EC$22*$F24*'Allgemeine Unternehmensdaten'!$G$37*(1+$N24)^(EC$20)/((1+$K24)^(EC$20)) -> 0 | ED24: =ED$22*$F24*'Allgemeine Unternehmensdaten'!$G$37*(1+$N24)^(ED$20)/((1+$K24)^(ED$20)) -> 0 | EE24: =EE$22*$F24*'Allgemeine Unternehmensdaten'!$G$37*(1+$N24)^(EE$20)/((1+$K24)^(EE$20)) -> 0 | EF24: =EF$22*$F24*'Allgemeine Unternehmensdaten'!$G$37*(1+$N24)^(EF$20)/((1+$K24)^(EF$20)) -> 0 | EG24: =EG$22*$F24*'Allgemeine Unternehmensdaten'!$G$37*(1+$N24)^(EG$20)/((1+$K24)^(EG$20)) -> 0 | EH24: =EH$22*$F24*'Allgemeine Unternehmensdaten'!$G$37*(1+$N24)^(EH$20)/((1+$K24)^(EH$20)) -> 0 | ... GB24: =GB$22*$F24*'Allgemeine Unternehmensdaten'!$G$37*(1+$N24)^(GB$20)/((1+$K24)^(GB$20)) -> 0
C25: Einspeisung Strom in kWh/Jahr | G25: 99 | H25: 99 | I25: 0 | J25: 0 | K25: 0 | L25: ='Allgemeine Unternehmensdaten'!G34 -> 0.01 | M25: ='Allgemeine Unternehmensdaten'!F34 -> 0.02 | N25: ='Allgemeine Unternehmensdaten'!E34 -> 0.03 | R25: =$C$25 -> Einspeisung Strom in kWh/Jahr | S25: =S$22*$E25*'Allgemeine Unternehmensdaten'!$F$33*(1+$M25)^(S$20)/((1+$J25)^(S$20)) -> 0 | T25: =T$22*$E25*'Allgemeine Unternehmensdaten'!$F$33*(1+$M25)^(T$20)/((1+$J25)^(T$20)) -> 0 | U25: =U$22*$E25*'Allgemeine Unternehmensdaten'!$F$33*(1+$M25)^(U$20)/((1+$J25)^(U$20)) -> 0 | V25: =V$22*$E25*'Allgemeine Unternehmensdaten'!$F$33*(1+$M25)^(V$20)/((1+$J25)^(V$20)) -> 0 | W25: =W$22*$E25*'Allgemeine Unternehmensdaten'!$F$33*(1+$M25)^(W$20)/((1+$J25)^(W$20)) -> 0 | X25: =X$22*$E25*'Allgemeine Unternehmensdaten'!$F$33*(1+$M25)^(X$20)/((1+$J25)^(X$20)) -> 0 | Y25: =Y$22*$E25*'Allgemeine Unternehmensdaten'!$F$33*(1+$M25)^(Y$20)/((1+$J25)^(Y$20)) -> 0 | Z25: =Z$22*$E25*'Allgemeine Unternehmensdaten'!$F$33*(1+$M25)^(Z$20)/((1+$J25)^(Z$20)) -> 0 | ... BT25: =BT$22*$E25*'Allgemeine Unternehmensdaten'!$F$33*(1+$M25)^(BT$20)/((1+$J25)^(BT$20)) -> 0 | BV25: =$C$25 -> Einspeisung Strom in kWh/Jahr | BW25: =BW$22*$D25*'Allgemeine Unternehmensdaten'!$E$33*(1+$L25)^(BW$20)/((1+$I25)^(BW$20)) -> 0 | BX25: =BX$22*$D25*'Allgemeine Unternehmensdaten'!$E$33*(1+$L25)^(BX$20)/((1+$I25)^(BX$20)) -> 0 | BY25: =BY$22*$D25*'Allgemeine Unternehmensdaten'!$E$33*(1+$L25)^(BY$20)/((1+$I25)^(BY$20)) -> 0 | BZ25: =BZ$22*$D25*'Allgemeine Unternehmensdaten'!$E$33*(1+$L25)^(BZ$20)/((1+$I25)^(BZ$20)) -> 0 | CA25: =CA$22*$D25*'Allgemeine Unternehmensdaten'!$E$33*(1+$L25)^(CA$20)/((1+$I25)^(CA$20)) -> 0 | CB25: =CB$22*$D25*'Allgemeine Unternehmensdaten'!$E$33*(1+$L25)^(CB$20)/((1+$I25)^(CB$20)) -> 0 | CC25: =CC$22*$D25*'Allgemeine Unternehmensdaten'!$E$33*(1+$L25)^(CC$20)/((1+$I25)^(CC$20)) -> 0 | CD25: =CD$22*$D25*'Allgemeine Unternehmensdaten'!$E$33*(1+$L25)^(CD$20)/((1+$I25)^(CD$20)) -> 0 | ... DX25: =DX$22*$D25*'Allgemeine Unternehmensdaten'!$E$33*(1+$L25)^(DX$20)/((1+$I25)^(DX$20)) -> 0 | DZ25: =$C$25 -> Einspeisung Strom in kWh/Jahr | EA25: =EA$22*$F25*'Allgemeine Unternehmensdaten'!$G$33*(1+$N25)^(EA$20)/((1+$K25)^(EA$20)) -> 0 | EB25: =EB$22*$F25*'Allgemeine Unternehmensdaten'!$G$33*(1+$N25)^(EB$20)/((1+$K25)^(EB$20)) -> 0 | EC25: =EC$22*$F25*'Allgemeine Unternehmensdaten'!$G$33*(1+$N25)^(EC$20)/((1+$K25)^(EC$20)) -> 0 | ED25: =ED$22*$F25*'Allgemeine Unternehmensdaten'!$G$33*(1+$N25)^(ED$20)/((1+$K25)^(ED$20)) -> 0 | EE25: =EE$22*$F25*'Allgemeine Unternehmensdaten'!$G$33*(1+$N25)^(EE$20)/((1+$K25)^(EE$20)) -> 0 | EF25: =EF$22*$F25*'Allgemeine Unternehmensdaten'!$G$33*(1+$N25)^(EF$20)/((1+$K25)^(EF$20)) -> 0 | EG25: =EG$22*$F25*'Allgemeine Unternehmensdaten'!$G$33*(1+$N25)^(EG$20)/((1+$K25)^(EG$20)) -> 0 | EH25: =EH$22*$F25*'Allgemeine Unternehmensdaten'!$G$33*(1+$N25)^(EH$20)/((1+$K25)^(EH$20)) -> 0 | ... GB25: =GB$22*$F25*'Allgemeine Unternehmensdaten'!$G$33*(1+$N25)^(GB$20)/((1+$K25)^(GB$20)) -> 0
C26: Einsparung Gas in % | D26: =IF(D12>G12,IFERROR((D12-G12)/D12,0),0) -> 0 | E26: =IF(E12>H12,IFERROR((E12-H12)/E12,0),0) -> 0 | F26: =IF(F12>I12,IFERROR((F12-I12)/F12,0),0) -> 0 | G26: 99 | H26: 99 | I26: 0 | J26: 0 | K26: 0 | L26: ='Allgemeine Unternehmensdaten'!$E$14 -> 0.04 | M26: ='Allgemeine Unternehmensdaten'!$F$14 -> 0.03 | N26: ='Allgemeine Unternehmensdaten'!$G$14 -> 0.02 | R26: Einspaarung Gas in Euro | S26: ='Allgemeine Unternehmensdaten'!$F$13*S$22*$E12*$E26*($M26+1)^(S$20)/((1+$J26)^(S$20)) -> 0 | T26: ='Allgemeine Unternehmensdaten'!$F$13*T$22*$E12*$E26*($M26+1)^(T$20)/((1+$J26)^(T$20)) -> 0 | U26: ='Allgemeine Unternehmensdaten'!$F$13*U$22*$E12*$E26*($M26+1)^(U$20)/((1+$J26)^(U$20)) -> 0 | V26: ='Allgemeine Unternehmensdaten'!$F$13*V$22*$E12*$E26*($M26+1)^(V$20)/((1+$J26)^(V$20)) -> 0 | W26: ='Allgemeine Unternehmensdaten'!$F$13*W$22*$E12*$E26*($M26+1)^(W$20)/((1+$J26)^(W$20)) -> 0 | X26: ='Allgemeine Unternehmensdaten'!$F$13*X$22*$E12*$E26*($M26+1)^(X$20)/((1+$J26)^(X$20)) -> 0 | Y26: ='Allgemeine Unternehmensdaten'!$F$13*Y$22*$E12*$E26*($M26+1)^(Y$20)/((1+$J26)^(Y$20)) -> 0 | Z26: ='Allgemeine Unternehmensdaten'!$F$13*Z$22*$E12*$E26*($M26+1)^(Z$20)/((1+$J26)^(Z$20)) -> 0 | ... BT26: ='Allgemeine Unternehmensdaten'!$F$13*BT$22*$E12*$E26*($M26+1)^(BT$20)/((1+$J26)^(BT$20)) -> 0 | BV26: Einspaarung Gas in Euro | BW26: ='Allgemeine Unternehmensdaten'!$E$13*BW$22*$D12*$D26*($L26+1)^(BW$20)/((1+$I26)^(BW$20)) -> 0 | BX26: ='Allgemeine Unternehmensdaten'!$E$13*BX$22*$D12*$D26*($L26+1)^(BX$20)/((1+$I26)^(BX$20)) -> 0 | BY26: ='Allgemeine Unternehmensdaten'!$E$13*BY$22*$D12*$D26*($L26+1)^(BY$20)/((1+$I26)^(BY$20)) -> 0 | BZ26: ='Allgemeine Unternehmensdaten'!$E$13*BZ$22*$D12*$D26*($L26+1)^(BZ$20)/((1+$I26)^(BZ$20)) -> 0 | CA26: ='Allgemeine Unternehmensdaten'!$E$13*CA$22*$D12*$D26*($L26+1)^(CA$20)/((1+$I26)^(CA$20)) -> 0 | CB26: ='Allgemeine Unternehmensdaten'!$E$13*CB$22*$D12*$D26*($L26+1)^(CB$20)/((1+$I26)^(CB$20)) -> 0 | CC26: ='Allgemeine Unternehmensdaten'!$E$13*CC$22*$D12*$D26*($L26+1)^(CC$20)/((1+$I26)^(CC$20)) -> 0 | CD26: ='Allgemeine Unternehmensdaten'!$E$13*CD$22*$D12*$D26*($L26+1)^(CD$20)/((1+$I26)^(CD$20)) -> 0 | ... DX26: ='Allgemeine Unternehmensdaten'!$E$13*DX$22*$D12*$D26*($L26+1)^(DX$20)/((1+$I26)^(DX$20)) -> 0 | DZ26: Einspaarung Gas in Euro | EA26: ='Allgemeine Unternehmensdaten'!$G$13*EA$22*$F12*$F26*($N26+1)^(EA$20)/((1+$K26)^(EA$20)) -> 0 | EB26: ='Allgemeine Unternehmensdaten'!$G$13*EB$22*$F12*$F26*($N26+1)^(EB$20)/((1+$K26)^(EB$20)) -> 0 | EC26: ='Allgemeine Unternehmensdaten'!$G$13*EC$22*$F12*$F26*($N26+1)^(EC$20)/((1+$K26)^(EC$20)) -> 0 | ED26: ='Allgemeine Unternehmensdaten'!$G$13*ED$22*$F12*$F26*($N26+1)^(ED$20)/((1+$K26)^(ED$20)) -> 0 | EE26: ='Allgemeine Unternehmensdaten'!$G$13*EE$22*$F12*$F26*($N26+1)^(EE$20)/((1+$K26)^(EE$20)) -> 0 | EF26: ='Allgemeine Unternehmensdaten'!$G$13*EF$22*$F12*$F26*($N26+1)^(EF$20)/((1+$K26)^(EF$20)) -> 0 | EG26: ='Allgemeine Unternehmensdaten'!$G$13*EG$22*$F12*$F26*($N26+1)^(EG$20)/((1+$K26)^(EG$20)) -> 0 | EH26: ='Allgemeine Unternehmensdaten'!$G$13*EH$22*$F12*$F26*($N26+1)^(EH$20)/((1+$K26)^(EH$20)) -> 0 | ... GB26: ='Allgemeine Unternehmensdaten'!$G$13*GB$22*$F12*$F26*($N26+1)^(GB$20)/((1+$K26)^(GB$20)) -> 0
C27: ="Einsparung "&'Allgemeine Unternehmensdaten'!C30&" in %" -> Einsparung Flexibler Kostenfaktor in % | D27: =IF(D13>G13,IFERROR((D13-G13)/D13,0),0) -> 0 | E27: =IF(E13>H13,IFERROR((E13-H13)/E13,0),0) -> 0 | F27: =IF(F13>I13,IFERROR((F13-I13)/F13,0),0) -> 0 | G27: 99 | H27: 99 | I27: 0 | J27: 0 | K27: 0 | L27: =L23 -> 0.04 | M27: =M23 -> 0.03 | N27: =N23 -> 0.02 | R27: ="Einspaarung "&'Allgemeine Unternehmensdaten'!C30& "in Euro" -> Einspaarung Flexibler Kostenfaktorin Euro | S27: ='Allgemeine Unternehmensdaten'!$E$30*S$22*$E13*$E27*($M27+1)^(S$20)/((1+$J27)^(S$20)) -> 0 | T27: ='Allgemeine Unternehmensdaten'!$E$30*T$22*$E13*$E27*($M27+1)^(T$20)/((1+$J27)^(T$20)) -> 0 | U27: ='Allgemeine Unternehmensdaten'!$E$30*U$22*$E13*$E27*($M27+1)^(U$20)/((1+$J27)^(U$20)) -> 0 | V27: ='Allgemeine Unternehmensdaten'!$E$30*V$22*$E13*$E27*($M27+1)^(V$20)/((1+$J27)^(V$20)) -> 0 | W27: ='Allgemeine Unternehmensdaten'!$E$30*W$22*$E13*$E27*($M27+1)^(W$20)/((1+$J27)^(W$20)) -> 0 | X27: ='Allgemeine Unternehmensdaten'!$E$30*X$22*$E13*$E27*($M27+1)^(X$20)/((1+$J27)^(X$20)) -> 0 | Y27: ='Allgemeine Unternehmensdaten'!$E$30*Y$22*$E13*$E27*($M27+1)^(Y$20)/((1+$J27)^(Y$20)) -> 0 | Z27: ='Allgemeine Unternehmensdaten'!$E$30*Z$22*$E13*$E27*($M27+1)^(Z$20)/((1+$J27)^(Z$20)) -> 0 | ... BT27: ='Allgemeine Unternehmensdaten'!$E$30*BT$22*$E13*$E27*($M27+1)^(BT$20)/((1+$J27)^(BT$20)) -> 0 | BV27: =R27 -> Einspaarung Flexibler Kostenfaktorin Euro | BW27: ='Allgemeine Unternehmensdaten'!$E$30*BW$22*$D13*$D27*($L27+1)^(BW$20)/((1+$I27)^(BW$20)) -> 0 | BX27: ='Allgemeine Unternehmensdaten'!$E$30*BX$22*$D13*$D27*($L27+1)^(BX$20)/((1+$I27)^(BX$20)) -> 0 | BY27: ='Allgemeine Unternehmensdaten'!$E$30*BY$22*$D13*$D27*($L27+1)^(BY$20)/((1+$I27)^(BY$20)) -> 0 | BZ27: ='Allgemeine Unternehmensdaten'!$E$30*BZ$22*$D13*$D27*($L27+1)^(BZ$20)/((1+$I27)^(BZ$20)) -> 0 | CA27: ='Allgemeine Unternehmensdaten'!$E$30*CA$22*$D13*$D27*($L27+1)^(CA$20)/((1+$I27)^(CA$20)) -> 0 | CB27: ='Allgemeine Unternehmensdaten'!$E$30*CB$22*$D13*$D27*($L27+1)^(CB$20)/((1+$I27)^(CB$20)) -> 0 | CC27: ='Allgemeine Unternehmensdaten'!$E$30*CC$22*$D13*$D27*($L27+1)^(CC$20)/((1+$I27)^(CC$20)) -> 0 | CD27: ='Allgemeine Unternehmensdaten'!$E$30*CD$22*$D13*$D27*($L27+1)^(CD$20)/((1+$I27)^(CD$20)) -> 0 | ... DX27: ='Allgemeine Unternehmensdaten'!$E$30*DX$22*$D13*$D27*($L27+1)^(DX$20)/((1+$I27)^(DX$20)) -> 0 | DZ27: Einspaarung Druckluft in Euro | EA27: ='Allgemeine Unternehmensdaten'!$E$30*EA$22*$F13*$F27*($N27+1)^(EA$20)/((1+$K27)^(EA$20)) -> 0 | EB27: ='Allgemeine Unternehmensdaten'!$E$30*EB$22*$F13*$F27*($N27+1)^(EB$20)/((1+$K27)^(EB$20)) -> 0 | EC27: ='Allgemeine Unternehmensdaten'!$E$30*EC$22*$F13*$F27*($N27+1)^(EC$20)/((1+$K27)^(EC$20)) -> 0 | ED27: ='Allgemeine Unternehmensdaten'!$E$30*ED$22*$F13*$F27*($N27+1)^(ED$20)/((1+$K27)^(ED$20)) -> 0 | EE27: ='Allgemeine Unternehmensdaten'!$E$30*EE$22*$F13*$F27*($N27+1)^(EE$20)/((1+$K27)^(EE$20)) -> 0 | EF27: ='Allgemeine Unternehmensdaten'!$E$30*EF$22*$F13*$F27*($N27+1)^(EF$20)/((1+$K27)^(EF$20)) -> 0 | EG27: ='Allgemeine Unternehmensdaten'!$E$30*EG$22*$F13*$F27*($N27+1)^(EG$20)/((1+$K27)^(EG$20)) -> 0 | EH27: ='Allgemeine Unternehmensdaten'!$E$30*EH$22*$F13*$F27*($N27+1)^(EH$20)/((1+$K27)^(EH$20)) -> 0 | ... GB27: ='Allgemeine Unternehmensdaten'!$E$30*GB$22*$F13*$F27*($N27+1)^(GB$20)/((1+$K27)^(GB$20)) -> 0
C28: Einsparung Arbeitskraft Betrieb in €/Jahr | G28: 99 | H28: 99 | I28: 0 | J28: 0 | K28: 0 | L28: =$D$7 -> 0.02 | M28: =$E$7 -> 0.03 | N28: =$F$7 -> 0.05 | R28: =C28 -> Einsparung Arbeitskraft Betrieb in €/Jahr | S28: =S22*$E$28*($M28+1)^(S20)/(1+$J28)^(S$20) -> 0 | T28: =T22*$E$28*($M28+1)^(T20)/(1+$J28)^(T$20) -> 0 | U28: =U22*$E$28*($M28+1)^(U20)/(1+$J28)^(U$20) -> 0 | V28: =V22*$E$28*($M28+1)^(V20)/(1+$J28)^(V$20) -> 0 | W28: =W22*$E$28*($M28+1)^(W20)/(1+$J28)^(W$20) -> 0 | X28: =X22*$E$28*($M28+1)^(X20)/(1+$J28)^(X$20) -> 0 | Y28: =Y22*$E$28*($M28+1)^(Y20)/(1+$J28)^(Y$20) -> 0 | Z28: =Z22*$E$28*($M28+1)^(Z20)/(1+$J28)^(Z$20) -> 0 | ... BT28: =BT22*$E$28*($M28+1)^(BT20)/(1+$J28)^(BT$20) -> 0 | BV28: =C28 -> Einsparung Arbeitskraft Betrieb in €/Jahr | BW28: =BW22*$D$28*($L28+1)^(BW20)/(1+$I28)^(BW$20) -> 0 | BX28: =BX22*$D$28*($L28+1)^(BX20)/(1+$I28)^(BX$20) -> 0 | BY28: =BY22*$D$28*($L28+1)^(BY20)/(1+$I28)^(BY$20) -> 0 | BZ28: =BZ22*$D$28*($L28+1)^(BZ20)/(1+$I28)^(BZ$20) -> 0 | CA28: =CA22*$D$28*($L28+1)^(CA20)/(1+$I28)^(CA$20) -> 0 | CB28: =CB22*$D$28*($L28+1)^(CB20)/(1+$I28)^(CB$20) -> 0 | CC28: =CC22*$D$28*($L28+1)^(CC20)/(1+$I28)^(CC$20) -> 0 | CD28: =CD22*$D$28*($L28+1)^(CD20)/(1+$I28)^(CD$20) -> 0 | ... DX28: =DX22*$D$28*($L28+1)^(DX20)/(1+$I28)^(DX$20) -> 0 | DZ28: =C28 -> Einsparung Arbeitskraft Betrieb in €/Jahr | EA28: =EA22*$F$28*($N28+1)^(EA20)/(1+$K28)^(EA$20) -> 0 | EB28: =EB22*$F$28*($N28+1)^(EB20)/(1+$K28)^(EB$20) -> 0 | EC28: =EC22*$F$28*($N28+1)^(EC20)/(1+$K28)^(EC$20) -> 0 | ED28: =ED22*$F$28*($N28+1)^(ED20)/(1+$K28)^(ED$20) -> 0 | EE28: =EE22*$F$28*($N28+1)^(EE20)/(1+$K28)^(EE$20) -> 0 | EF28: =EF22*$F$28*($N28+1)^(EF20)/(1+$K28)^(EF$20) -> 0 | EG28: =EG22*$F$28*($N28+1)^(EG20)/(1+$K28)^(EG$20) -> 0 | EH28: =EH22*$F$28*($N28+1)^(EH20)/(1+$K28)^(EH$20) -> 0 | ... GB28: =GB22*$F$28*($N28+1)^(GB20)/(1+$K28)^(GB$20) -> 0
C29: Mehrproduktion in €/Jahr | G29: 99 | H29: 99 | I29: 0 | J29: 0 | K29: 0 | L29: =$D$7 -> 0.02 | M29: =$E$7 -> 0.03 | N29: =$F$7 -> 0.05 | R29: =C29 -> Mehrproduktion in €/Jahr | S29: =S22*$E$29*(1+$M29)^(S20)/(1+$J29)^(S$20) -> 0 | T29: =T22*$E$29*(1+$M29)^(T20)/(1+$J29)^(T$20) -> 0 | U29: =U22*$E$29*(1+$M29)^(U20)/(1+$J29)^(U$20) -> 0 | V29: =V22*$E$29*(1+$M29)^(V20)/(1+$J29)^(V$20) -> 0 | W29: =W22*$E$29*(1+$M29)^(W20)/(1+$J29)^(W$20) -> 0 | X29: =X22*$E$29*(1+$M29)^(X20)/(1+$J29)^(X$20) -> 0 | Y29: =Y22*$E$29*(1+$M29)^(Y20)/(1+$J29)^(Y$20) -> 0 | Z29: =Z22*$E$29*(1+$M29)^(Z20)/(1+$J29)^(Z$20) -> 0 | ... BT29: =BT22*$E$29*(1+$M29)^(BT20)/(1+$J29)^(BT$20) -> 0 | BV29: =C29 -> Mehrproduktion in €/Jahr | BW29: =BW22*$D$29*(1+$L29)^(BW20)/(1+$I29)^(BW$20) -> 0 | BX29: =BX22*$D$29*(1+$L29)^(BX20)/(1+$I29)^(BX$20) -> 0 | BY29: =BY22*$D$29*(1+$L29)^(BY20)/(1+$I29)^(BY$20) -> 0 | BZ29: =BZ22*$D$29*(1+$L29)^(BZ20)/(1+$I29)^(BZ$20) -> 0 | CA29: =CA22*$D$29*(1+$L29)^(CA20)/(1+$I29)^(CA$20) -> 0 | CB29: =CB22*$D$29*(1+$L29)^(CB20)/(1+$I29)^(CB$20) -> 0 | CC29: =CC22*$D$29*(1+$L29)^(CC20)/(1+$I29)^(CC$20) -> 0 | CD29: =CD22*$D$29*(1+$L29)^(CD20)/(1+$I29)^(CD$20) -> 0 | ... DX29: =DX22*$D$29*(1+$L29)^(DX20)/(1+$I29)^(DX$20) -> 0 | DZ29: =C29 -> Mehrproduktion in €/Jahr | EA29: =EA22*$F$29*(1+$N29)^(EA20)/(1+$K29)^(EA$20) -> 0 | EB29: =EB22*$F$29*(1+$N29)^(EB20)/(1+$K29)^(EB$20) -> 0 | EC29: =EC22*$F$29*(1+$N29)^(EC20)/(1+$K29)^(EC$20) -> 0 | ED29: =ED22*$F$29*(1+$N29)^(ED20)/(1+$K29)^(ED$20) -> 0 | EE29: =EE22*$F$29*(1+$N29)^(EE20)/(1+$K29)^(EE$20) -> 0 | EF29: =EF22*$F$29*(1+$N29)^(EF20)/(1+$K29)^(EF$20) -> 0 | EG29: =EG22*$F$29*(1+$N29)^(EG20)/(1+$K29)^(EG$20) -> 0 | EH29: =EH22*$F$29*(1+$N29)^(EH20)/(1+$K29)^(EH$20) -> 0 | ... GB29: =GB22*$F$29*(1+$N29)^(GB20)/(1+$K29)^(GB$20) -> 0
C30: Entsorgung - Gewinn in € (Gewinn heute) | G30: 99 | H30: 99 | I30: 0 | J30: 0 | K30: 0 | L30: =$D$7 -> 0.02 | M30: =$E$7 -> 0.03 | N30: =$F$7 -> 0.05 | R30: =C30 -> Entsorgung - Gewinn in € (Gewinn heute) | S30: =IF(S21+T21=1,$E$30*(1+$M$30)^(S20)/((1+$J30)^(S$20)),0) -> 0 | T30: =IF(T21+U21=1,$E$30*(1+$M$30)^(T20)/((1+$J30)^(T$20)),0) -> 0 | U30: =IF(U21+V21=1,$E$30*(1+$M$30)^(U20)/((1+$J30)^(U$20)),0) -> 0 | V30: =IF(V21+W21=1,$E$30*(1+$M$30)^(V20)/((1+$J30)^(V$20)),0) -> 0 | W30: =IF(W21+X21=1,$E$30*(1+$M$30)^(W20)/((1+$J30)^(W$20)),0) -> 0 | X30: =IF(X21+Y21=1,$E$30*(1+$M$30)^(X20)/((1+$J30)^(X$20)),0) -> 0 | Y30: =IF(Y21+Z21=1,$E$30*(1+$M$30)^(Y20)/((1+$J30)^(Y$20)),0) -> 0 | Z30: =IF(Z21+AA21=1,$E$30*(1+$M$30)^(Z20)/((1+$J30)^(Z$20)),0) -> 0 | ... BT30: =IF(BT21+BU21=1,$E$30*(1+$M$30)^(BT20)/((1+$J30)^(BT$20)),0) -> 0 | BV30: =C30 -> Entsorgung - Gewinn in € (Gewinn heute) | BW30: =IF(BW21+BX21=1,$D$30*(1+$L$30)^(BW20)/((1+$I30)^(BW$20)),0) -> 0 | BX30: =IF(BX21+BY21=1,$D$30*(1+$L$30)^(BX20)/((1+$I30)^(BX$20)),0) -> 0 | BY30: =IF(BY21+BZ21=1,$D$30*(1+$L$30)^(BY20)/((1+$I30)^(BY$20)),0) -> 0 | BZ30: =IF(BZ21+CA21=1,$D$30*(1+$L$30)^(BZ20)/((1+$I30)^(BZ$20)),0) -> 0 | CA30: =IF(CA21+CB21=1,$D$30*(1+$L$30)^(CA20)/((1+$I30)^(CA$20)),0) -> 0 | CB30: =IF(CB21+CC21=1,$D$30*(1+$L$30)^(CB20)/((1+$I30)^(CB$20)),0) -> 0 | CC30: =IF(CC21+CD21=1,$D$30*(1+$L$30)^(CC20)/((1+$I30)^(CC$20)),0) -> 0 | CD30: =IF(CD21+CE21=1,$D$30*(1+$L$30)^(CD20)/((1+$I30)^(CD$20)),0) -> 0 | ... DX30: =IF(DX21+DY21=1,$D$30*(1+$L$30)^(DX20)/((1+$I30)^(DX$20)),0) -> 0 | DZ30: =C30 -> Entsorgung - Gewinn in € (Gewinn heute) | EA30: =IF(EA21+EB21=1,$F$30*(1+$N$30)^(EA20)/((1+$K30)^(EA$20)),0) -> 0 | EB30: =IF(EB21+EC21=1,$F$30*(1+$N$30)^(EB20)/((1+$K30)^(EB$20)),0) -> 0 | EC30: =IF(EC21+ED21=1,$F$30*(1+$N$30)^(EC20)/((1+$K30)^(EC$20)),0) -> 0 | ED30: =IF(ED21+EE21=1,$F$30*(1+$N$30)^(ED20)/((1+$K30)^(ED$20)),0) -> 0 | EE30: =IF(EE21+EF21=1,$F$30*(1+$N$30)^(EE20)/((1+$K30)^(EE$20)),0) -> 0 | EF30: =IF(EF21+EG21=1,$F$30*(1+$N$30)^(EF20)/((1+$K30)^(EF$20)),0) -> 0 | EG30: =IF(EG21+EH21=1,$F$30*(1+$N$30)^(EG20)/((1+$K30)^(EG$20)),0) -> 0 | EH30: =IF(EH21+EI21=1,$F$30*(1+$N$30)^(EH20)/((1+$K30)^(EH$20)),0) -> 0 | ... GB30: =IF(GB21+GC21=1,$F$30*(1+$N$30)^(GB20)/((1+$K30)^(GB$20)),0) -> 0
C31: Einsparung Arbeitskraft in €/Jahr | I31: 0 | J31: 0 | K31: 0 | L31: =$D$7 -> 0.02 | M31: =$E$7 -> 0.03 | N31: =$F$7 -> 0.05 | R31: =C31 -> Einsparung Arbeitskraft in €/Jahr | S31: =IF(AND($G31=99,$H31=99),S$22*$E31*(1+$M31)^(S$20)/((1+$J31)^(S$20)),IF(AND($H31=99,S$20>=$G31,S$20<=$E$20),$E31*(1+$M31)^(S$20)/((1+$J31)^(S$20)),IF(AND($G31=99,S$20<=$H31,S$20>=$E$18),$E31*(1+$M31)^(S$20)/((1+$J31)^(S$20)),IF(AND(S$20<=$H31,S$20>=$G31,$G31<>99,$H31<>99),$E31*(1+$M31)^(S$20)/((1+$J31)^(S$20)),0)))) -> 0 | T31: =IF(AND($G31=99,$H31=99),T$22*$E31*(1+$M31)^(T$20)/((1+$J31)^(T$20)),IF(AND($H31=99,T$20>=$G31,T$20<=$E$20),$E31*(1+$M31)^(T$20)/((1+$J31)^(T$20)),IF(AND($G31=99,T$20<=$H31,T$20>=$E$18),$E31*(1+$M31)^(T$20)/((1+$J31)^(T$20)),IF(AND(T$20<=$H31,T$20>=$G31,$G31<>99,$H31<>99),$E31*(1+$M31)^(T$20)/((1+$J31)^(T$20)),0)))) -> 0 | U31: =IF(AND($G31=99,$H31=99),U$22*$E31*(1+$M31)^(U$20)/((1+$J31)^(U$20)),IF(AND($H31=99,U$20>=$G31,U$20<=$E$20),$E31*(1+$M31)^(U$20)/((1+$J31)^(U$20)),IF(AND($G31=99,U$20<=$H31,U$20>=$E$18),$E31*(1+$M31)^(U$20)/((1+$J31)^(U$20)),IF(AND(U$20<=$H31,U$20>=$G31,$G31<>99,$H31<>99),$E31*(1+$M31)^(U$20)/((1+$J31)^(U$20)),0)))) -> 0 | V31: =IF(AND($G31=99,$H31=99),V$22*$E31*(1+$M31)^(V$20)/((1+$J31)^(V$20)),IF(AND($H31=99,V$20>=$G31,V$20<=$E$20),$E31*(1+$M31)^(V$20)/((1+$J31)^(V$20)),IF(AND($G31=99,V$20<=$H31,V$20>=$E$18),$E31*(1+$M31)^(V$20)/((1+$J31)^(V$20)),IF(AND(V$20<=$H31,V$20>=$G31,$G31<>99,$H31<>99),$E31*(1+$M31)^(V$20)/((1+$J31)^(V$20)),0)))) -> 0 | W31: =IF(AND($G31=99,$H31=99),W$22*$E31*(1+$M31)^(W$20)/((1+$J31)^(W$20)),IF(AND($H31=99,W$20>=$G31,W$20<=$E$20),$E31*(1+$M31)^(W$20)/((1+$J31)^(W$20)),IF(AND($G31=99,W$20<=$H31,W$20>=$E$18),$E31*(1+$M31)^(W$20)/((1+$J31)^(W$20)),IF(AND(W$20<=$H31,W$20>=$G31,$G31<>99,$H31<>99),$E31*(1+$M31)^(W$20)/((1+$J31)^(W$20)),0)))) -> 0 | X31: =IF(AND($G31=99,$H31=99),X$22*$E31*(1+$M31)^(X$20)/((1+$J31)^(X$20)),IF(AND($H31=99,X$20>=$G31,X$20<=$E$20),$E31*(1+$M31)^(X$20)/((1+$J31)^(X$20)),IF(AND($G31=99,X$20<=$H31,X$20>=$E$18),$E31*(1+$M31)^(X$20)/((1+$J31)^(X$20)),IF(AND(X$20<=$H31,X$20>=$G31,$G31<>99,$H31<>99),$E31*(1+$M31)^(X$20)/((1+$J31)^(X$20)),0)))) -> 0 | Y31: =IF(AND($G31=99,$H31=99),Y$22*$E31*(1+$M31)^(Y$20)/((1+$J31)^(Y$20)),IF(AND($H31=99,Y$20>=$G31,Y$20<=$E$20),$E31*(1+$M31)^(Y$20)/((1+$J31)^(Y$20)),IF(AND($G31=99,Y$20<=$H31,Y$20>=$E$18),$E31*(1+$M31)^(Y$20)/((1+$J31)^(Y$20)),IF(AND(Y$20<=$H31,Y$20>=$G31,$G31<>99,$H31<>99),$E31*(1+$M31)^(Y$20)/((1+$J31)^(Y$20)),0)))) -> 0 | Z31: =IF(AND($G31=99,$H31=99),Z$22*$E31*(1+$M31)^(Z$20)/((1+$J31)^(Z$20)),IF(AND($H31=99,Z$20>=$G31,Z$20<=$E$20),$E31*(1+$M31)^(Z$20)/((1+$J31)^(Z$20)),IF(AND($G31=99,Z$20<=$H31,Z$20>=$E$18),$E31*(1+$M31)^(Z$20)/((1+$J31)^(Z$20)),IF(AND(Z$20<=$H31,Z$20>=$G31,$G31<>99,$H31<>99),$E31*(1+$M31)^(Z$20)/((1+$J31)^(Z$20)),0)))) -> 0 | ... BT31: =IF(AND($G31=99,$H31=99),BT$22*$E31*(1+$M31)^(BT$20)/((1+$J31)^(BT$20)),IF(AND($H31=99,BT$20>=$G31,BT$20<=$E$20),$E31*(1+$M31)^(BT$20)/((1+$J31)^(BT$20)),IF(AND($G31=99,BT$20<=$H31,BT$20>=$E$18),$E31*(1+$M31)^(BT$20)/((1+$J31)^(BT$20)),IF(AND(BT$20<=$H31,BT$20>=$G31,$G31<>99,$H31<>99),$E31*(1+$M31)^(BT$20)/((1+$J31)^(BT$20)),0)))) -> 0 | BV31: =C31 -> Einsparung Arbeitskraft in €/Jahr | BW31: =IF(AND($G31=99,$H31=99),BW$22*$D31*(1+$L31)^(BW$20)/((1+$I31)^(BW$20)),IF(AND($H31=99,BW$20>=$G31,BW$20<=$D$20),$D31*(1+$L31)^(BW$20)/((1+$I31)^(BW$20)),IF(AND($G31=99,BW$20<=$H31,BW$20>=$D$18),$D31*(1+$L31)^(BW$20)/((1+$I31)^(BW$20)),IF(AND(BW$20<=$H31,BW$20>=$G31,$G31<>99,$H31<>99),$D31*(1+$L31)^(BW$20)/((1+$I31)^(BW$20)),0)))) -> 0 | BX31: =IF(AND($G31=99,$H31=99),BX$22*$D31*(1+$L31)^(BX$20)/((1+$I31)^(BX$20)),IF(AND($H31=99,BX$20>=$G31,BX$20<=$D$20),$D31*(1+$L31)^(BX$20)/((1+$I31)^(BX$20)),IF(AND($G31=99,BX$20<=$H31,BX$20>=$D$18),$D31*(1+$L31)^(BX$20)/((1+$I31)^(BX$20)),IF(AND(BX$20<=$H31,BX$20>=$G31,$G31<>99,$H31<>99),$D31*(1+$L31)^(BX$20)/((1+$I31)^(BX$20)),0)))) -> 0 | BY31: =IF(AND($G31=99,$H31=99),BY$22*$D31*(1+$L31)^(BY$20)/((1+$I31)^(BY$20)),IF(AND($H31=99,BY$20>=$G31,BY$20<=$D$20),$D31*(1+$L31)^(BY$20)/((1+$I31)^(BY$20)),IF(AND($G31=99,BY$20<=$H31,BY$20>=$D$18),$D31*(1+$L31)^(BY$20)/((1+$I31)^(BY$20)),IF(AND(BY$20<=$H31,BY$20>=$G31,$G31<>99,$H31<>99),$D31*(1+$L31)^(BY$20)/((1+$I31)^(BY$20)),0)))) -> 0 | BZ31: =IF(AND($G31=99,$H31=99),BZ$22*$D31*(1+$L31)^(BZ$20)/((1+$I31)^(BZ$20)),IF(AND($H31=99,BZ$20>=$G31,BZ$20<=$D$20),$D31*(1+$L31)^(BZ$20)/((1+$I31)^(BZ$20)),IF(AND($G31=99,BZ$20<=$H31,BZ$20>=$D$18),$D31*(1+$L31)^(BZ$20)/((1+$I31)^(BZ$20)),IF(AND(BZ$20<=$H31,BZ$20>=$G31,$G31<>99,$H31<>99),$D31*(1+$L31)^(BZ$20)/((1+$I31)^(BZ$20)),0)))) -> 0 | CA31: =IF(AND($G31=99,$H31=99),CA$22*$D31*(1+$L31)^(CA$20)/((1+$I31)^(CA$20)),IF(AND($H31=99,CA$20>=$G31,CA$20<=$D$20),$D31*(1+$L31)^(CA$20)/((1+$I31)^(CA$20)),IF(AND($G31=99,CA$20<=$H31,CA$20>=$D$18),$D31*(1+$L31)^(CA$20)/((1+$I31)^(CA$20)),IF(AND(CA$20<=$H31,CA$20>=$G31,$G31<>99,$H31<>99),$D31*(1+$L31)^(CA$20)/((1+$I31)^(CA$20)),0)))) -> 0 | CB31: =IF(AND($G31=99,$H31=99),CB$22*$D31*(1+$L31)^(CB$20)/((1+$I31)^(CB$20)),IF(AND($H31=99,CB$20>=$G31,CB$20<=$D$20),$D31*(1+$L31)^(CB$20)/((1+$I31)^(CB$20)),IF(AND($G31=99,CB$20<=$H31,CB$20>=$D$18),$D31*(1+$L31)^(CB$20)/((1+$I31)^(CB$20)),IF(AND(CB$20<=$H31,CB$20>=$G31,$G31<>99,$H31<>99),$D31*(1+$L31)^(CB$20)/((1+$I31)^(CB$20)),0)))) -> 0 | CC31: =IF(AND($G31=99,$H31=99),CC$22*$D31*(1+$L31)^(CC$20)/((1+$I31)^(CC$20)),IF(AND($H31=99,CC$20>=$G31,CC$20<=$D$20),$D31*(1+$L31)^(CC$20)/((1+$I31)^(CC$20)),IF(AND($G31=99,CC$20<=$H31,CC$20>=$D$18),$D31*(1+$L31)^(CC$20)/((1+$I31)^(CC$20)),IF(AND(CC$20<=$H31,CC$20>=$G31,$G31<>99,$H31<>99),$D31*(1+$L31)^(CC$20)/((1+$I31)^(CC$20)),0)))) -> 0 | CD31: =IF(AND($G31=99,$H31=99),CD$22*$D31*(1+$L31)^(CD$20)/((1+$I31)^(CD$20)),IF(AND($H31=99,CD$20>=$G31,CD$20<=$D$20),$D31*(1+$L31)^(CD$20)/((1+$I31)^(CD$20)),IF(AND($G31=99,CD$20<=$H31,CD$20>=$D$18),$D31*(1+$L31)^(CD$20)/((1+$I31)^(CD$20)),IF(AND(CD$20<=$H31,CD$20>=$G31,$G31<>99,$H31<>99),$D31*(1+$L31)^(CD$20)/((1+$I31)^(CD$20)),0)))) -> 0 | ... DX31: =IF(AND($G31=99,$H31=99),DX$22*$D31*(1+$L31)^(DX$20)/((1+$I31)^(DX$20)),IF(AND($H31=99,DX$20>=$G31,DX$20<=$D$20),$D31*(1+$L31)^(DX$20)/((1+$I31)^(DX$20)),IF(AND($G31=99,DX$20<=$H31,DX$20>=$D$18),$D31*(1+$L31)^(DX$20)/((1+$I31)^(DX$20)),IF(AND(DX$20<=$H31,DX$20>=$G31,$G31<>99,$H31<>99),$D31*(1+$L31)^(DX$20)/((1+$I31)^(DX$20)),0)))) -> 0 | DZ31: =C31 -> Einsparung Arbeitskraft in €/Jahr | EA31: =IF(AND($G31=99,$H31=99),EA$22*$F31*(1+$N31)^(EA$20)/((1+$K31)^(EA$20)),IF(AND($H31=99,EA$20>=$G31,EA$20<=$F$20),$F31*(1+$N31)^(EA$20)/((1+$K31)^(EA$20)),IF(AND($G31=99,EA$20<=$H31,EA$20>=$F$18),$F31*(1+$N31)^(EA$20)/((1+$K31)^(EA$20)),IF(AND(EA$20<=$H31,EA$20>=$G31,$G31<>99,$H31<>99),$F31*(1+$N31)^(EA$20)/((1+$K31)^(EA$20)),0)))) -> 0 | EB31: =IF(AND($G31=99,$H31=99),EB$22*$F31*(1+$N31)^(EB$20)/((1+$K31)^(EB$20)),IF(AND($H31=99,EB$20>=$G31,EB$20<=$F$20),$F31*(1+$N31)^(EB$20)/((1+$K31)^(EB$20)),IF(AND($G31=99,EB$20<=$H31,EB$20>=$F$18),$F31*(1+$N31)^(EB$20)/((1+$K31)^(EB$20)),IF(AND(EB$20<=$H31,EB$20>=$G31,$G31<>99,$H31<>99),$F31*(1+$N31)^(EB$20)/((1+$K31)^(EB$20)),0)))) -> 0 | EC31: =IF(AND($G31=99,$H31=99),EC$22*$F31*(1+$N31)^(EC$20)/((1+$K31)^(EC$20)),IF(AND($H31=99,EC$20>=$G31,EC$20<=$F$20),$F31*(1+$N31)^(EC$20)/((1+$K31)^(EC$20)),IF(AND($G31=99,EC$20<=$H31,EC$20>=$F$18),$F31*(1+$N31)^(EC$20)/((1+$K31)^(EC$20)),IF(AND(EC$20<=$H31,EC$20>=$G31,$G31<>99,$H31<>99),$F31*(1+$N31)^(EC$20)/((1+$K31)^(EC$20)),0)))) -> 0 | ED31: =IF(AND($G31=99,$H31=99),ED$22*$F31*(1+$N31)^(ED$20)/((1+$K31)^(ED$20)),IF(AND($H31=99,ED$20>=$G31,ED$20<=$F$20),$F31*(1+$N31)^(ED$20)/((1+$K31)^(ED$20)),IF(AND($G31=99,ED$20<=$H31,ED$20>=$F$18),$F31*(1+$N31)^(ED$20)/((1+$K31)^(ED$20)),IF(AND(ED$20<=$H31,ED$20>=$G31,$G31<>99,$H31<>99),$F31*(1+$N31)^(ED$20)/((1+$K31)^(ED$20)),0)))) -> 0 | EE31: =IF(AND($G31=99,$H31=99),EE$22*$F31*(1+$N31)^(EE$20)/((1+$K31)^(EE$20)),IF(AND($H31=99,EE$20>=$G31,EE$20<=$F$20),$F31*(1+$N31)^(EE$20)/((1+$K31)^(EE$20)),IF(AND($G31=99,EE$20<=$H31,EE$20>=$F$18),$F31*(1+$N31)^(EE$20)/((1+$K31)^(EE$20)),IF(AND(EE$20<=$H31,EE$20>=$G31,$G31<>99,$H31<>99),$F31*(1+$N31)^(EE$20)/((1+$K31)^(EE$20)),0)))) -> 0 | EF31: =IF(AND($G31=99,$H31=99),EF$22*$F31*(1+$N31)^(EF$20)/((1+$K31)^(EF$20)),IF(AND($H31=99,EF$20>=$G31,EF$20<=$F$20),$F31*(1+$N31)^(EF$20)/((1+$K31)^(EF$20)),IF(AND($G31=99,EF$20<=$H31,EF$20>=$F$18),$F31*(1+$N31)^(EF$20)/((1+$K31)^(EF$20)),IF(AND(EF$20<=$H31,EF$20>=$G31,$G31<>99,$H31<>99),$F31*(1+$N31)^(EF$20)/((1+$K31)^(EF$20)),0)))) -> 0 | EG31: =IF(AND($G31=99,$H31=99),EG$22*$F31*(1+$N31)^(EG$20)/((1+$K31)^(EG$20)),IF(AND($H31=99,EG$20>=$G31,EG$20<=$F$20),$F31*(1+$N31)^(EG$20)/((1+$K31)^(EG$20)),IF(AND($G31=99,EG$20<=$H31,EG$20>=$F$18),$F31*(1+$N31)^(EG$20)/((1+$K31)^(EG$20)),IF(AND(EG$20<=$H31,EG$20>=$G31,$G31<>99,$H31<>99),$F31*(1+$N31)^(EG$20)/((1+$K31)^(EG$20)),0)))) -> 0 | EH31: =IF(AND($G31=99,$H31=99),EH$22*$F31*(1+$N31)^(EH$20)/((1+$K31)^(EH$20)),IF(AND($H31=99,EH$20>=$G31,EH$20<=$F$20),$F31*(1+$N31)^(EH$20)/((1+$K31)^(EH$20)),IF(AND($G31=99,EH$20<=$H31,EH$20>=$F$18),$F31*(1+$N31)^(EH$20)/((1+$K31)^(EH$20)),IF(AND(EH$20<=$H31,EH$20>=$G31,$G31<>99,$H31<>99),$F31*(1+$N31)^(EH$20)/((1+$K31)^(EH$20)),0)))) -> 0 | ... GB31: =IF(AND($G31=99,$H31=99),GB$22*$F31*(1+$N31)^(GB$20)/((1+$K31)^(GB$20)),IF(AND($H31=99,GB$20>=$G31,GB$20<=$F$20),$F31*(1+$N31)^(GB$20)/((1+$K31)^(GB$20)),IF(AND($G31=99,GB$20<=$H31,GB$20>=$F$18),$F31*(1+$N31)^(GB$20)/((1+$K31)^(GB$20)),IF(AND(GB$20<=$H31,GB$20>=$G31,$G31<>99,$H31<>99),$F31*(1+$N31)^(GB$20)/((1+$K31)^(GB$20)),0)))) -> 0
C32: XX in €/Jahr | I32: 0 | J32: 0 | K32: 0 | L32: =$D$7 -> 0.02 | M32: =$E$7 -> 0.03 | N32: =$F$7 -> 0.05 | R32: =C32 -> XX in €/Jahr | S32: =IF(AND($G32=99,$H32=99),S$22*$E32*(1+$M32)^(S$20)/((1+$J32)^(S$20)),IF(AND($H32=99,S$20>=$G32,S$20<=$E$20),$E32*(1+$M32)^(S$20)/((1+$J32)^(S$20)),IF(AND($G32=99,S$20<=$H32,S$20>=$E$18),$E32*(1+$M32)^(S$20)/((1+$J32)^(S$20)),IF(AND(S$20<=$H32,S$20>=$G32,$G32<>99,$H32<>99),$E32*(1+$M32)^(S$20)/((1+$J32)^(S$20)),0)))) -> 0 | T32: =IF(AND($G32=99,$H32=99),T$22*$E32*(1+$M32)^(T$20)/((1+$J32)^(T$20)),IF(AND($H32=99,T$20>=$G32,T$20<=$E$20),$E32*(1+$M32)^(T$20)/((1+$J32)^(T$20)),IF(AND($G32=99,T$20<=$H32,T$20>=$E$18),$E32*(1+$M32)^(T$20)/((1+$J32)^(T$20)),IF(AND(T$20<=$H32,T$20>=$G32,$G32<>99,$H32<>99),$E32*(1+$M32)^(T$20)/((1+$J32)^(T$20)),0)))) -> 0 | U32: =IF(AND($G32=99,$H32=99),U$22*$E32*(1+$M32)^(U$20)/((1+$J32)^(U$20)),IF(AND($H32=99,U$20>=$G32,U$20<=$E$20),$E32*(1+$M32)^(U$20)/((1+$J32)^(U$20)),IF(AND($G32=99,U$20<=$H32,U$20>=$E$18),$E32*(1+$M32)^(U$20)/((1+$J32)^(U$20)),IF(AND(U$20<=$H32,U$20>=$G32,$G32<>99,$H32<>99),$E32*(1+$M32)^(U$20)/((1+$J32)^(U$20)),0)))) -> 0 | V32: =IF(AND($G32=99,$H32=99),V$22*$E32*(1+$M32)^(V$20)/((1+$J32)^(V$20)),IF(AND($H32=99,V$20>=$G32,V$20<=$E$20),$E32*(1+$M32)^(V$20)/((1+$J32)^(V$20)),IF(AND($G32=99,V$20<=$H32,V$20>=$E$18),$E32*(1+$M32)^(V$20)/((1+$J32)^(V$20)),IF(AND(V$20<=$H32,V$20>=$G32,$G32<>99,$H32<>99),$E32*(1+$M32)^(V$20)/((1+$J32)^(V$20)),0)))) -> 0 | W32: =IF(AND($G32=99,$H32=99),W$22*$E32*(1+$M32)^(W$20)/((1+$J32)^(W$20)),IF(AND($H32=99,W$20>=$G32,W$20<=$E$20),$E32*(1+$M32)^(W$20)/((1+$J32)^(W$20)),IF(AND($G32=99,W$20<=$H32,W$20>=$E$18),$E32*(1+$M32)^(W$20)/((1+$J32)^(W$20)),IF(AND(W$20<=$H32,W$20>=$G32,$G32<>99,$H32<>99),$E32*(1+$M32)^(W$20)/((1+$J32)^(W$20)),0)))) -> 0 | X32: =IF(AND($G32=99,$H32=99),X$22*$E32*(1+$M32)^(X$20)/((1+$J32)^(X$20)),IF(AND($H32=99,X$20>=$G32,X$20<=$E$20),$E32*(1+$M32)^(X$20)/((1+$J32)^(X$20)),IF(AND($G32=99,X$20<=$H32,X$20>=$E$18),$E32*(1+$M32)^(X$20)/((1+$J32)^(X$20)),IF(AND(X$20<=$H32,X$20>=$G32,$G32<>99,$H32<>99),$E32*(1+$M32)^(X$20)/((1+$J32)^(X$20)),0)))) -> 0 | Y32: =IF(AND($G32=99,$H32=99),Y$22*$E32*(1+$M32)^(Y$20)/((1+$J32)^(Y$20)),IF(AND($H32=99,Y$20>=$G32,Y$20<=$E$20),$E32*(1+$M32)^(Y$20)/((1+$J32)^(Y$20)),IF(AND($G32=99,Y$20<=$H32,Y$20>=$E$18),$E32*(1+$M32)^(Y$20)/((1+$J32)^(Y$20)),IF(AND(Y$20<=$H32,Y$20>=$G32,$G32<>99,$H32<>99),$E32*(1+$M32)^(Y$20)/((1+$J32)^(Y$20)),0)))) -> 0 | Z32: =IF(AND($G32=99,$H32=99),Z$22*$E32*(1+$M32)^(Z$20)/((1+$J32)^(Z$20)),IF(AND($H32=99,Z$20>=$G32,Z$20<=$E$20),$E32*(1+$M32)^(Z$20)/((1+$J32)^(Z$20)),IF(AND($G32=99,Z$20<=$H32,Z$20>=$E$18),$E32*(1+$M32)^(Z$20)/((1+$J32)^(Z$20)),IF(AND(Z$20<=$H32,Z$20>=$G32,$G32<>99,$H32<>99),$E32*(1+$M32)^(Z$20)/((1+$J32)^(Z$20)),0)))) -> 0 | ... BT32: =IF(AND($G32=99,$H32=99),BT$22*$E32*(1+$M32)^(BT$20)/((1+$J32)^(BT$20)),IF(AND($H32=99,BT$20>=$G32,BT$20<=$E$20),$E32*(1+$M32)^(BT$20)/((1+$J32)^(BT$20)),IF(AND($G32=99,BT$20<=$H32,BT$20>=$E$18),$E32*(1+$M32)^(BT$20)/((1+$J32)^(BT$20)),IF(AND(BT$20<=$H32,BT$20>=$G32,$G32<>99,$H32<>99),$E32*(1+$M32)^(BT$20)/((1+$J32)^(BT$20)),0)))) -> 0 | BV32: =C32 -> XX in €/Jahr | BW32: =IF(AND($G32=99,$H32=99),BW$22*$D32*(1+$L32)^(BW$20)/((1+$I32)^(BW$20)),IF(AND($H32=99,BW$20>=$G32,BW$20<=$D$20),$D32*(1+$L32)^(BW$20)/((1+$I32)^(BW$20)),IF(AND($G32=99,BW$20<=$H32,BW$20>=$D$18),$D32*(1+$L32)^(BW$20)/((1+$I32)^(BW$20)),IF(AND(BW$20<=$H32,BW$20>=$G32,$G32<>99,$H32<>99),$D32*(1+$L32)^(BW$20)/((1+$I32)^(BW$20)),0)))) -> 0 | BX32: =IF(AND($G32=99,$H32=99),BX$22*$D32*(1+$L32)^(BX$20)/((1+$I32)^(BX$20)),IF(AND($H32=99,BX$20>=$G32,BX$20<=$D$20),$D32*(1+$L32)^(BX$20)/((1+$I32)^(BX$20)),IF(AND($G32=99,BX$20<=$H32,BX$20>=$D$18),$D32*(1+$L32)^(BX$20)/((1+$I32)^(BX$20)),IF(AND(BX$20<=$H32,BX$20>=$G32,$G32<>99,$H32<>99),$D32*(1+$L32)^(BX$20)/((1+$I32)^(BX$20)),0)))) -> 0 | BY32: =IF(AND($G32=99,$H32=99),BY$22*$D32*(1+$L32)^(BY$20)/((1+$I32)^(BY$20)),IF(AND($H32=99,BY$20>=$G32,BY$20<=$D$20),$D32*(1+$L32)^(BY$20)/((1+$I32)^(BY$20)),IF(AND($G32=99,BY$20<=$H32,BY$20>=$D$18),$D32*(1+$L32)^(BY$20)/((1+$I32)^(BY$20)),IF(AND(BY$20<=$H32,BY$20>=$G32,$G32<>99,$H32<>99),$D32*(1+$L32)^(BY$20)/((1+$I32)^(BY$20)),0)))) -> 0 | BZ32: =IF(AND($G32=99,$H32=99),BZ$22*$D32*(1+$L32)^(BZ$20)/((1+$I32)^(BZ$20)),IF(AND($H32=99,BZ$20>=$G32,BZ$20<=$D$20),$D32*(1+$L32)^(BZ$20)/((1+$I32)^(BZ$20)),IF(AND($G32=99,BZ$20<=$H32,BZ$20>=$D$18),$D32*(1+$L32)^(BZ$20)/((1+$I32)^(BZ$20)),IF(AND(BZ$20<=$H32,BZ$20>=$G32,$G32<>99,$H32<>99),$D32*(1+$L32)^(BZ$20)/((1+$I32)^(BZ$20)),0)))) -> 0 | CA32: =IF(AND($G32=99,$H32=99),CA$22*$D32*(1+$L32)^(CA$20)/((1+$I32)^(CA$20)),IF(AND($H32=99,CA$20>=$G32,CA$20<=$D$20),$D32*(1+$L32)^(CA$20)/((1+$I32)^(CA$20)),IF(AND($G32=99,CA$20<=$H32,CA$20>=$D$18),$D32*(1+$L32)^(CA$20)/((1+$I32)^(CA$20)),IF(AND(CA$20<=$H32,CA$20>=$G32,$G32<>99,$H32<>99),$D32*(1+$L32)^(CA$20)/((1+$I32)^(CA$20)),0)))) -> 0 | CB32: =IF(AND($G32=99,$H32=99),CB$22*$D32*(1+$L32)^(CB$20)/((1+$I32)^(CB$20)),IF(AND($H32=99,CB$20>=$G32,CB$20<=$D$20),$D32*(1+$L32)^(CB$20)/((1+$I32)^(CB$20)),IF(AND($G32=99,CB$20<=$H32,CB$20>=$D$18),$D32*(1+$L32)^(CB$20)/((1+$I32)^(CB$20)),IF(AND(CB$20<=$H32,CB$20>=$G32,$G32<>99,$H32<>99),$D32*(1+$L32)^(CB$20)/((1+$I32)^(CB$20)),0)))) -> 0 | CC32: =IF(AND($G32=99,$H32=99),CC$22*$D32*(1+$L32)^(CC$20)/((1+$I32)^(CC$20)),IF(AND($H32=99,CC$20>=$G32,CC$20<=$D$20),$D32*(1+$L32)^(CC$20)/((1+$I32)^(CC$20)),IF(AND($G32=99,CC$20<=$H32,CC$20>=$D$18),$D32*(1+$L32)^(CC$20)/((1+$I32)^(CC$20)),IF(AND(CC$20<=$H32,CC$20>=$G32,$G32<>99,$H32<>99),$D32*(1+$L32)^(CC$20)/((1+$I32)^(CC$20)),0)))) -> 0 | CD32: =IF(AND($G32=99,$H32=99),CD$22*$D32*(1+$L32)^(CD$20)/((1+$I32)^(CD$20)),IF(AND($H32=99,CD$20>=$G32,CD$20<=$D$20),$D32*(1+$L32)^(CD$20)/((1+$I32)^(CD$20)),IF(AND($G32=99,CD$20<=$H32,CD$20>=$D$18),$D32*(1+$L32)^(CD$20)/((1+$I32)^(CD$20)),IF(AND(CD$20<=$H32,CD$20>=$G32,$G32<>99,$H32<>99),$D32*(1+$L32)^(CD$20)/((1+$I32)^(CD$20)),0)))) -> 0 | ... DX32: =IF(AND($G32=99,$H32=99),DX$22*$D32*(1+$L32)^(DX$20)/((1+$I32)^(DX$20)),IF(AND($H32=99,DX$20>=$G32,DX$20<=$D$20),$D32*(1+$L32)^(DX$20)/((1+$I32)^(DX$20)),IF(AND($G32=99,DX$20<=$H32,DX$20>=$D$18),$D32*(1+$L32)^(DX$20)/((1+$I32)^(DX$20)),IF(AND(DX$20<=$H32,DX$20>=$G32,$G32<>99,$H32<>99),$D32*(1+$L32)^(DX$20)/((1+$I32)^(DX$20)),0)))) -> 0 | DZ32: =C32 -> XX in €/Jahr | EA32: =IF(AND($G32=99,$H32=99),EA$22*$F32*(1+$N32)^(EA$20)/((1+$K32)^(EA$20)),IF(AND($H32=99,EA$20>=$G32,EA$20<=$F$20),$F32*(1+$N32)^(EA$20)/((1+$K32)^(EA$20)),IF(AND($G32=99,EA$20<=$H32,EA$20>=$F$18),$F32*(1+$N32)^(EA$20)/((1+$K32)^(EA$20)),IF(AND(EA$20<=$H32,EA$20>=$G32,$G32<>99,$H32<>99),$F32*(1+$N32)^(EA$20)/((1+$K32)^(EA$20)),0)))) -> 0 | EB32: =IF(AND($G32=99,$H32=99),EB$22*$F32*(1+$N32)^(EB$20)/((1+$K32)^(EB$20)),IF(AND($H32=99,EB$20>=$G32,EB$20<=$F$20),$F32*(1+$N32)^(EB$20)/((1+$K32)^(EB$20)),IF(AND($G32=99,EB$20<=$H32,EB$20>=$F$18),$F32*(1+$N32)^(EB$20)/((1+$K32)^(EB$20)),IF(AND(EB$20<=$H32,EB$20>=$G32,$G32<>99,$H32<>99),$F32*(1+$N32)^(EB$20)/((1+$K32)^(EB$20)),0)))) -> 0 | EC32: =IF(AND($G32=99,$H32=99),EC$22*$F32*(1+$N32)^(EC$20)/((1+$K32)^(EC$20)),IF(AND($H32=99,EC$20>=$G32,EC$20<=$F$20),$F32*(1+$N32)^(EC$20)/((1+$K32)^(EC$20)),IF(AND($G32=99,EC$20<=$H32,EC$20>=$F$18),$F32*(1+$N32)^(EC$20)/((1+$K32)^(EC$20)),IF(AND(EC$20<=$H32,EC$20>=$G32,$G32<>99,$H32<>99),$F32*(1+$N32)^(EC$20)/((1+$K32)^(EC$20)),0)))) -> 0 | ED32: =IF(AND($G32=99,$H32=99),ED$22*$F32*(1+$N32)^(ED$20)/((1+$K32)^(ED$20)),IF(AND($H32=99,ED$20>=$G32,ED$20<=$F$20),$F32*(1+$N32)^(ED$20)/((1+$K32)^(ED$20)),IF(AND($G32=99,ED$20<=$H32,ED$20>=$F$18),$F32*(1+$N32)^(ED$20)/((1+$K32)^(ED$20)),IF(AND(ED$20<=$H32,ED$20>=$G32,$G32<>99,$H32<>99),$F32*(1+$N32)^(ED$20)/((1+$K32)^(ED$20)),0)))) -> 0 | EE32: =IF(AND($G32=99,$H32=99),EE$22*$F32*(1+$N32)^(EE$20)/((1+$K32)^(EE$20)),IF(AND($H32=99,EE$20>=$G32,EE$20<=$F$20),$F32*(1+$N32)^(EE$20)/((1+$K32)^(EE$20)),IF(AND($G32=99,EE$20<=$H32,EE$20>=$F$18),$F32*(1+$N32)^(EE$20)/((1+$K32)^(EE$20)),IF(AND(EE$20<=$H32,EE$20>=$G32,$G32<>99,$H32<>99),$F32*(1+$N32)^(EE$20)/((1+$K32)^(EE$20)),0)))) -> 0 | EF32: =IF(AND($G32=99,$H32=99),EF$22*$F32*(1+$N32)^(EF$20)/((1+$K32)^(EF$20)),IF(AND($H32=99,EF$20>=$G32,EF$20<=$F$20),$F32*(1+$N32)^(EF$20)/((1+$K32)^(EF$20)),IF(AND($G32=99,EF$20<=$H32,EF$20>=$F$18),$F32*(1+$N32)^(EF$20)/((1+$K32)^(EF$20)),IF(AND(EF$20<=$H32,EF$20>=$G32,$G32<>99,$H32<>99),$F32*(1+$N32)^(EF$20)/((1+$K32)^(EF$20)),0)))) -> 0 | EG32: =IF(AND($G32=99,$H32=99),EG$22*$F32*(1+$N32)^(EG$20)/((1+$K32)^(EG$20)),IF(AND($H32=99,EG$20>=$G32,EG$20<=$F$20),$F32*(1+$N32)^(EG$20)/((1+$K32)^(EG$20)),IF(AND($G32=99,EG$20<=$H32,EG$20>=$F$18),$F32*(1+$N32)^(EG$20)/((1+$K32)^(EG$20)),IF(AND(EG$20<=$H32,EG$20>=$G32,$G32<>99,$H32<>99),$F32*(1+$N32)^(EG$20)/((1+$K32)^(EG$20)),0)))) -> 0 | EH32: =IF(AND($G32=99,$H32=99),EH$22*$F32*(1+$N32)^(EH$20)/((1+$K32)^(EH$20)),IF(AND($H32=99,EH$20>=$G32,EH$20<=$F$20),$F32*(1+$N32)^(EH$20)/((1+$K32)^(EH$20)),IF(AND($G32=99,EH$20<=$H32,EH$20>=$F$18),$F32*(1+$N32)^(EH$20)/((1+$K32)^(EH$20)),IF(AND(EH$20<=$H32,EH$20>=$G32,$G32<>99,$H32<>99),$F32*(1+$N32)^(EH$20)/((1+$K32)^(EH$20)),0)))) -> 0 | ... GB32: =IF(AND($G32=99,$H32=99),GB$22*$F32*(1+$N32)^(GB$20)/((1+$K32)^(GB$20)),IF(AND($H32=99,GB$20>=$G32,GB$20<=$F$20),$F32*(1+$N32)^(GB$20)/((1+$K32)^(GB$20)),IF(AND($G32=99,GB$20<=$H32,GB$20>=$F$18),$F32*(1+$N32)^(GB$20)/((1+$K32)^(GB$20)),IF(AND(GB$20<=$H32,GB$20>=$G32,$G32<>99,$H32<>99),$F32*(1+$N32)^(GB$20)/((1+$K32)^(GB$20)),0)))) -> 0
C33: XX in €/Jahr | I33: 0 | J33: 0 | K33: 0 | L33: =$D$7 -> 0.02 | M33: =$E$7 -> 0.03 | N33: =$F$7 -> 0.05 | R33: =C33 -> XX in €/Jahr | S33: =IF(AND($G33=99,$H33=99),S$22*$E33*(1+$M33)^(S$20)/((1+$J33)^(S$20)),IF(AND($H33=99,S$20>=$G33,S$20<=$E$20),$E33*(1+$M33)^(S$20)/((1+$J33)^(S$20)),IF(AND($G33=99,S$20<=$H33,S$20>=$E$18),$E33*(1+$M33)^(S$20)/((1+$J33)^(S$20)),IF(AND(S$20<=$H33,S$20>=$G33,$G33<>99,$H33<>99),$E33*(1+$M33)^(S$20)/((1+$J33)^(S$20)),0)))) -> 0 | T33: =IF(AND($G33=99,$H33=99),T$22*$E33*(1+$M33)^(T$20)/((1+$J33)^(T$20)),IF(AND($H33=99,T$20>=$G33,T$20<=$E$20),$E33*(1+$M33)^(T$20)/((1+$J33)^(T$20)),IF(AND($G33=99,T$20<=$H33,T$20>=$E$18),$E33*(1+$M33)^(T$20)/((1+$J33)^(T$20)),IF(AND(T$20<=$H33,T$20>=$G33,$G33<>99,$H33<>99),$E33*(1+$M33)^(T$20)/((1+$J33)^(T$20)),0)))) -> 0 | U33: =IF(AND($G33=99,$H33=99),U$22*$E33*(1+$M33)^(U$20)/((1+$J33)^(U$20)),IF(AND($H33=99,U$20>=$G33,U$20<=$E$20),$E33*(1+$M33)^(U$20)/((1+$J33)^(U$20)),IF(AND($G33=99,U$20<=$H33,U$20>=$E$18),$E33*(1+$M33)^(U$20)/((1+$J33)^(U$20)),IF(AND(U$20<=$H33,U$20>=$G33,$G33<>99,$H33<>99),$E33*(1+$M33)^(U$20)/((1+$J33)^(U$20)),0)))) -> 0 | V33: =IF(AND($G33=99,$H33=99),V$22*$E33*(1+$M33)^(V$20)/((1+$J33)^(V$20)),IF(AND($H33=99,V$20>=$G33,V$20<=$E$20),$E33*(1+$M33)^(V$20)/((1+$J33)^(V$20)),IF(AND($G33=99,V$20<=$H33,V$20>=$E$18),$E33*(1+$M33)^(V$20)/((1+$J33)^(V$20)),IF(AND(V$20<=$H33,V$20>=$G33,$G33<>99,$H33<>99),$E33*(1+$M33)^(V$20)/((1+$J33)^(V$20)),0)))) -> 0 | W33: =IF(AND($G33=99,$H33=99),W$22*$E33*(1+$M33)^(W$20)/((1+$J33)^(W$20)),IF(AND($H33=99,W$20>=$G33,W$20<=$E$20),$E33*(1+$M33)^(W$20)/((1+$J33)^(W$20)),IF(AND($G33=99,W$20<=$H33,W$20>=$E$18),$E33*(1+$M33)^(W$20)/((1+$J33)^(W$20)),IF(AND(W$20<=$H33,W$20>=$G33,$G33<>99,$H33<>99),$E33*(1+$M33)^(W$20)/((1+$J33)^(W$20)),0)))) -> 0 | X33: =IF(AND($G33=99,$H33=99),X$22*$E33*(1+$M33)^(X$20)/((1+$J33)^(X$20)),IF(AND($H33=99,X$20>=$G33,X$20<=$E$20),$E33*(1+$M33)^(X$20)/((1+$J33)^(X$20)),IF(AND($G33=99,X$20<=$H33,X$20>=$E$18),$E33*(1+$M33)^(X$20)/((1+$J33)^(X$20)),IF(AND(X$20<=$H33,X$20>=$G33,$G33<>99,$H33<>99),$E33*(1+$M33)^(X$20)/((1+$J33)^(X$20)),0)))) -> 0 | Y33: =IF(AND($G33=99,$H33=99),Y$22*$E33*(1+$M33)^(Y$20)/((1+$J33)^(Y$20)),IF(AND($H33=99,Y$20>=$G33,Y$20<=$E$20),$E33*(1+$M33)^(Y$20)/((1+$J33)^(Y$20)),IF(AND($G33=99,Y$20<=$H33,Y$20>=$E$18),$E33*(1+$M33)^(Y$20)/((1+$J33)^(Y$20)),IF(AND(Y$20<=$H33,Y$20>=$G33,$G33<>99,$H33<>99),$E33*(1+$M33)^(Y$20)/((1+$J33)^(Y$20)),0)))) -> 0 | Z33: =IF(AND($G33=99,$H33=99),Z$22*$E33*(1+$M33)^(Z$20)/((1+$J33)^(Z$20)),IF(AND($H33=99,Z$20>=$G33,Z$20<=$E$20),$E33*(1+$M33)^(Z$20)/((1+$J33)^(Z$20)),IF(AND($G33=99,Z$20<=$H33,Z$20>=$E$18),$E33*(1+$M33)^(Z$20)/((1+$J33)^(Z$20)),IF(AND(Z$20<=$H33,Z$20>=$G33,$G33<>99,$H33<>99),$E33*(1+$M33)^(Z$20)/((1+$J33)^(Z$20)),0)))) -> 0 | ... BT33: =IF(AND($G33=99,$H33=99),BT$22*$E33*(1+$M33)^(BT$20)/((1+$J33)^(BT$20)),IF(AND($H33=99,BT$20>=$G33,BT$20<=$E$20),$E33*(1+$M33)^(BT$20)/((1+$J33)^(BT$20)),IF(AND($G33=99,BT$20<=$H33,BT$20>=$E$18),$E33*(1+$M33)^(BT$20)/((1+$J33)^(BT$20)),IF(AND(BT$20<=$H33,BT$20>=$G33,$G33<>99,$H33<>99),$E33*(1+$M33)^(BT$20)/((1+$J33)^(BT$20)),0)))) -> 0 | BV33: =C33 -> XX in €/Jahr | BW33: =IF(AND($G33=99,$H33=99),BW$22*$D33*(1+$L33)^(BW$20)/((1+$I33)^(BW$20)),IF(AND($H33=99,BW$20>=$G33,BW$20<=$D$20),$D33*(1+$L33)^(BW$20)/((1+$I33)^(BW$20)),IF(AND($G33=99,BW$20<=$H33,BW$20>=$D$18),$D33*(1+$L33)^(BW$20)/((1+$I33)^(BW$20)),IF(AND(BW$20<=$H33,BW$20>=$G33,$G33<>99,$H33<>99),$D33*(1+$L33)^(BW$20)/((1+$I33)^(BW$20)),0)))) -> 0 | BX33: =IF(AND($G33=99,$H33=99),BX$22*$D33*(1+$L33)^(BX$20)/((1+$I33)^(BX$20)),IF(AND($H33=99,BX$20>=$G33,BX$20<=$D$20),$D33*(1+$L33)^(BX$20)/((1+$I33)^(BX$20)),IF(AND($G33=99,BX$20<=$H33,BX$20>=$D$18),$D33*(1+$L33)^(BX$20)/((1+$I33)^(BX$20)),IF(AND(BX$20<=$H33,BX$20>=$G33,$G33<>99,$H33<>99),$D33*(1+$L33)^(BX$20)/((1+$I33)^(BX$20)),0)))) -> 0 | BY33: =IF(AND($G33=99,$H33=99),BY$22*$D33*(1+$L33)^(BY$20)/((1+$I33)^(BY$20)),IF(AND($H33=99,BY$20>=$G33,BY$20<=$D$20),$D33*(1+$L33)^(BY$20)/((1+$I33)^(BY$20)),IF(AND($G33=99,BY$20<=$H33,BY$20>=$D$18),$D33*(1+$L33)^(BY$20)/((1+$I33)^(BY$20)),IF(AND(BY$20<=$H33,BY$20>=$G33,$G33<>99,$H33<>99),$D33*(1+$L33)^(BY$20)/((1+$I33)^(BY$20)),0)))) -> 0 | BZ33: =IF(AND($G33=99,$H33=99),BZ$22*$D33*(1+$L33)^(BZ$20)/((1+$I33)^(BZ$20)),IF(AND($H33=99,BZ$20>=$G33,BZ$20<=$D$20),$D33*(1+$L33)^(BZ$20)/((1+$I33)^(BZ$20)),IF(AND($G33=99,BZ$20<=$H33,BZ$20>=$D$18),$D33*(1+$L33)^(BZ$20)/((1+$I33)^(BZ$20)),IF(AND(BZ$20<=$H33,BZ$20>=$G33,$G33<>99,$H33<>99),$D33*(1+$L33)^(BZ$20)/((1+$I33)^(BZ$20)),0)))) -> 0 | CA33: =IF(AND($G33=99,$H33=99),CA$22*$D33*(1+$L33)^(CA$20)/((1+$I33)^(CA$20)),IF(AND($H33=99,CA$20>=$G33,CA$20<=$D$20),$D33*(1+$L33)^(CA$20)/((1+$I33)^(CA$20)),IF(AND($G33=99,CA$20<=$H33,CA$20>=$D$18),$D33*(1+$L33)^(CA$20)/((1+$I33)^(CA$20)),IF(AND(CA$20<=$H33,CA$20>=$G33,$G33<>99,$H33<>99),$D33*(1+$L33)^(CA$20)/((1+$I33)^(CA$20)),0)))) -> 0 | CB33: =IF(AND($G33=99,$H33=99),CB$22*$D33*(1+$L33)^(CB$20)/((1+$I33)^(CB$20)),IF(AND($H33=99,CB$20>=$G33,CB$20<=$D$20),$D33*(1+$L33)^(CB$20)/((1+$I33)^(CB$20)),IF(AND($G33=99,CB$20<=$H33,CB$20>=$D$18),$D33*(1+$L33)^(CB$20)/((1+$I33)^(CB$20)),IF(AND(CB$20<=$H33,CB$20>=$G33,$G33<>99,$H33<>99),$D33*(1+$L33)^(CB$20)/((1+$I33)^(CB$20)),0)))) -> 0 | CC33: =IF(AND($G33=99,$H33=99),CC$22*$D33*(1+$L33)^(CC$20)/((1+$I33)^(CC$20)),IF(AND($H33=99,CC$20>=$G33,CC$20<=$D$20),$D33*(1+$L33)^(CC$20)/((1+$I33)^(CC$20)),IF(AND($G33=99,CC$20<=$H33,CC$20>=$D$18),$D33*(1+$L33)^(CC$20)/((1+$I33)^(CC$20)),IF(AND(CC$20<=$H33,CC$20>=$G33,$G33<>99,$H33<>99),$D33*(1+$L33)^(CC$20)/((1+$I33)^(CC$20)),0)))) -> 0 | CD33: =IF(AND($G33=99,$H33=99),CD$22*$D33*(1+$L33)^(CD$20)/((1+$I33)^(CD$20)),IF(AND($H33=99,CD$20>=$G33,CD$20<=$D$20),$D33*(1+$L33)^(CD$20)/((1+$I33)^(CD$20)),IF(AND($G33=99,CD$20<=$H33,CD$20>=$D$18),$D33*(1+$L33)^(CD$20)/((1+$I33)^(CD$20)),IF(AND(CD$20<=$H33,CD$20>=$G33,$G33<>99,$H33<>99),$D33*(1+$L33)^(CD$20)/((1+$I33)^(CD$20)),0)))) -> 0 | ... DX33: =IF(AND($G33=99,$H33=99),DX$22*$D33*(1+$L33)^(DX$20)/((1+$I33)^(DX$20)),IF(AND($H33=99,DX$20>=$G33,DX$20<=$D$20),$D33*(1+$L33)^(DX$20)/((1+$I33)^(DX$20)),IF(AND($G33=99,DX$20<=$H33,DX$20>=$D$18),$D33*(1+$L33)^(DX$20)/((1+$I33)^(DX$20)),IF(AND(DX$20<=$H33,DX$20>=$G33,$G33<>99,$H33<>99),$D33*(1+$L33)^(DX$20)/((1+$I33)^(DX$20)),0)))) -> 0 | DZ33: =C33 -> XX in €/Jahr | EA33: =IF(AND($G33=99,$H33=99),EA$22*$F33*(1+$N33)^(EA$20)/((1+$K33)^(EA$20)),IF(AND($H33=99,EA$20>=$G33,EA$20<=$F$20),$F33*(1+$N33)^(EA$20)/((1+$K33)^(EA$20)),IF(AND($G33=99,EA$20<=$H33,EA$20>=$F$18),$F33*(1+$N33)^(EA$20)/((1+$K33)^(EA$20)),IF(AND(EA$20<=$H33,EA$20>=$G33,$G33<>99,$H33<>99),$F33*(1+$N33)^(EA$20)/((1+$K33)^(EA$20)),0)))) -> 0 | EB33: =IF(AND($G33=99,$H33=99),EB$22*$F33*(1+$N33)^(EB$20)/((1+$K33)^(EB$20)),IF(AND($H33=99,EB$20>=$G33,EB$20<=$F$20),$F33*(1+$N33)^(EB$20)/((1+$K33)^(EB$20)),IF(AND($G33=99,EB$20<=$H33,EB$20>=$F$18),$F33*(1+$N33)^(EB$20)/((1+$K33)^(EB$20)),IF(AND(EB$20<=$H33,EB$20>=$G33,$G33<>99,$H33<>99),$F33*(1+$N33)^(EB$20)/((1+$K33)^(EB$20)),0)))) -> 0 | EC33: =IF(AND($G33=99,$H33=99),EC$22*$F33*(1+$N33)^(EC$20)/((1+$K33)^(EC$20)),IF(AND($H33=99,EC$20>=$G33,EC$20<=$F$20),$F33*(1+$N33)^(EC$20)/((1+$K33)^(EC$20)),IF(AND($G33=99,EC$20<=$H33,EC$20>=$F$18),$F33*(1+$N33)^(EC$20)/((1+$K33)^(EC$20)),IF(AND(EC$20<=$H33,EC$20>=$G33,$G33<>99,$H33<>99),$F33*(1+$N33)^(EC$20)/((1+$K33)^(EC$20)),0)))) -> 0 | ED33: =IF(AND($G33=99,$H33=99),ED$22*$F33*(1+$N33)^(ED$20)/((1+$K33)^(ED$20)),IF(AND($H33=99,ED$20>=$G33,ED$20<=$F$20),$F33*(1+$N33)^(ED$20)/((1+$K33)^(ED$20)),IF(AND($G33=99,ED$20<=$H33,ED$20>=$F$18),$F33*(1+$N33)^(ED$20)/((1+$K33)^(ED$20)),IF(AND(ED$20<=$H33,ED$20>=$G33,$G33<>99,$H33<>99),$F33*(1+$N33)^(ED$20)/((1+$K33)^(ED$20)),0)))) -> 0 | EE33: =IF(AND($G33=99,$H33=99),EE$22*$F33*(1+$N33)^(EE$20)/((1+$K33)^(EE$20)),IF(AND($H33=99,EE$20>=$G33,EE$20<=$F$20),$F33*(1+$N33)^(EE$20)/((1+$K33)^(EE$20)),IF(AND($G33=99,EE$20<=$H33,EE$20>=$F$18),$F33*(1+$N33)^(EE$20)/((1+$K33)^(EE$20)),IF(AND(EE$20<=$H33,EE$20>=$G33,$G33<>99,$H33<>99),$F33*(1+$N33)^(EE$20)/((1+$K33)^(EE$20)),0)))) -> 0 | EF33: =IF(AND($G33=99,$H33=99),EF$22*$F33*(1+$N33)^(EF$20)/((1+$K33)^(EF$20)),IF(AND($H33=99,EF$20>=$G33,EF$20<=$F$20),$F33*(1+$N33)^(EF$20)/((1+$K33)^(EF$20)),IF(AND($G33=99,EF$20<=$H33,EF$20>=$F$18),$F33*(1+$N33)^(EF$20)/((1+$K33)^(EF$20)),IF(AND(EF$20<=$H33,EF$20>=$G33,$G33<>99,$H33<>99),$F33*(1+$N33)^(EF$20)/((1+$K33)^(EF$20)),0)))) -> 0 | EG33: =IF(AND($G33=99,$H33=99),EG$22*$F33*(1+$N33)^(EG$20)/((1+$K33)^(EG$20)),IF(AND($H33=99,EG$20>=$G33,EG$20<=$F$20),$F33*(1+$N33)^(EG$20)/((1+$K33)^(EG$20)),IF(AND($G33=99,EG$20<=$H33,EG$20>=$F$18),$F33*(1+$N33)^(EG$20)/((1+$K33)^(EG$20)),IF(AND(EG$20<=$H33,EG$20>=$G33,$G33<>99,$H33<>99),$F33*(1+$N33)^(EG$20)/((1+$K33)^(EG$20)),0)))) -> 0 | EH33: =IF(AND($G33=99,$H33=99),EH$22*$F33*(1+$N33)^(EH$20)/((1+$K33)^(EH$20)),IF(AND($H33=99,EH$20>=$G33,EH$20<=$F$20),$F33*(1+$N33)^(EH$20)/((1+$K33)^(EH$20)),IF(AND($G33=99,EH$20<=$H33,EH$20>=$F$18),$F33*(1+$N33)^(EH$20)/((1+$K33)^(EH$20)),IF(AND(EH$20<=$H33,EH$20>=$G33,$G33<>99,$H33<>99),$F33*(1+$N33)^(EH$20)/((1+$K33)^(EH$20)),0)))) -> 0 | ... GB33: =IF(AND($G33=99,$H33=99),GB$22*$F33*(1+$N33)^(GB$20)/((1+$K33)^(GB$20)),IF(AND($H33=99,GB$20>=$G33,GB$20<=$F$20),$F33*(1+$N33)^(GB$20)/((1+$K33)^(GB$20)),IF(AND($G33=99,GB$20<=$H33,GB$20>=$F$18),$F33*(1+$N33)^(GB$20)/((1+$K33)^(GB$20)),IF(AND(GB$20<=$H33,GB$20>=$G33,$G33<>99,$H33<>99),$F33*(1+$N33)^(GB$20)/((1+$K33)^(GB$20)),0)))) -> 0
C34: XX in €/Jahr | I34: 0 | J34: 0 | K34: 0 | L34: =$D$7 -> 0.02 | M34: =$E$7 -> 0.03 | N34: =$F$7 -> 0.05 | R34: =C34 -> XX in €/Jahr | S34: =IF(AND($G34=99,$H34=99),S$22*$E34*(1+$M34)^(S$20)/((1+$J34)^(S$20)),IF(AND($H34=99,S$20>=$G34,S$20<=$E$20),$E34*(1+$M34)^(S$20)/((1+$J34)^(S$20)),IF(AND($G34=99,S$20<=$H34,S$20>=$E$18),$E34*(1+$M34)^(S$20)/((1+$J34)^(S$20)),IF(AND(S$20<=$H34,S$20>=$G34,$G34<>99,$H34<>99),$E34*(1+$M34)^(S$20)/((1+$J34)^(S$20)),0)))) -> 0 | T34: =IF(AND($G34=99,$H34=99),T$22*$E34*(1+$M34)^(T$20)/((1+$J34)^(T$20)),IF(AND($H34=99,T$20>=$G34,T$20<=$E$20),$E34*(1+$M34)^(T$20)/((1+$J34)^(T$20)),IF(AND($G34=99,T$20<=$H34,T$20>=$E$18),$E34*(1+$M34)^(T$20)/((1+$J34)^(T$20)),IF(AND(T$20<=$H34,T$20>=$G34,$G34<>99,$H34<>99),$E34*(1+$M34)^(T$20)/((1+$J34)^(T$20)),0)))) -> 0 | U34: =IF(AND($G34=99,$H34=99),U$22*$E34*(1+$M34)^(U$20)/((1+$J34)^(U$20)),IF(AND($H34=99,U$20>=$G34,U$20<=$E$20),$E34*(1+$M34)^(U$20)/((1+$J34)^(U$20)),IF(AND($G34=99,U$20<=$H34,U$20>=$E$18),$E34*(1+$M34)^(U$20)/((1+$J34)^(U$20)),IF(AND(U$20<=$H34,U$20>=$G34,$G34<>99,$H34<>99),$E34*(1+$M34)^(U$20)/((1+$J34)^(U$20)),0)))) -> 0 | V34: =IF(AND($G34=99,$H34=99),V$22*$E34*(1+$M34)^(V$20)/((1+$J34)^(V$20)),IF(AND($H34=99,V$20>=$G34,V$20<=$E$20),$E34*(1+$M34)^(V$20)/((1+$J34)^(V$20)),IF(AND($G34=99,V$20<=$H34,V$20>=$E$18),$E34*(1+$M34)^(V$20)/((1+$J34)^(V$20)),IF(AND(V$20<=$H34,V$20>=$G34,$G34<>99,$H34<>99),$E34*(1+$M34)^(V$20)/((1+$J34)^(V$20)),0)))) -> 0 | W34: =IF(AND($G34=99,$H34=99),W$22*$E34*(1+$M34)^(W$20)/((1+$J34)^(W$20)),IF(AND($H34=99,W$20>=$G34,W$20<=$E$20),$E34*(1+$M34)^(W$20)/((1+$J34)^(W$20)),IF(AND($G34=99,W$20<=$H34,W$20>=$E$18),$E34*(1+$M34)^(W$20)/((1+$J34)^(W$20)),IF(AND(W$20<=$H34,W$20>=$G34,$G34<>99,$H34<>99),$E34*(1+$M34)^(W$20)/((1+$J34)^(W$20)),0)))) -> 0 | X34: =IF(AND($G34=99,$H34=99),X$22*$E34*(1+$M34)^(X$20)/((1+$J34)^(X$20)),IF(AND($H34=99,X$20>=$G34,X$20<=$E$20),$E34*(1+$M34)^(X$20)/((1+$J34)^(X$20)),IF(AND($G34=99,X$20<=$H34,X$20>=$E$18),$E34*(1+$M34)^(X$20)/((1+$J34)^(X$20)),IF(AND(X$20<=$H34,X$20>=$G34,$G34<>99,$H34<>99),$E34*(1+$M34)^(X$20)/((1+$J34)^(X$20)),0)))) -> 0 | Y34: =IF(AND($G34=99,$H34=99),Y$22*$E34*(1+$M34)^(Y$20)/((1+$J34)^(Y$20)),IF(AND($H34=99,Y$20>=$G34,Y$20<=$E$20),$E34*(1+$M34)^(Y$20)/((1+$J34)^(Y$20)),IF(AND($G34=99,Y$20<=$H34,Y$20>=$E$18),$E34*(1+$M34)^(Y$20)/((1+$J34)^(Y$20)),IF(AND(Y$20<=$H34,Y$20>=$G34,$G34<>99,$H34<>99),$E34*(1+$M34)^(Y$20)/((1+$J34)^(Y$20)),0)))) -> 0 | Z34: =IF(AND($G34=99,$H34=99),Z$22*$E34*(1+$M34)^(Z$20)/((1+$J34)^(Z$20)),IF(AND($H34=99,Z$20>=$G34,Z$20<=$E$20),$E34*(1+$M34)^(Z$20)/((1+$J34)^(Z$20)),IF(AND($G34=99,Z$20<=$H34,Z$20>=$E$18),$E34*(1+$M34)^(Z$20)/((1+$J34)^(Z$20)),IF(AND(Z$20<=$H34,Z$20>=$G34,$G34<>99,$H34<>99),$E34*(1+$M34)^(Z$20)/((1+$J34)^(Z$20)),0)))) -> 0 | ... BT34: =IF(AND($G34=99,$H34=99),BT$22*$E34*(1+$M34)^(BT$20)/((1+$J34)^(BT$20)),IF(AND($H34=99,BT$20>=$G34,BT$20<=$E$20),$E34*(1+$M34)^(BT$20)/((1+$J34)^(BT$20)),IF(AND($G34=99,BT$20<=$H34,BT$20>=$E$18),$E34*(1+$M34)^(BT$20)/((1+$J34)^(BT$20)),IF(AND(BT$20<=$H34,BT$20>=$G34,$G34<>99,$H34<>99),$E34*(1+$M34)^(BT$20)/((1+$J34)^(BT$20)),0)))) -> 0 | BV34: =C34 -> XX in €/Jahr | BW34: =IF(AND($G34=99,$H34=99),BW$22*$D34*(1+$L34)^(BW$20)/((1+$I34)^(BW$20)),IF(AND($H34=99,BW$20>=$G34,BW$20<=$D$20),$D34*(1+$L34)^(BW$20)/((1+$I34)^(BW$20)),IF(AND($G34=99,BW$20<=$H34,BW$20>=$D$18),$D34*(1+$L34)^(BW$20)/((1+$I34)^(BW$20)),IF(AND(BW$20<=$H34,BW$20>=$G34,$G34<>99,$H34<>99),$D34*(1+$L34)^(BW$20)/((1+$I34)^(BW$20)),0)))) -> 0 | BX34: =IF(AND($G34=99,$H34=99),BX$22*$D34*(1+$L34)^(BX$20)/((1+$I34)^(BX$20)),IF(AND($H34=99,BX$20>=$G34,BX$20<=$D$20),$D34*(1+$L34)^(BX$20)/((1+$I34)^(BX$20)),IF(AND($G34=99,BX$20<=$H34,BX$20>=$D$18),$D34*(1+$L34)^(BX$20)/((1+$I34)^(BX$20)),IF(AND(BX$20<=$H34,BX$20>=$G34,$G34<>99,$H34<>99),$D34*(1+$L34)^(BX$20)/((1+$I34)^(BX$20)),0)))) -> 0 | BY34: =IF(AND($G34=99,$H34=99),BY$22*$D34*(1+$L34)^(BY$20)/((1+$I34)^(BY$20)),IF(AND($H34=99,BY$20>=$G34,BY$20<=$D$20),$D34*(1+$L34)^(BY$20)/((1+$I34)^(BY$20)),IF(AND($G34=99,BY$20<=$H34,BY$20>=$D$18),$D34*(1+$L34)^(BY$20)/((1+$I34)^(BY$20)),IF(AND(BY$20<=$H34,BY$20>=$G34,$G34<>99,$H34<>99),$D34*(1+$L34)^(BY$20)/((1+$I34)^(BY$20)),0)))) -> 0 | BZ34: =IF(AND($G34=99,$H34=99),BZ$22*$D34*(1+$L34)^(BZ$20)/((1+$I34)^(BZ$20)),IF(AND($H34=99,BZ$20>=$G34,BZ$20<=$D$20),$D34*(1+$L34)^(BZ$20)/((1+$I34)^(BZ$20)),IF(AND($G34=99,BZ$20<=$H34,BZ$20>=$D$18),$D34*(1+$L34)^(BZ$20)/((1+$I34)^(BZ$20)),IF(AND(BZ$20<=$H34,BZ$20>=$G34,$G34<>99,$H34<>99),$D34*(1+$L34)^(BZ$20)/((1+$I34)^(BZ$20)),0)))) -> 0 | CA34: =IF(AND($G34=99,$H34=99),CA$22*$D34*(1+$L34)^(CA$20)/((1+$I34)^(CA$20)),IF(AND($H34=99,CA$20>=$G34,CA$20<=$D$20),$D34*(1+$L34)^(CA$20)/((1+$I34)^(CA$20)),IF(AND($G34=99,CA$20<=$H34,CA$20>=$D$18),$D34*(1+$L34)^(CA$20)/((1+$I34)^(CA$20)),IF(AND(CA$20<=$H34,CA$20>=$G34,$G34<>99,$H34<>99),$D34*(1+$L34)^(CA$20)/((1+$I34)^(CA$20)),0)))) -> 0 | CB34: =IF(AND($G34=99,$H34=99),CB$22*$D34*(1+$L34)^(CB$20)/((1+$I34)^(CB$20)),IF(AND($H34=99,CB$20>=$G34,CB$20<=$D$20),$D34*(1+$L34)^(CB$20)/((1+$I34)^(CB$20)),IF(AND($G34=99,CB$20<=$H34,CB$20>=$D$18),$D34*(1+$L34)^(CB$20)/((1+$I34)^(CB$20)),IF(AND(CB$20<=$H34,CB$20>=$G34,$G34<>99,$H34<>99),$D34*(1+$L34)^(CB$20)/((1+$I34)^(CB$20)),0)))) -> 0 | CC34: =IF(AND($G34=99,$H34=99),CC$22*$D34*(1+$L34)^(CC$20)/((1+$I34)^(CC$20)),IF(AND($H34=99,CC$20>=$G34,CC$20<=$D$20),$D34*(1+$L34)^(CC$20)/((1+$I34)^(CC$20)),IF(AND($G34=99,CC$20<=$H34,CC$20>=$D$18),$D34*(1+$L34)^(CC$20)/((1+$I34)^(CC$20)),IF(AND(CC$20<=$H34,CC$20>=$G34,$G34<>99,$H34<>99),$D34*(1+$L34)^(CC$20)/((1+$I34)^(CC$20)),0)))) -> 0 | CD34: =IF(AND($G34=99,$H34=99),CD$22*$D34*(1+$L34)^(CD$20)/((1+$I34)^(CD$20)),IF(AND($H34=99,CD$20>=$G34,CD$20<=$D$20),$D34*(1+$L34)^(CD$20)/((1+$I34)^(CD$20)),IF(AND($G34=99,CD$20<=$H34,CD$20>=$D$18),$D34*(1+$L34)^(CD$20)/((1+$I34)^(CD$20)),IF(AND(CD$20<=$H34,CD$20>=$G34,$G34<>99,$H34<>99),$D34*(1+$L34)^(CD$20)/((1+$I34)^(CD$20)),0)))) -> 0 | ... DX34: =IF(AND($G34=99,$H34=99),DX$22*$D34*(1+$L34)^(DX$20)/((1+$I34)^(DX$20)),IF(AND($H34=99,DX$20>=$G34,DX$20<=$D$20),$D34*(1+$L34)^(DX$20)/((1+$I34)^(DX$20)),IF(AND($G34=99,DX$20<=$H34,DX$20>=$D$18),$D34*(1+$L34)^(DX$20)/((1+$I34)^(DX$20)),IF(AND(DX$20<=$H34,DX$20>=$G34,$G34<>99,$H34<>99),$D34*(1+$L34)^(DX$20)/((1+$I34)^(DX$20)),0)))) -> 0 | DZ34: =C34 -> XX in €/Jahr | EA34: =IF(AND($G34=99,$H34=99),EA$22*$F34*(1+$N34)^(EA$20)/((1+$K34)^(EA$20)),IF(AND($H34=99,EA$20>=$G34,EA$20<=$F$20),$F34*(1+$N34)^(EA$20)/((1+$K34)^(EA$20)),IF(AND($G34=99,EA$20<=$H34,EA$20>=$F$18),$F34*(1+$N34)^(EA$20)/((1+$K34)^(EA$20)),IF(AND(EA$20<=$H34,EA$20>=$G34,$G34<>99,$H34<>99),$F34*(1+$N34)^(EA$20)/((1+$K34)^(EA$20)),0)))) -> 0 | EB34: =IF(AND($G34=99,$H34=99),EB$22*$F34*(1+$N34)^(EB$20)/((1+$K34)^(EB$20)),IF(AND($H34=99,EB$20>=$G34,EB$20<=$F$20),$F34*(1+$N34)^(EB$20)/((1+$K34)^(EB$20)),IF(AND($G34=99,EB$20<=$H34,EB$20>=$F$18),$F34*(1+$N34)^(EB$20)/((1+$K34)^(EB$20)),IF(AND(EB$20<=$H34,EB$20>=$G34,$G34<>99,$H34<>99),$F34*(1+$N34)^(EB$20)/((1+$K34)^(EB$20)),0)))) -> 0 | EC34: =IF(AND($G34=99,$H34=99),EC$22*$F34*(1+$N34)^(EC$20)/((1+$K34)^(EC$20)),IF(AND($H34=99,EC$20>=$G34,EC$20<=$F$20),$F34*(1+$N34)^(EC$20)/((1+$K34)^(EC$20)),IF(AND($G34=99,EC$20<=$H34,EC$20>=$F$18),$F34*(1+$N34)^(EC$20)/((1+$K34)^(EC$20)),IF(AND(EC$20<=$H34,EC$20>=$G34,$G34<>99,$H34<>99),$F34*(1+$N34)^(EC$20)/((1+$K34)^(EC$20)),0)))) -> 0 | ED34: =IF(AND($G34=99,$H34=99),ED$22*$F34*(1+$N34)^(ED$20)/((1+$K34)^(ED$20)),IF(AND($H34=99,ED$20>=$G34,ED$20<=$F$20),$F34*(1+$N34)^(ED$20)/((1+$K34)^(ED$20)),IF(AND($G34=99,ED$20<=$H34,ED$20>=$F$18),$F34*(1+$N34)^(ED$20)/((1+$K34)^(ED$20)),IF(AND(ED$20<=$H34,ED$20>=$G34,$G34<>99,$H34<>99),$F34*(1+$N34)^(ED$20)/((1+$K34)^(ED$20)),0)))) -> 0 | EE34: =IF(AND($G34=99,$H34=99),EE$22*$F34*(1+$N34)^(EE$20)/((1+$K34)^(EE$20)),IF(AND($H34=99,EE$20>=$G34,EE$20<=$F$20),$F34*(1+$N34)^(EE$20)/((1+$K34)^(EE$20)),IF(AND($G34=99,EE$20<=$H34,EE$20>=$F$18),$F34*(1+$N34)^(EE$20)/((1+$K34)^(EE$20)),IF(AND(EE$20<=$H34,EE$20>=$G34,$G34<>99,$H34<>99),$F34*(1+$N34)^(EE$20)/((1+$K34)^(EE$20)),0)))) -> 0 | EF34: =IF(AND($G34=99,$H34=99),EF$22*$F34*(1+$N34)^(EF$20)/((1+$K34)^(EF$20)),IF(AND($H34=99,EF$20>=$G34,EF$20<=$F$20),$F34*(1+$N34)^(EF$20)/((1+$K34)^(EF$20)),IF(AND($G34=99,EF$20<=$H34,EF$20>=$F$18),$F34*(1+$N34)^(EF$20)/((1+$K34)^(EF$20)),IF(AND(EF$20<=$H34,EF$20>=$G34,$G34<>99,$H34<>99),$F34*(1+$N34)^(EF$20)/((1+$K34)^(EF$20)),0)))) -> 0 | EG34: =IF(AND($G34=99,$H34=99),EG$22*$F34*(1+$N34)^(EG$20)/((1+$K34)^(EG$20)),IF(AND($H34=99,EG$20>=$G34,EG$20<=$F$20),$F34*(1+$N34)^(EG$20)/((1+$K34)^(EG$20)),IF(AND($G34=99,EG$20<=$H34,EG$20>=$F$18),$F34*(1+$N34)^(EG$20)/((1+$K34)^(EG$20)),IF(AND(EG$20<=$H34,EG$20>=$G34,$G34<>99,$H34<>99),$F34*(1+$N34)^(EG$20)/((1+$K34)^(EG$20)),0)))) -> 0 | EH34: =IF(AND($G34=99,$H34=99),EH$22*$F34*(1+$N34)^(EH$20)/((1+$K34)^(EH$20)),IF(AND($H34=99,EH$20>=$G34,EH$20<=$F$20),$F34*(1+$N34)^(EH$20)/((1+$K34)^(EH$20)),IF(AND($G34=99,EH$20<=$H34,EH$20>=$F$18),$F34*(1+$N34)^(EH$20)/((1+$K34)^(EH$20)),IF(AND(EH$20<=$H34,EH$20>=$G34,$G34<>99,$H34<>99),$F34*(1+$N34)^(EH$20)/((1+$K34)^(EH$20)),0)))) -> 0 | ... GB34: =IF(AND($G34=99,$H34=99),GB$22*$F34*(1+$N34)^(GB$20)/((1+$K34)^(GB$20)),IF(AND($H34=99,GB$20>=$G34,GB$20<=$F$20),$F34*(1+$N34)^(GB$20)/((1+$K34)^(GB$20)),IF(AND($G34=99,GB$20<=$H34,GB$20>=$F$18),$F34*(1+$N34)^(GB$20)/((1+$K34)^(GB$20)),IF(AND(GB$20<=$H34,GB$20>=$G34,$G34<>99,$H34<>99),$F34*(1+$N34)^(GB$20)/((1+$K34)^(GB$20)),0)))) -> 0
C35: XX in €/Jahr | I35: 0 | J35: 0 | K35: 0 | L35: =$D$7 -> 0.02 | M35: =$E$7 -> 0.03 | N35: =$F$7 -> 0.05 | R35: =C35 -> XX in €/Jahr | S35: =IF(AND($G35=99,$H35=99),S$22*$E35*(1+$M35)^(S$20)/((1+$J35)^(S$20)),IF(AND($H35=99,S$20>=$G35,S$20<=$E$20),$E35*(1+$M35)^(S$20)/((1+$J35)^(S$20)),IF(AND($G35=99,S$20<=$H35,S$20>=$E$18),$E35*(1+$M35)^(S$20)/((1+$J35)^(S$20)),IF(AND(S$20<=$H35,S$20>=$G35,$G35<>99,$H35<>99),$E35*(1+$M35)^(S$20)/((1+$J35)^(S$20)),0)))) -> 0 | T35: =IF(AND($G35=99,$H35=99),T$22*$E35*(1+$M35)^(T$20)/((1+$J35)^(T$20)),IF(AND($H35=99,T$20>=$G35,T$20<=$E$20),$E35*(1+$M35)^(T$20)/((1+$J35)^(T$20)),IF(AND($G35=99,T$20<=$H35,T$20>=$E$18),$E35*(1+$M35)^(T$20)/((1+$J35)^(T$20)),IF(AND(T$20<=$H35,T$20>=$G35,$G35<>99,$H35<>99),$E35*(1+$M35)^(T$20)/((1+$J35)^(T$20)),0)))) -> 0 | U35: =IF(AND($G35=99,$H35=99),U$22*$E35*(1+$M35)^(U$20)/((1+$J35)^(U$20)),IF(AND($H35=99,U$20>=$G35,U$20<=$E$20),$E35*(1+$M35)^(U$20)/((1+$J35)^(U$20)),IF(AND($G35=99,U$20<=$H35,U$20>=$E$18),$E35*(1+$M35)^(U$20)/((1+$J35)^(U$20)),IF(AND(U$20<=$H35,U$20>=$G35,$G35<>99,$H35<>99),$E35*(1+$M35)^(U$20)/((1+$J35)^(U$20)),0)))) -> 0 | V35: =IF(AND($G35=99,$H35=99),V$22*$E35*(1+$M35)^(V$20)/((1+$J35)^(V$20)),IF(AND($H35=99,V$20>=$G35,V$20<=$E$20),$E35*(1+$M35)^(V$20)/((1+$J35)^(V$20)),IF(AND($G35=99,V$20<=$H35,V$20>=$E$18),$E35*(1+$M35)^(V$20)/((1+$J35)^(V$20)),IF(AND(V$20<=$H35,V$20>=$G35,$G35<>99,$H35<>99),$E35*(1+$M35)^(V$20)/((1+$J35)^(V$20)),0)))) -> 0 | W35: =IF(AND($G35=99,$H35=99),W$22*$E35*(1+$M35)^(W$20)/((1+$J35)^(W$20)),IF(AND($H35=99,W$20>=$G35,W$20<=$E$20),$E35*(1+$M35)^(W$20)/((1+$J35)^(W$20)),IF(AND($G35=99,W$20<=$H35,W$20>=$E$18),$E35*(1+$M35)^(W$20)/((1+$J35)^(W$20)),IF(AND(W$20<=$H35,W$20>=$G35,$G35<>99,$H35<>99),$E35*(1+$M35)^(W$20)/((1+$J35)^(W$20)),0)))) -> 0 | X35: =IF(AND($G35=99,$H35=99),X$22*$E35*(1+$M35)^(X$20)/((1+$J35)^(X$20)),IF(AND($H35=99,X$20>=$G35,X$20<=$E$20),$E35*(1+$M35)^(X$20)/((1+$J35)^(X$20)),IF(AND($G35=99,X$20<=$H35,X$20>=$E$18),$E35*(1+$M35)^(X$20)/((1+$J35)^(X$20)),IF(AND(X$20<=$H35,X$20>=$G35,$G35<>99,$H35<>99),$E35*(1+$M35)^(X$20)/((1+$J35)^(X$20)),0)))) -> 0 | Y35: =IF(AND($G35=99,$H35=99),Y$22*$E35*(1+$M35)^(Y$20)/((1+$J35)^(Y$20)),IF(AND($H35=99,Y$20>=$G35,Y$20<=$E$20),$E35*(1+$M35)^(Y$20)/((1+$J35)^(Y$20)),IF(AND($G35=99,Y$20<=$H35,Y$20>=$E$18),$E35*(1+$M35)^(Y$20)/((1+$J35)^(Y$20)),IF(AND(Y$20<=$H35,Y$20>=$G35,$G35<>99,$H35<>99),$E35*(1+$M35)^(Y$20)/((1+$J35)^(Y$20)),0)))) -> 0 | Z35: =IF(AND($G35=99,$H35=99),Z$22*$E35*(1+$M35)^(Z$20)/((1+$J35)^(Z$20)),IF(AND($H35=99,Z$20>=$G35,Z$20<=$E$20),$E35*(1+$M35)^(Z$20)/((1+$J35)^(Z$20)),IF(AND($G35=99,Z$20<=$H35,Z$20>=$E$18),$E35*(1+$M35)^(Z$20)/((1+$J35)^(Z$20)),IF(AND(Z$20<=$H35,Z$20>=$G35,$G35<>99,$H35<>99),$E35*(1+$M35)^(Z$20)/((1+$J35)^(Z$20)),0)))) -> 0 | ... BT35: =IF(AND($G35=99,$H35=99),BT$22*$E35*(1+$M35)^(BT$20)/((1+$J35)^(BT$20)),IF(AND($H35=99,BT$20>=$G35,BT$20<=$E$20),$E35*(1+$M35)^(BT$20)/((1+$J35)^(BT$20)),IF(AND($G35=99,BT$20<=$H35,BT$20>=$E$18),$E35*(1+$M35)^(BT$20)/((1+$J35)^(BT$20)),IF(AND(BT$20<=$H35,BT$20>=$G35,$G35<>99,$H35<>99),$E35*(1+$M35)^(BT$20)/((1+$J35)^(BT$20)),0)))) -> 0 | BV35: =C35 -> XX in €/Jahr | BW35: =IF(AND($G35=99,$H35=99),BW$22*$D35*(1+$L35)^(BW$20)/((1+$I35)^(BW$20)),IF(AND($H35=99,BW$20>=$G35,BW$20<=$D$20),$D35*(1+$L35)^(BW$20)/((1+$I35)^(BW$20)),IF(AND($G35=99,BW$20<=$H35,BW$20>=$D$18),$D35*(1+$L35)^(BW$20)/((1+$I35)^(BW$20)),IF(AND(BW$20<=$H35,BW$20>=$G35,$G35<>99,$H35<>99),$D35*(1+$L35)^(BW$20)/((1+$I35)^(BW$20)),0)))) -> 0 | BX35: =IF(AND($G35=99,$H35=99),BX$22*$D35*(1+$L35)^(BX$20)/((1+$I35)^(BX$20)),IF(AND($H35=99,BX$20>=$G35,BX$20<=$D$20),$D35*(1+$L35)^(BX$20)/((1+$I35)^(BX$20)),IF(AND($G35=99,BX$20<=$H35,BX$20>=$D$18),$D35*(1+$L35)^(BX$20)/((1+$I35)^(BX$20)),IF(AND(BX$20<=$H35,BX$20>=$G35,$G35<>99,$H35<>99),$D35*(1+$L35)^(BX$20)/((1+$I35)^(BX$20)),0)))) -> 0 | BY35: =IF(AND($G35=99,$H35=99),BY$22*$D35*(1+$L35)^(BY$20)/((1+$I35)^(BY$20)),IF(AND($H35=99,BY$20>=$G35,BY$20<=$D$20),$D35*(1+$L35)^(BY$20)/((1+$I35)^(BY$20)),IF(AND($G35=99,BY$20<=$H35,BY$20>=$D$18),$D35*(1+$L35)^(BY$20)/((1+$I35)^(BY$20)),IF(AND(BY$20<=$H35,BY$20>=$G35,$G35<>99,$H35<>99),$D35*(1+$L35)^(BY$20)/((1+$I35)^(BY$20)),0)))) -> 0 | BZ35: =IF(AND($G35=99,$H35=99),BZ$22*$D35*(1+$L35)^(BZ$20)/((1+$I35)^(BZ$20)),IF(AND($H35=99,BZ$20>=$G35,BZ$20<=$D$20),$D35*(1+$L35)^(BZ$20)/((1+$I35)^(BZ$20)),IF(AND($G35=99,BZ$20<=$H35,BZ$20>=$D$18),$D35*(1+$L35)^(BZ$20)/((1+$I35)^(BZ$20)),IF(AND(BZ$20<=$H35,BZ$20>=$G35,$G35<>99,$H35<>99),$D35*(1+$L35)^(BZ$20)/((1+$I35)^(BZ$20)),0)))) -> 0 | CA35: =IF(AND($G35=99,$H35=99),CA$22*$D35*(1+$L35)^(CA$20)/((1+$I35)^(CA$20)),IF(AND($H35=99,CA$20>=$G35,CA$20<=$D$20),$D35*(1+$L35)^(CA$20)/((1+$I35)^(CA$20)),IF(AND($G35=99,CA$20<=$H35,CA$20>=$D$18),$D35*(1+$L35)^(CA$20)/((1+$I35)^(CA$20)),IF(AND(CA$20<=$H35,CA$20>=$G35,$G35<>99,$H35<>99),$D35*(1+$L35)^(CA$20)/((1+$I35)^(CA$20)),0)))) -> 0 | CB35: =IF(AND($G35=99,$H35=99),CB$22*$D35*(1+$L35)^(CB$20)/((1+$I35)^(CB$20)),IF(AND($H35=99,CB$20>=$G35,CB$20<=$D$20),$D35*(1+$L35)^(CB$20)/((1+$I35)^(CB$20)),IF(AND($G35=99,CB$20<=$H35,CB$20>=$D$18),$D35*(1+$L35)^(CB$20)/((1+$I35)^(CB$20)),IF(AND(CB$20<=$H35,CB$20>=$G35,$G35<>99,$H35<>99),$D35*(1+$L35)^(CB$20)/((1+$I35)^(CB$20)),0)))) -> 0 | CC35: =IF(AND($G35=99,$H35=99),CC$22*$D35*(1+$L35)^(CC$20)/((1+$I35)^(CC$20)),IF(AND($H35=99,CC$20>=$G35,CC$20<=$D$20),$D35*(1+$L35)^(CC$20)/((1+$I35)^(CC$20)),IF(AND($G35=99,CC$20<=$H35,CC$20>=$D$18),$D35*(1+$L35)^(CC$20)/((1+$I35)^(CC$20)),IF(AND(CC$20<=$H35,CC$20>=$G35,$G35<>99,$H35<>99),$D35*(1+$L35)^(CC$20)/((1+$I35)^(CC$20)),0)))) -> 0 | CD35: =IF(AND($G35=99,$H35=99),CD$22*$D35*(1+$L35)^(CD$20)/((1+$I35)^(CD$20)),IF(AND($H35=99,CD$20>=$G35,CD$20<=$D$20),$D35*(1+$L35)^(CD$20)/((1+$I35)^(CD$20)),IF(AND($G35=99,CD$20<=$H35,CD$20>=$D$18),$D35*(1+$L35)^(CD$20)/((1+$I35)^(CD$20)),IF(AND(CD$20<=$H35,CD$20>=$G35,$G35<>99,$H35<>99),$D35*(1+$L35)^(CD$20)/((1+$I35)^(CD$20)),0)))) -> 0 | ... DX35: =IF(AND($G35=99,$H35=99),DX$22*$D35*(1+$L35)^(DX$20)/((1+$I35)^(DX$20)),IF(AND($H35=99,DX$20>=$G35,DX$20<=$D$20),$D35*(1+$L35)^(DX$20)/((1+$I35)^(DX$20)),IF(AND($G35=99,DX$20<=$H35,DX$20>=$D$18),$D35*(1+$L35)^(DX$20)/((1+$I35)^(DX$20)),IF(AND(DX$20<=$H35,DX$20>=$G35,$G35<>99,$H35<>99),$D35*(1+$L35)^(DX$20)/((1+$I35)^(DX$20)),0)))) -> 0 | DZ35: =C35 -> XX in €/Jahr | EA35: =IF(AND($G35=99,$H35=99),EA$22*$F35*(1+$N35)^(EA$20)/((1+$K35)^(EA$20)),IF(AND($H35=99,EA$20>=$G35,EA$20<=$F$20),$F35*(1+$N35)^(EA$20)/((1+$K35)^(EA$20)),IF(AND($G35=99,EA$20<=$H35,EA$20>=$F$18),$F35*(1+$N35)^(EA$20)/((1+$K35)^(EA$20)),IF(AND(EA$20<=$H35,EA$20>=$G35,$G35<>99,$H35<>99),$F35*(1+$N35)^(EA$20)/((1+$K35)^(EA$20)),0)))) -> 0 | EB35: =IF(AND($G35=99,$H35=99),EB$22*$F35*(1+$N35)^(EB$20)/((1+$K35)^(EB$20)),IF(AND($H35=99,EB$20>=$G35,EB$20<=$F$20),$F35*(1+$N35)^(EB$20)/((1+$K35)^(EB$20)),IF(AND($G35=99,EB$20<=$H35,EB$20>=$F$18),$F35*(1+$N35)^(EB$20)/((1+$K35)^(EB$20)),IF(AND(EB$20<=$H35,EB$20>=$G35,$G35<>99,$H35<>99),$F35*(1+$N35)^(EB$20)/((1+$K35)^(EB$20)),0)))) -> 0 | EC35: =IF(AND($G35=99,$H35=99),EC$22*$F35*(1+$N35)^(EC$20)/((1+$K35)^(EC$20)),IF(AND($H35=99,EC$20>=$G35,EC$20<=$F$20),$F35*(1+$N35)^(EC$20)/((1+$K35)^(EC$20)),IF(AND($G35=99,EC$20<=$H35,EC$20>=$F$18),$F35*(1+$N35)^(EC$20)/((1+$K35)^(EC$20)),IF(AND(EC$20<=$H35,EC$20>=$G35,$G35<>99,$H35<>99),$F35*(1+$N35)^(EC$20)/((1+$K35)^(EC$20)),0)))) -> 0 | ED35: =IF(AND($G35=99,$H35=99),ED$22*$F35*(1+$N35)^(ED$20)/((1+$K35)^(ED$20)),IF(AND($H35=99,ED$20>=$G35,ED$20<=$F$20),$F35*(1+$N35)^(ED$20)/((1+$K35)^(ED$20)),IF(AND($G35=99,ED$20<=$H35,ED$20>=$F$18),$F35*(1+$N35)^(ED$20)/((1+$K35)^(ED$20)),IF(AND(ED$20<=$H35,ED$20>=$G35,$G35<>99,$H35<>99),$F35*(1+$N35)^(ED$20)/((1+$K35)^(ED$20)),0)))) -> 0 | EE35: =IF(AND($G35=99,$H35=99),EE$22*$F35*(1+$N35)^(EE$20)/((1+$K35)^(EE$20)),IF(AND($H35=99,EE$20>=$G35,EE$20<=$F$20),$F35*(1+$N35)^(EE$20)/((1+$K35)^(EE$20)),IF(AND($G35=99,EE$20<=$H35,EE$20>=$F$18),$F35*(1+$N35)^(EE$20)/((1+$K35)^(EE$20)),IF(AND(EE$20<=$H35,EE$20>=$G35,$G35<>99,$H35<>99),$F35*(1+$N35)^(EE$20)/((1+$K35)^(EE$20)),0)))) -> 0 | EF35: =IF(AND($G35=99,$H35=99),EF$22*$F35*(1+$N35)^(EF$20)/((1+$K35)^(EF$20)),IF(AND($H35=99,EF$20>=$G35,EF$20<=$F$20),$F35*(1+$N35)^(EF$20)/((1+$K35)^(EF$20)),IF(AND($G35=99,EF$20<=$H35,EF$20>=$F$18),$F35*(1+$N35)^(EF$20)/((1+$K35)^(EF$20)),IF(AND(EF$20<=$H35,EF$20>=$G35,$G35<>99,$H35<>99),$F35*(1+$N35)^(EF$20)/((1+$K35)^(EF$20)),0)))) -> 0 | EG35: =IF(AND($G35=99,$H35=99),EG$22*$F35*(1+$N35)^(EG$20)/((1+$K35)^(EG$20)),IF(AND($H35=99,EG$20>=$G35,EG$20<=$F$20),$F35*(1+$N35)^(EG$20)/((1+$K35)^(EG$20)),IF(AND($G35=99,EG$20<=$H35,EG$20>=$F$18),$F35*(1+$N35)^(EG$20)/((1+$K35)^(EG$20)),IF(AND(EG$20<=$H35,EG$20>=$G35,$G35<>99,$H35<>99),$F35*(1+$N35)^(EG$20)/((1+$K35)^(EG$20)),0)))) -> 0 | EH35: =IF(AND($G35=99,$H35=99),EH$22*$F35*(1+$N35)^(EH$20)/((1+$K35)^(EH$20)),IF(AND($H35=99,EH$20>=$G35,EH$20<=$F$20),$F35*(1+$N35)^(EH$20)/((1+$K35)^(EH$20)),IF(AND($G35=99,EH$20<=$H35,EH$20>=$F$18),$F35*(1+$N35)^(EH$20)/((1+$K35)^(EH$20)),IF(AND(EH$20<=$H35,EH$20>=$G35,$G35<>99,$H35<>99),$F35*(1+$N35)^(EH$20)/((1+$K35)^(EH$20)),0)))) -> 0 | ... GB35: =IF(AND($G35=99,$H35=99),GB$22*$F35*(1+$N35)^(GB$20)/((1+$K35)^(GB$20)),IF(AND($H35=99,GB$20>=$G35,GB$20<=$F$20),$F35*(1+$N35)^(GB$20)/((1+$K35)^(GB$20)),IF(AND($G35=99,GB$20<=$H35,GB$20>=$F$18),$F35*(1+$N35)^(GB$20)/((1+$K35)^(GB$20)),IF(AND(GB$20<=$H35,GB$20>=$G35,$G35<>99,$H35<>99),$F35*(1+$N35)^(GB$20)/((1+$K35)^(GB$20)),0)))) -> 0
C36: XX in €/Jahr | I36: 0 | J36: 0 | K36: 0 | L36: =$D$7 -> 0.02 | M36: =$E$7 -> 0.03 | N36: =$F$7 -> 0.05 | R36: =C36 -> XX in €/Jahr | S36: =IF(AND($G36=99,$H36=99),S$22*$E36*(1+$M36)^(S$20)/((1+$J36)^(S$20)),IF(AND($H36=99,S$20>=$G36,S$20<=$E$20),$E36*(1+$M36)^(S$20)/((1+$J36)^(S$20)),IF(AND($G36=99,S$20<=$H36,S$20>=$E$18),$E36*(1+$M36)^(S$20)/((1+$J36)^(S$20)),IF(AND(S$20<=$H36,S$20>=$G36,$G36<>99,$H36<>99),$E36*(1+$M36)^(S$20)/((1+$J36)^(S$20)),0)))) -> 0 | T36: =IF(AND($G36=99,$H36=99),T$22*$E36*(1+$M36)^(T$20)/((1+$J36)^(T$20)),IF(AND($H36=99,T$20>=$G36,T$20<=$E$20),$E36*(1+$M36)^(T$20)/((1+$J36)^(T$20)),IF(AND($G36=99,T$20<=$H36,T$20>=$E$18),$E36*(1+$M36)^(T$20)/((1+$J36)^(T$20)),IF(AND(T$20<=$H36,T$20>=$G36,$G36<>99,$H36<>99),$E36*(1+$M36)^(T$20)/((1+$J36)^(T$20)),0)))) -> 0 | U36: =IF(AND($G36=99,$H36=99),U$22*$E36*(1+$M36)^(U$20)/((1+$J36)^(U$20)),IF(AND($H36=99,U$20>=$G36,U$20<=$E$20),$E36*(1+$M36)^(U$20)/((1+$J36)^(U$20)),IF(AND($G36=99,U$20<=$H36,U$20>=$E$18),$E36*(1+$M36)^(U$20)/((1+$J36)^(U$20)),IF(AND(U$20<=$H36,U$20>=$G36,$G36<>99,$H36<>99),$E36*(1+$M36)^(U$20)/((1+$J36)^(U$20)),0)))) -> 0 | V36: =IF(AND($G36=99,$H36=99),V$22*$E36*(1+$M36)^(V$20)/((1+$J36)^(V$20)),IF(AND($H36=99,V$20>=$G36,V$20<=$E$20),$E36*(1+$M36)^(V$20)/((1+$J36)^(V$20)),IF(AND($G36=99,V$20<=$H36,V$20>=$E$18),$E36*(1+$M36)^(V$20)/((1+$J36)^(V$20)),IF(AND(V$20<=$H36,V$20>=$G36,$G36<>99,$H36<>99),$E36*(1+$M36)^(V$20)/((1+$J36)^(V$20)),0)))) -> 0 | W36: =IF(AND($G36=99,$H36=99),W$22*$E36*(1+$M36)^(W$20)/((1+$J36)^(W$20)),IF(AND($H36=99,W$20>=$G36,W$20<=$E$20),$E36*(1+$M36)^(W$20)/((1+$J36)^(W$20)),IF(AND($G36=99,W$20<=$H36,W$20>=$E$18),$E36*(1+$M36)^(W$20)/((1+$J36)^(W$20)),IF(AND(W$20<=$H36,W$20>=$G36,$G36<>99,$H36<>99),$E36*(1+$M36)^(W$20)/((1+$J36)^(W$20)),0)))) -> 0 | X36: =IF(AND($G36=99,$H36=99),X$22*$E36*(1+$M36)^(X$20)/((1+$J36)^(X$20)),IF(AND($H36=99,X$20>=$G36,X$20<=$E$20),$E36*(1+$M36)^(X$20)/((1+$J36)^(X$20)),IF(AND($G36=99,X$20<=$H36,X$20>=$E$18),$E36*(1+$M36)^(X$20)/((1+$J36)^(X$20)),IF(AND(X$20<=$H36,X$20>=$G36,$G36<>99,$H36<>99),$E36*(1+$M36)^(X$20)/((1+$J36)^(X$20)),0)))) -> 0 | Y36: =IF(AND($G36=99,$H36=99),Y$22*$E36*(1+$M36)^(Y$20)/((1+$J36)^(Y$20)),IF(AND($H36=99,Y$20>=$G36,Y$20<=$E$20),$E36*(1+$M36)^(Y$20)/((1+$J36)^(Y$20)),IF(AND($G36=99,Y$20<=$H36,Y$20>=$E$18),$E36*(1+$M36)^(Y$20)/((1+$J36)^(Y$20)),IF(AND(Y$20<=$H36,Y$20>=$G36,$G36<>99,$H36<>99),$E36*(1+$M36)^(Y$20)/((1+$J36)^(Y$20)),0)))) -> 0 | Z36: =IF(AND($G36=99,$H36=99),Z$22*$E36*(1+$M36)^(Z$20)/((1+$J36)^(Z$20)),IF(AND($H36=99,Z$20>=$G36,Z$20<=$E$20),$E36*(1+$M36)^(Z$20)/((1+$J36)^(Z$20)),IF(AND($G36=99,Z$20<=$H36,Z$20>=$E$18),$E36*(1+$M36)^(Z$20)/((1+$J36)^(Z$20)),IF(AND(Z$20<=$H36,Z$20>=$G36,$G36<>99,$H36<>99),$E36*(1+$M36)^(Z$20)/((1+$J36)^(Z$20)),0)))) -> 0 | ... BT36: =IF(AND($G36=99,$H36=99),BT$22*$E36*(1+$M36)^(BT$20)/((1+$J36)^(BT$20)),IF(AND($H36=99,BT$20>=$G36,BT$20<=$E$20),$E36*(1+$M36)^(BT$20)/((1+$J36)^(BT$20)),IF(AND($G36=99,BT$20<=$H36,BT$20>=$E$18),$E36*(1+$M36)^(BT$20)/((1+$J36)^(BT$20)),IF(AND(BT$20<=$H36,BT$20>=$G36,$G36<>99,$H36<>99),$E36*(1+$M36)^(BT$20)/((1+$J36)^(BT$20)),0)))) -> 0 | BV36: =C36 -> XX in €/Jahr | BW36: =IF(AND($G36=99,$H36=99),BW$22*$D36*(1+$L36)^(BW$20)/((1+$I36)^(BW$20)),IF(AND($H36=99,BW$20>=$G36,BW$20<=$D$20),$D36*(1+$L36)^(BW$20)/((1+$I36)^(BW$20)),IF(AND($G36=99,BW$20<=$H36,BW$20>=$D$18),$D36*(1+$L36)^(BW$20)/((1+$I36)^(BW$20)),IF(AND(BW$20<=$H36,BW$20>=$G36,$G36<>99,$H36<>99),$D36*(1+$L36)^(BW$20)/((1+$I36)^(BW$20)),0)))) -> 0 | BX36: =IF(AND($G36=99,$H36=99),BX$22*$D36*(1+$L36)^(BX$20)/((1+$I36)^(BX$20)),IF(AND($H36=99,BX$20>=$G36,BX$20<=$D$20),$D36*(1+$L36)^(BX$20)/((1+$I36)^(BX$20)),IF(AND($G36=99,BX$20<=$H36,BX$20>=$D$18),$D36*(1+$L36)^(BX$20)/((1+$I36)^(BX$20)),IF(AND(BX$20<=$H36,BX$20>=$G36,$G36<>99,$H36<>99),$D36*(1+$L36)^(BX$20)/((1+$I36)^(BX$20)),0)))) -> 0 | BY36: =IF(AND($G36=99,$H36=99),BY$22*$D36*(1+$L36)^(BY$20)/((1+$I36)^(BY$20)),IF(AND($H36=99,BY$20>=$G36,BY$20<=$D$20),$D36*(1+$L36)^(BY$20)/((1+$I36)^(BY$20)),IF(AND($G36=99,BY$20<=$H36,BY$20>=$D$18),$D36*(1+$L36)^(BY$20)/((1+$I36)^(BY$20)),IF(AND(BY$20<=$H36,BY$20>=$G36,$G36<>99,$H36<>99),$D36*(1+$L36)^(BY$20)/((1+$I36)^(BY$20)),0)))) -> 0 | BZ36: =IF(AND($G36=99,$H36=99),BZ$22*$D36*(1+$L36)^(BZ$20)/((1+$I36)^(BZ$20)),IF(AND($H36=99,BZ$20>=$G36,BZ$20<=$D$20),$D36*(1+$L36)^(BZ$20)/((1+$I36)^(BZ$20)),IF(AND($G36=99,BZ$20<=$H36,BZ$20>=$D$18),$D36*(1+$L36)^(BZ$20)/((1+$I36)^(BZ$20)),IF(AND(BZ$20<=$H36,BZ$20>=$G36,$G36<>99,$H36<>99),$D36*(1+$L36)^(BZ$20)/((1+$I36)^(BZ$20)),0)))) -> 0 | CA36: =IF(AND($G36=99,$H36=99),CA$22*$D36*(1+$L36)^(CA$20)/((1+$I36)^(CA$20)),IF(AND($H36=99,CA$20>=$G36,CA$20<=$D$20),$D36*(1+$L36)^(CA$20)/((1+$I36)^(CA$20)),IF(AND($G36=99,CA$20<=$H36,CA$20>=$D$18),$D36*(1+$L36)^(CA$20)/((1+$I36)^(CA$20)),IF(AND(CA$20<=$H36,CA$20>=$G36,$G36<>99,$H36<>99),$D36*(1+$L36)^(CA$20)/((1+$I36)^(CA$20)),0)))) -> 0 | CB36: =IF(AND($G36=99,$H36=99),CB$22*$D36*(1+$L36)^(CB$20)/((1+$I36)^(CB$20)),IF(AND($H36=99,CB$20>=$G36,CB$20<=$D$20),$D36*(1+$L36)^(CB$20)/((1+$I36)^(CB$20)),IF(AND($G36=99,CB$20<=$H36,CB$20>=$D$18),$D36*(1+$L36)^(CB$20)/((1+$I36)^(CB$20)),IF(AND(CB$20<=$H36,CB$20>=$G36,$G36<>99,$H36<>99),$D36*(1+$L36)^(CB$20)/((1+$I36)^(CB$20)),0)))) -> 0 | CC36: =IF(AND($G36=99,$H36=99),CC$22*$D36*(1+$L36)^(CC$20)/((1+$I36)^(CC$20)),IF(AND($H36=99,CC$20>=$G36,CC$20<=$D$20),$D36*(1+$L36)^(CC$20)/((1+$I36)^(CC$20)),IF(AND($G36=99,CC$20<=$H36,CC$20>=$D$18),$D36*(1+$L36)^(CC$20)/((1+$I36)^(CC$20)),IF(AND(CC$20<=$H36,CC$20>=$G36,$G36<>99,$H36<>99),$D36*(1+$L36)^(CC$20)/((1+$I36)^(CC$20)),0)))) -> 0 | CD36: =IF(AND($G36=99,$H36=99),CD$22*$D36*(1+$L36)^(CD$20)/((1+$I36)^(CD$20)),IF(AND($H36=99,CD$20>=$G36,CD$20<=$D$20),$D36*(1+$L36)^(CD$20)/((1+$I36)^(CD$20)),IF(AND($G36=99,CD$20<=$H36,CD$20>=$D$18),$D36*(1+$L36)^(CD$20)/((1+$I36)^(CD$20)),IF(AND(CD$20<=$H36,CD$20>=$G36,$G36<>99,$H36<>99),$D36*(1+$L36)^(CD$20)/((1+$I36)^(CD$20)),0)))) -> 0 | ... DX36: =IF(AND($G36=99,$H36=99),DX$22*$D36*(1+$L36)^(DX$20)/((1+$I36)^(DX$20)),IF(AND($H36=99,DX$20>=$G36,DX$20<=$D$20),$D36*(1+$L36)^(DX$20)/((1+$I36)^(DX$20)),IF(AND($G36=99,DX$20<=$H36,DX$20>=$D$18),$D36*(1+$L36)^(DX$20)/((1+$I36)^(DX$20)),IF(AND(DX$20<=$H36,DX$20>=$G36,$G36<>99,$H36<>99),$D36*(1+$L36)^(DX$20)/((1+$I36)^(DX$20)),0)))) -> 0 | DZ36: =C36 -> XX in €/Jahr | EA36: =IF(AND($G36=99,$H36=99),EA$22*$F36*(1+$N36)^(EA$20)/((1+$K36)^(EA$20)),IF(AND($H36=99,EA$20>=$G36,EA$20<=$F$20),$F36*(1+$N36)^(EA$20)/((1+$K36)^(EA$20)),IF(AND($G36=99,EA$20<=$H36,EA$20>=$F$18),$F36*(1+$N36)^(EA$20)/((1+$K36)^(EA$20)),IF(AND(EA$20<=$H36,EA$20>=$G36,$G36<>99,$H36<>99),$F36*(1+$N36)^(EA$20)/((1+$K36)^(EA$20)),0)))) -> 0 | EB36: =IF(AND($G36=99,$H36=99),EB$22*$F36*(1+$N36)^(EB$20)/((1+$K36)^(EB$20)),IF(AND($H36=99,EB$20>=$G36,EB$20<=$F$20),$F36*(1+$N36)^(EB$20)/((1+$K36)^(EB$20)),IF(AND($G36=99,EB$20<=$H36,EB$20>=$F$18),$F36*(1+$N36)^(EB$20)/((1+$K36)^(EB$20)),IF(AND(EB$20<=$H36,EB$20>=$G36,$G36<>99,$H36<>99),$F36*(1+$N36)^(EB$20)/((1+$K36)^(EB$20)),0)))) -> 0 | EC36: =IF(AND($G36=99,$H36=99),EC$22*$F36*(1+$N36)^(EC$20)/((1+$K36)^(EC$20)),IF(AND($H36=99,EC$20>=$G36,EC$20<=$F$20),$F36*(1+$N36)^(EC$20)/((1+$K36)^(EC$20)),IF(AND($G36=99,EC$20<=$H36,EC$20>=$F$18),$F36*(1+$N36)^(EC$20)/((1+$K36)^(EC$20)),IF(AND(EC$20<=$H36,EC$20>=$G36,$G36<>99,$H36<>99),$F36*(1+$N36)^(EC$20)/((1+$K36)^(EC$20)),0)))) -> 0 | ED36: =IF(AND($G36=99,$H36=99),ED$22*$F36*(1+$N36)^(ED$20)/((1+$K36)^(ED$20)),IF(AND($H36=99,ED$20>=$G36,ED$20<=$F$20),$F36*(1+$N36)^(ED$20)/((1+$K36)^(ED$20)),IF(AND($G36=99,ED$20<=$H36,ED$20>=$F$18),$F36*(1+$N36)^(ED$20)/((1+$K36)^(ED$20)),IF(AND(ED$20<=$H36,ED$20>=$G36,$G36<>99,$H36<>99),$F36*(1+$N36)^(ED$20)/((1+$K36)^(ED$20)),0)))) -> 0 | EE36: =IF(AND($G36=99,$H36=99),EE$22*$F36*(1+$N36)^(EE$20)/((1+$K36)^(EE$20)),IF(AND($H36=99,EE$20>=$G36,EE$20<=$F$20),$F36*(1+$N36)^(EE$20)/((1+$K36)^(EE$20)),IF(AND($G36=99,EE$20<=$H36,EE$20>=$F$18),$F36*(1+$N36)^(EE$20)/((1+$K36)^(EE$20)),IF(AND(EE$20<=$H36,EE$20>=$G36,$G36<>99,$H36<>99),$F36*(1+$N36)^(EE$20)/((1+$K36)^(EE$20)),0)))) -> 0 | EF36: =IF(AND($G36=99,$H36=99),EF$22*$F36*(1+$N36)^(EF$20)/((1+$K36)^(EF$20)),IF(AND($H36=99,EF$20>=$G36,EF$20<=$F$20),$F36*(1+$N36)^(EF$20)/((1+$K36)^(EF$20)),IF(AND($G36=99,EF$20<=$H36,EF$20>=$F$18),$F36*(1+$N36)^(EF$20)/((1+$K36)^(EF$20)),IF(AND(EF$20<=$H36,EF$20>=$G36,$G36<>99,$H36<>99),$F36*(1+$N36)^(EF$20)/((1+$K36)^(EF$20)),0)))) -> 0 | EG36: =IF(AND($G36=99,$H36=99),EG$22*$F36*(1+$N36)^(EG$20)/((1+$K36)^(EG$20)),IF(AND($H36=99,EG$20>=$G36,EG$20<=$F$20),$F36*(1+$N36)^(EG$20)/((1+$K36)^(EG$20)),IF(AND($G36=99,EG$20<=$H36,EG$20>=$F$18),$F36*(1+$N36)^(EG$20)/((1+$K36)^(EG$20)),IF(AND(EG$20<=$H36,EG$20>=$G36,$G36<>99,$H36<>99),$F36*(1+$N36)^(EG$20)/((1+$K36)^(EG$20)),0)))) -> 0 | EH36: =IF(AND($G36=99,$H36=99),EH$22*$F36*(1+$N36)^(EH$20)/((1+$K36)^(EH$20)),IF(AND($H36=99,EH$20>=$G36,EH$20<=$F$20),$F36*(1+$N36)^(EH$20)/((1+$K36)^(EH$20)),IF(AND($G36=99,EH$20<=$H36,EH$20>=$F$18),$F36*(1+$N36)^(EH$20)/((1+$K36)^(EH$20)),IF(AND(EH$20<=$H36,EH$20>=$G36,$G36<>99,$H36<>99),$F36*(1+$N36)^(EH$20)/((1+$K36)^(EH$20)),0)))) -> 0 | ... GB36: =IF(AND($G36=99,$H36=99),GB$22*$F36*(1+$N36)^(GB$20)/((1+$K36)^(GB$20)),IF(AND($H36=99,GB$20>=$G36,GB$20<=$F$20),$F36*(1+$N36)^(GB$20)/((1+$K36)^(GB$20)),IF(AND($G36=99,GB$20<=$H36,GB$20>=$F$18),$F36*(1+$N36)^(GB$20)/((1+$K36)^(GB$20)),IF(AND(GB$20<=$H36,GB$20>=$G36,$G36<>99,$H36<>99),$F36*(1+$N36)^(GB$20)/((1+$K36)^(GB$20)),0)))) -> 0
C37: XX in €/Jahr | I37: 0 | J37: 0 | K37: 0 | L37: =$D$7 -> 0.02 | M37: =$E$7 -> 0.03 | N37: =$F$7 -> 0.05 | R37: =C37 -> XX in €/Jahr | S37: =IF(AND($G37=99,$H37=99),S$22*$E37*(1+$M37)^(S$20)/((1+$J37)^(S$20)),IF(AND($H37=99,S$20>=$G37,S$20<=$E$20),$E37*(1+$M37)^(S$20)/((1+$J37)^(S$20)),IF(AND($G37=99,S$20<=$H37,S$20>=$E$18),$E37*(1+$M37)^(S$20)/((1+$J37)^(S$20)),IF(AND(S$20<=$H37,S$20>=$G37,$G37<>99,$H37<>99),$E37*(1+$M37)^(S$20)/((1+$J37)^(S$20)),0)))) -> 0 | T37: =IF(AND($G37=99,$H37=99),T$22*$E37*(1+$M37)^(T$20)/((1+$J37)^(T$20)),IF(AND($H37=99,T$20>=$G37,T$20<=$E$20),$E37*(1+$M37)^(T$20)/((1+$J37)^(T$20)),IF(AND($G37=99,T$20<=$H37,T$20>=$E$18),$E37*(1+$M37)^(T$20)/((1+$J37)^(T$20)),IF(AND(T$20<=$H37,T$20>=$G37,$G37<>99,$H37<>99),$E37*(1+$M37)^(T$20)/((1+$J37)^(T$20)),0)))) -> 0 | U37: =IF(AND($G37=99,$H37=99),U$22*$E37*(1+$M37)^(U$20)/((1+$J37)^(U$20)),IF(AND($H37=99,U$20>=$G37,U$20<=$E$20),$E37*(1+$M37)^(U$20)/((1+$J37)^(U$20)),IF(AND($G37=99,U$20<=$H37,U$20>=$E$18),$E37*(1+$M37)^(U$20)/((1+$J37)^(U$20)),IF(AND(U$20<=$H37,U$20>=$G37,$G37<>99,$H37<>99),$E37*(1+$M37)^(U$20)/((1+$J37)^(U$20)),0)))) -> 0 | V37: =IF(AND($G37=99,$H37=99),V$22*$E37*(1+$M37)^(V$20)/((1+$J37)^(V$20)),IF(AND($H37=99,V$20>=$G37,V$20<=$E$20),$E37*(1+$M37)^(V$20)/((1+$J37)^(V$20)),IF(AND($G37=99,V$20<=$H37,V$20>=$E$18),$E37*(1+$M37)^(V$20)/((1+$J37)^(V$20)),IF(AND(V$20<=$H37,V$20>=$G37,$G37<>99,$H37<>99),$E37*(1+$M37)^(V$20)/((1+$J37)^(V$20)),0)))) -> 0 | W37: =IF(AND($G37=99,$H37=99),W$22*$E37*(1+$M37)^(W$20)/((1+$J37)^(W$20)),IF(AND($H37=99,W$20>=$G37,W$20<=$E$20),$E37*(1+$M37)^(W$20)/((1+$J37)^(W$20)),IF(AND($G37=99,W$20<=$H37,W$20>=$E$18),$E37*(1+$M37)^(W$20)/((1+$J37)^(W$20)),IF(AND(W$20<=$H37,W$20>=$G37,$G37<>99,$H37<>99),$E37*(1+$M37)^(W$20)/((1+$J37)^(W$20)),0)))) -> 0 | X37: =IF(AND($G37=99,$H37=99),X$22*$E37*(1+$M37)^(X$20)/((1+$J37)^(X$20)),IF(AND($H37=99,X$20>=$G37,X$20<=$E$20),$E37*(1+$M37)^(X$20)/((1+$J37)^(X$20)),IF(AND($G37=99,X$20<=$H37,X$20>=$E$18),$E37*(1+$M37)^(X$20)/((1+$J37)^(X$20)),IF(AND(X$20<=$H37,X$20>=$G37,$G37<>99,$H37<>99),$E37*(1+$M37)^(X$20)/((1+$J37)^(X$20)),0)))) -> 0 | Y37: =IF(AND($G37=99,$H37=99),Y$22*$E37*(1+$M37)^(Y$20)/((1+$J37)^(Y$20)),IF(AND($H37=99,Y$20>=$G37,Y$20<=$E$20),$E37*(1+$M37)^(Y$20)/((1+$J37)^(Y$20)),IF(AND($G37=99,Y$20<=$H37,Y$20>=$E$18),$E37*(1+$M37)^(Y$20)/((1+$J37)^(Y$20)),IF(AND(Y$20<=$H37,Y$20>=$G37,$G37<>99,$H37<>99),$E37*(1+$M37)^(Y$20)/((1+$J37)^(Y$20)),0)))) -> 0 | Z37: =IF(AND($G37=99,$H37=99),Z$22*$E37*(1+$M37)^(Z$20)/((1+$J37)^(Z$20)),IF(AND($H37=99,Z$20>=$G37,Z$20<=$E$20),$E37*(1+$M37)^(Z$20)/((1+$J37)^(Z$20)),IF(AND($G37=99,Z$20<=$H37,Z$20>=$E$18),$E37*(1+$M37)^(Z$20)/((1+$J37)^(Z$20)),IF(AND(Z$20<=$H37,Z$20>=$G37,$G37<>99,$H37<>99),$E37*(1+$M37)^(Z$20)/((1+$J37)^(Z$20)),0)))) -> 0 | ... BT37: =IF(AND($G37=99,$H37=99),BT$22*$E37*(1+$M37)^(BT$20)/((1+$J37)^(BT$20)),IF(AND($H37=99,BT$20>=$G37,BT$20<=$E$20),$E37*(1+$M37)^(BT$20)/((1+$J37)^(BT$20)),IF(AND($G37=99,BT$20<=$H37,BT$20>=$E$18),$E37*(1+$M37)^(BT$20)/((1+$J37)^(BT$20)),IF(AND(BT$20<=$H37,BT$20>=$G37,$G37<>99,$H37<>99),$E37*(1+$M37)^(BT$20)/((1+$J37)^(BT$20)),0)))) -> 0 | BV37: =C37 -> XX in €/Jahr | BW37: =IF(AND($G37=99,$H37=99),BW$22*$D37*(1+$L37)^(BW$20)/((1+$I37)^(BW$20)),IF(AND($H37=99,BW$20>=$G37,BW$20<=$D$20),$D37*(1+$L37)^(BW$20)/((1+$I37)^(BW$20)),IF(AND($G37=99,BW$20<=$H37,BW$20>=$D$18),$D37*(1+$L37)^(BW$20)/((1+$I37)^(BW$20)),IF(AND(BW$20<=$H37,BW$20>=$G37,$G37<>99,$H37<>99),$D37*(1+$L37)^(BW$20)/((1+$I37)^(BW$20)),0)))) -> 0 | BX37: =IF(AND($G37=99,$H37=99),BX$22*$D37*(1+$L37)^(BX$20)/((1+$I37)^(BX$20)),IF(AND($H37=99,BX$20>=$G37,BX$20<=$D$20),$D37*(1+$L37)^(BX$20)/((1+$I37)^(BX$20)),IF(AND($G37=99,BX$20<=$H37,BX$20>=$D$18),$D37*(1+$L37)^(BX$20)/((1+$I37)^(BX$20)),IF(AND(BX$20<=$H37,BX$20>=$G37,$G37<>99,$H37<>99),$D37*(1+$L37)^(BX$20)/((1+$I37)^(BX$20)),0)))) -> 0 | BY37: =IF(AND($G37=99,$H37=99),BY$22*$D37*(1+$L37)^(BY$20)/((1+$I37)^(BY$20)),IF(AND($H37=99,BY$20>=$G37,BY$20<=$D$20),$D37*(1+$L37)^(BY$20)/((1+$I37)^(BY$20)),IF(AND($G37=99,BY$20<=$H37,BY$20>=$D$18),$D37*(1+$L37)^(BY$20)/((1+$I37)^(BY$20)),IF(AND(BY$20<=$H37,BY$20>=$G37,$G37<>99,$H37<>99),$D37*(1+$L37)^(BY$20)/((1+$I37)^(BY$20)),0)))) -> 0 | BZ37: =IF(AND($G37=99,$H37=99),BZ$22*$D37*(1+$L37)^(BZ$20)/((1+$I37)^(BZ$20)),IF(AND($H37=99,BZ$20>=$G37,BZ$20<=$D$20),$D37*(1+$L37)^(BZ$20)/((1+$I37)^(BZ$20)),IF(AND($G37=99,BZ$20<=$H37,BZ$20>=$D$18),$D37*(1+$L37)^(BZ$20)/((1+$I37)^(BZ$20)),IF(AND(BZ$20<=$H37,BZ$20>=$G37,$G37<>99,$H37<>99),$D37*(1+$L37)^(BZ$20)/((1+$I37)^(BZ$20)),0)))) -> 0 | CA37: =IF(AND($G37=99,$H37=99),CA$22*$D37*(1+$L37)^(CA$20)/((1+$I37)^(CA$20)),IF(AND($H37=99,CA$20>=$G37,CA$20<=$D$20),$D37*(1+$L37)^(CA$20)/((1+$I37)^(CA$20)),IF(AND($G37=99,CA$20<=$H37,CA$20>=$D$18),$D37*(1+$L37)^(CA$20)/((1+$I37)^(CA$20)),IF(AND(CA$20<=$H37,CA$20>=$G37,$G37<>99,$H37<>99),$D37*(1+$L37)^(CA$20)/((1+$I37)^(CA$20)),0)))) -> 0 | CB37: =IF(AND($G37=99,$H37=99),CB$22*$D37*(1+$L37)^(CB$20)/((1+$I37)^(CB$20)),IF(AND($H37=99,CB$20>=$G37,CB$20<=$D$20),$D37*(1+$L37)^(CB$20)/((1+$I37)^(CB$20)),IF(AND($G37=99,CB$20<=$H37,CB$20>=$D$18),$D37*(1+$L37)^(CB$20)/((1+$I37)^(CB$20)),IF(AND(CB$20<=$H37,CB$20>=$G37,$G37<>99,$H37<>99),$D37*(1+$L37)^(CB$20)/((1+$I37)^(CB$20)),0)))) -> 0 | CC37: =IF(AND($G37=99,$H37=99),CC$22*$D37*(1+$L37)^(CC$20)/((1+$I37)^(CC$20)),IF(AND($H37=99,CC$20>=$G37,CC$20<=$D$20),$D37*(1+$L37)^(CC$20)/((1+$I37)^(CC$20)),IF(AND($G37=99,CC$20<=$H37,CC$20>=$D$18),$D37*(1+$L37)^(CC$20)/((1+$I37)^(CC$20)),IF(AND(CC$20<=$H37,CC$20>=$G37,$G37<>99,$H37<>99),$D37*(1+$L37)^(CC$20)/((1+$I37)^(CC$20)),0)))) -> 0 | CD37: =IF(AND($G37=99,$H37=99),CD$22*$D37*(1+$L37)^(CD$20)/((1+$I37)^(CD$20)),IF(AND($H37=99,CD$20>=$G37,CD$20<=$D$20),$D37*(1+$L37)^(CD$20)/((1+$I37)^(CD$20)),IF(AND($G37=99,CD$20<=$H37,CD$20>=$D$18),$D37*(1+$L37)^(CD$20)/((1+$I37)^(CD$20)),IF(AND(CD$20<=$H37,CD$20>=$G37,$G37<>99,$H37<>99),$D37*(1+$L37)^(CD$20)/((1+$I37)^(CD$20)),0)))) -> 0 | ... DX37: =IF(AND($G37=99,$H37=99),DX$22*$D37*(1+$L37)^(DX$20)/((1+$I37)^(DX$20)),IF(AND($H37=99,DX$20>=$G37,DX$20<=$D$20),$D37*(1+$L37)^(DX$20)/((1+$I37)^(DX$20)),IF(AND($G37=99,DX$20<=$H37,DX$20>=$D$18),$D37*(1+$L37)^(DX$20)/((1+$I37)^(DX$20)),IF(AND(DX$20<=$H37,DX$20>=$G37,$G37<>99,$H37<>99),$D37*(1+$L37)^(DX$20)/((1+$I37)^(DX$20)),0)))) -> 0 | DZ37: =C37 -> XX in €/Jahr | EA37: =IF(AND($G37=99,$H37=99),EA$22*$F37*(1+$N37)^(EA$20)/((1+$K37)^(EA$20)),IF(AND($H37=99,EA$20>=$G37,EA$20<=$F$20),$F37*(1+$N37)^(EA$20)/((1+$K37)^(EA$20)),IF(AND($G37=99,EA$20<=$H37,EA$20>=$F$18),$F37*(1+$N37)^(EA$20)/((1+$K37)^(EA$20)),IF(AND(EA$20<=$H37,EA$20>=$G37,$G37<>99,$H37<>99),$F37*(1+$N37)^(EA$20)/((1+$K37)^(EA$20)),0)))) -> 0 | EB37: =IF(AND($G37=99,$H37=99),EB$22*$F37*(1+$N37)^(EB$20)/((1+$K37)^(EB$20)),IF(AND($H37=99,EB$20>=$G37,EB$20<=$F$20),$F37*(1+$N37)^(EB$20)/((1+$K37)^(EB$20)),IF(AND($G37=99,EB$20<=$H37,EB$20>=$F$18),$F37*(1+$N37)^(EB$20)/((1+$K37)^(EB$20)),IF(AND(EB$20<=$H37,EB$20>=$G37,$G37<>99,$H37<>99),$F37*(1+$N37)^(EB$20)/((1+$K37)^(EB$20)),0)))) -> 0 | EC37: =IF(AND($G37=99,$H37=99),EC$22*$F37*(1+$N37)^(EC$20)/((1+$K37)^(EC$20)),IF(AND($H37=99,EC$20>=$G37,EC$20<=$F$20),$F37*(1+$N37)^(EC$20)/((1+$K37)^(EC$20)),IF(AND($G37=99,EC$20<=$H37,EC$20>=$F$18),$F37*(1+$N37)^(EC$20)/((1+$K37)^(EC$20)),IF(AND(EC$20<=$H37,EC$20>=$G37,$G37<>99,$H37<>99),$F37*(1+$N37)^(EC$20)/((1+$K37)^(EC$20)),0)))) -> 0 | ED37: =IF(AND($G37=99,$H37=99),ED$22*$F37*(1+$N37)^(ED$20)/((1+$K37)^(ED$20)),IF(AND($H37=99,ED$20>=$G37,ED$20<=$F$20),$F37*(1+$N37)^(ED$20)/((1+$K37)^(ED$20)),IF(AND($G37=99,ED$20<=$H37,ED$20>=$F$18),$F37*(1+$N37)^(ED$20)/((1+$K37)^(ED$20)),IF(AND(ED$20<=$H37,ED$20>=$G37,$G37<>99,$H37<>99),$F37*(1+$N37)^(ED$20)/((1+$K37)^(ED$20)),0)))) -> 0 | EE37: =IF(AND($G37=99,$H37=99),EE$22*$F37*(1+$N37)^(EE$20)/((1+$K37)^(EE$20)),IF(AND($H37=99,EE$20>=$G37,EE$20<=$F$20),$F37*(1+$N37)^(EE$20)/((1+$K37)^(EE$20)),IF(AND($G37=99,EE$20<=$H37,EE$20>=$F$18),$F37*(1+$N37)^(EE$20)/((1+$K37)^(EE$20)),IF(AND(EE$20<=$H37,EE$20>=$G37,$G37<>99,$H37<>99),$F37*(1+$N37)^(EE$20)/((1+$K37)^(EE$20)),0)))) -> 0 | EF37: =IF(AND($G37=99,$H37=99),EF$22*$F37*(1+$N37)^(EF$20)/((1+$K37)^(EF$20)),IF(AND($H37=99,EF$20>=$G37,EF$20<=$F$20),$F37*(1+$N37)^(EF$20)/((1+$K37)^(EF$20)),IF(AND($G37=99,EF$20<=$H37,EF$20>=$F$18),$F37*(1+$N37)^(EF$20)/((1+$K37)^(EF$20)),IF(AND(EF$20<=$H37,EF$20>=$G37,$G37<>99,$H37<>99),$F37*(1+$N37)^(EF$20)/((1+$K37)^(EF$20)),0)))) -> 0 | EG37: =IF(AND($G37=99,$H37=99),EG$22*$F37*(1+$N37)^(EG$20)/((1+$K37)^(EG$20)),IF(AND($H37=99,EG$20>=$G37,EG$20<=$F$20),$F37*(1+$N37)^(EG$20)/((1+$K37)^(EG$20)),IF(AND($G37=99,EG$20<=$H37,EG$20>=$F$18),$F37*(1+$N37)^(EG$20)/((1+$K37)^(EG$20)),IF(AND(EG$20<=$H37,EG$20>=$G37,$G37<>99,$H37<>99),$F37*(1+$N37)^(EG$20)/((1+$K37)^(EG$20)),0)))) -> 0 | EH37: =IF(AND($G37=99,$H37=99),EH$22*$F37*(1+$N37)^(EH$20)/((1+$K37)^(EH$20)),IF(AND($H37=99,EH$20>=$G37,EH$20<=$F$20),$F37*(1+$N37)^(EH$20)/((1+$K37)^(EH$20)),IF(AND($G37=99,EH$20<=$H37,EH$20>=$F$18),$F37*(1+$N37)^(EH$20)/((1+$K37)^(EH$20)),IF(AND(EH$20<=$H37,EH$20>=$G37,$G37<>99,$H37<>99),$F37*(1+$N37)^(EH$20)/((1+$K37)^(EH$20)),0)))) -> 0 | ... GB37: =IF(AND($G37=99,$H37=99),GB$22*$F37*(1+$N37)^(GB$20)/((1+$K37)^(GB$20)),IF(AND($H37=99,GB$20>=$G37,GB$20<=$F$20),$F37*(1+$N37)^(GB$20)/((1+$K37)^(GB$20)),IF(AND($G37=99,GB$20<=$H37,GB$20>=$F$18),$F37*(1+$N37)^(GB$20)/((1+$K37)^(GB$20)),IF(AND(GB$20<=$H37,GB$20>=$G37,$G37<>99,$H37<>99),$F37*(1+$N37)^(GB$20)/((1+$K37)^(GB$20)),0)))) -> 0
C38: XX in €/Jahr | I38: 0 | J38: 0 | K38: 0 | L38: =$D$7 -> 0.02 | M38: =$E$7 -> 0.03 | N38: =$F$7 -> 0.05 | R38: =C38 -> XX in €/Jahr | S38: =IF(AND($G38=99,$H38=99),S$22*$E38*(1+$M38)^(S$20)/((1+$J38)^(S$20)),IF(AND($H38=99,S$20>=$G38,S$20<=$E$20),$E38*(1+$M38)^(S$20)/((1+$J38)^(S$20)),IF(AND($G38=99,S$20<=$H38,S$20>=$E$18),$E38*(1+$M38)^(S$20)/((1+$J38)^(S$20)),IF(AND(S$20<=$H38,S$20>=$G38,$G38<>99,$H38<>99),$E38*(1+$M38)^(S$20)/((1+$J38)^(S$20)),0)))) -> 0 | T38: =IF(AND($G38=99,$H38=99),T$22*$E38*(1+$M38)^(T$20)/((1+$J38)^(T$20)),IF(AND($H38=99,T$20>=$G38,T$20<=$E$20),$E38*(1+$M38)^(T$20)/((1+$J38)^(T$20)),IF(AND($G38=99,T$20<=$H38,T$20>=$E$18),$E38*(1+$M38)^(T$20)/((1+$J38)^(T$20)),IF(AND(T$20<=$H38,T$20>=$G38,$G38<>99,$H38<>99),$E38*(1+$M38)^(T$20)/((1+$J38)^(T$20)),0)))) -> 0 | U38: =IF(AND($G38=99,$H38=99),U$22*$E38*(1+$M38)^(U$20)/((1+$J38)^(U$20)),IF(AND($H38=99,U$20>=$G38,U$20<=$E$20),$E38*(1+$M38)^(U$20)/((1+$J38)^(U$20)),IF(AND($G38=99,U$20<=$H38,U$20>=$E$18),$E38*(1+$M38)^(U$20)/((1+$J38)^(U$20)),IF(AND(U$20<=$H38,U$20>=$G38,$G38<>99,$H38<>99),$E38*(1+$M38)^(U$20)/((1+$J38)^(U$20)),0)))) -> 0 | V38: =IF(AND($G38=99,$H38=99),V$22*$E38*(1+$M38)^(V$20)/((1+$J38)^(V$20)),IF(AND($H38=99,V$20>=$G38,V$20<=$E$20),$E38*(1+$M38)^(V$20)/((1+$J38)^(V$20)),IF(AND($G38=99,V$20<=$H38,V$20>=$E$18),$E38*(1+$M38)^(V$20)/((1+$J38)^(V$20)),IF(AND(V$20<=$H38,V$20>=$G38,$G38<>99,$H38<>99),$E38*(1+$M38)^(V$20)/((1+$J38)^(V$20)),0)))) -> 0 | W38: =IF(AND($G38=99,$H38=99),W$22*$E38*(1+$M38)^(W$20)/((1+$J38)^(W$20)),IF(AND($H38=99,W$20>=$G38,W$20<=$E$20),$E38*(1+$M38)^(W$20)/((1+$J38)^(W$20)),IF(AND($G38=99,W$20<=$H38,W$20>=$E$18),$E38*(1+$M38)^(W$20)/((1+$J38)^(W$20)),IF(AND(W$20<=$H38,W$20>=$G38,$G38<>99,$H38<>99),$E38*(1+$M38)^(W$20)/((1+$J38)^(W$20)),0)))) -> 0 | X38: =IF(AND($G38=99,$H38=99),X$22*$E38*(1+$M38)^(X$20)/((1+$J38)^(X$20)),IF(AND($H38=99,X$20>=$G38,X$20<=$E$20),$E38*(1+$M38)^(X$20)/((1+$J38)^(X$20)),IF(AND($G38=99,X$20<=$H38,X$20>=$E$18),$E38*(1+$M38)^(X$20)/((1+$J38)^(X$20)),IF(AND(X$20<=$H38,X$20>=$G38,$G38<>99,$H38<>99),$E38*(1+$M38)^(X$20)/((1+$J38)^(X$20)),0)))) -> 0 | Y38: =IF(AND($G38=99,$H38=99),Y$22*$E38*(1+$M38)^(Y$20)/((1+$J38)^(Y$20)),IF(AND($H38=99,Y$20>=$G38,Y$20<=$E$20),$E38*(1+$M38)^(Y$20)/((1+$J38)^(Y$20)),IF(AND($G38=99,Y$20<=$H38,Y$20>=$E$18),$E38*(1+$M38)^(Y$20)/((1+$J38)^(Y$20)),IF(AND(Y$20<=$H38,Y$20>=$G38,$G38<>99,$H38<>99),$E38*(1+$M38)^(Y$20)/((1+$J38)^(Y$20)),0)))) -> 0 | Z38: =IF(AND($G38=99,$H38=99),Z$22*$E38*(1+$M38)^(Z$20)/((1+$J38)^(Z$20)),IF(AND($H38=99,Z$20>=$G38,Z$20<=$E$20),$E38*(1+$M38)^(Z$20)/((1+$J38)^(Z$20)),IF(AND($G38=99,Z$20<=$H38,Z$20>=$E$18),$E38*(1+$M38)^(Z$20)/((1+$J38)^(Z$20)),IF(AND(Z$20<=$H38,Z$20>=$G38,$G38<>99,$H38<>99),$E38*(1+$M38)^(Z$20)/((1+$J38)^(Z$20)),0)))) -> 0 | ... BT38: =IF(AND($G38=99,$H38=99),BT$22*$E38*(1+$M38)^(BT$20)/((1+$J38)^(BT$20)),IF(AND($H38=99,BT$20>=$G38,BT$20<=$E$20),$E38*(1+$M38)^(BT$20)/((1+$J38)^(BT$20)),IF(AND($G38=99,BT$20<=$H38,BT$20>=$E$18),$E38*(1+$M38)^(BT$20)/((1+$J38)^(BT$20)),IF(AND(BT$20<=$H38,BT$20>=$G38,$G38<>99,$H38<>99),$E38*(1+$M38)^(BT$20)/((1+$J38)^(BT$20)),0)))) -> 0 | BV38: =C38 -> XX in €/Jahr | BW38: =IF(AND($G38=99,$H38=99),BW$22*$D38*(1+$L38)^(BW$20)/((1+$I38)^(BW$20)),IF(AND($H38=99,BW$20>=$G38,BW$20<=$D$20),$D38*(1+$L38)^(BW$20)/((1+$I38)^(BW$20)),IF(AND($G38=99,BW$20<=$H38,BW$20>=$D$18),$D38*(1+$L38)^(BW$20)/((1+$I38)^(BW$20)),IF(AND(BW$20<=$H38,BW$20>=$G38,$G38<>99,$H38<>99),$D38*(1+$L38)^(BW$20)/((1+$I38)^(BW$20)),0)))) -> 0 | BX38: =IF(AND($G38=99,$H38=99),BX$22*$D38*(1+$L38)^(BX$20)/((1+$I38)^(BX$20)),IF(AND($H38=99,BX$20>=$G38,BX$20<=$D$20),$D38*(1+$L38)^(BX$20)/((1+$I38)^(BX$20)),IF(AND($G38=99,BX$20<=$H38,BX$20>=$D$18),$D38*(1+$L38)^(BX$20)/((1+$I38)^(BX$20)),IF(AND(BX$20<=$H38,BX$20>=$G38,$G38<>99,$H38<>99),$D38*(1+$L38)^(BX$20)/((1+$I38)^(BX$20)),0)))) -> 0 | BY38: =IF(AND($G38=99,$H38=99),BY$22*$D38*(1+$L38)^(BY$20)/((1+$I38)^(BY$20)),IF(AND($H38=99,BY$20>=$G38,BY$20<=$D$20),$D38*(1+$L38)^(BY$20)/((1+$I38)^(BY$20)),IF(AND($G38=99,BY$20<=$H38,BY$20>=$D$18),$D38*(1+$L38)^(BY$20)/((1+$I38)^(BY$20)),IF(AND(BY$20<=$H38,BY$20>=$G38,$G38<>99,$H38<>99),$D38*(1+$L38)^(BY$20)/((1+$I38)^(BY$20)),0)))) -> 0 | BZ38: =IF(AND($G38=99,$H38=99),BZ$22*$D38*(1+$L38)^(BZ$20)/((1+$I38)^(BZ$20)),IF(AND($H38=99,BZ$20>=$G38,BZ$20<=$D$20),$D38*(1+$L38)^(BZ$20)/((1+$I38)^(BZ$20)),IF(AND($G38=99,BZ$20<=$H38,BZ$20>=$D$18),$D38*(1+$L38)^(BZ$20)/((1+$I38)^(BZ$20)),IF(AND(BZ$20<=$H38,BZ$20>=$G38,$G38<>99,$H38<>99),$D38*(1+$L38)^(BZ$20)/((1+$I38)^(BZ$20)),0)))) -> 0 | CA38: =IF(AND($G38=99,$H38=99),CA$22*$D38*(1+$L38)^(CA$20)/((1+$I38)^(CA$20)),IF(AND($H38=99,CA$20>=$G38,CA$20<=$D$20),$D38*(1+$L38)^(CA$20)/((1+$I38)^(CA$20)),IF(AND($G38=99,CA$20<=$H38,CA$20>=$D$18),$D38*(1+$L38)^(CA$20)/((1+$I38)^(CA$20)),IF(AND(CA$20<=$H38,CA$20>=$G38,$G38<>99,$H38<>99),$D38*(1+$L38)^(CA$20)/((1+$I38)^(CA$20)),0)))) -> 0 | CB38: =IF(AND($G38=99,$H38=99),CB$22*$D38*(1+$L38)^(CB$20)/((1+$I38)^(CB$20)),IF(AND($H38=99,CB$20>=$G38,CB$20<=$D$20),$D38*(1+$L38)^(CB$20)/((1+$I38)^(CB$20)),IF(AND($G38=99,CB$20<=$H38,CB$20>=$D$18),$D38*(1+$L38)^(CB$20)/((1+$I38)^(CB$20)),IF(AND(CB$20<=$H38,CB$20>=$G38,$G38<>99,$H38<>99),$D38*(1+$L38)^(CB$20)/((1+$I38)^(CB$20)),0)))) -> 0 | CC38: =IF(AND($G38=99,$H38=99),CC$22*$D38*(1+$L38)^(CC$20)/((1+$I38)^(CC$20)),IF(AND($H38=99,CC$20>=$G38,CC$20<=$D$20),$D38*(1+$L38)^(CC$20)/((1+$I38)^(CC$20)),IF(AND($G38=99,CC$20<=$H38,CC$20>=$D$18),$D38*(1+$L38)^(CC$20)/((1+$I38)^(CC$20)),IF(AND(CC$20<=$H38,CC$20>=$G38,$G38<>99,$H38<>99),$D38*(1+$L38)^(CC$20)/((1+$I38)^(CC$20)),0)))) -> 0 | CD38: =IF(AND($G38=99,$H38=99),CD$22*$D38*(1+$L38)^(CD$20)/((1+$I38)^(CD$20)),IF(AND($H38=99,CD$20>=$G38,CD$20<=$D$20),$D38*(1+$L38)^(CD$20)/((1+$I38)^(CD$20)),IF(AND($G38=99,CD$20<=$H38,CD$20>=$D$18),$D38*(1+$L38)^(CD$20)/((1+$I38)^(CD$20)),IF(AND(CD$20<=$H38,CD$20>=$G38,$G38<>99,$H38<>99),$D38*(1+$L38)^(CD$20)/((1+$I38)^(CD$20)),0)))) -> 0 | ... DX38: =IF(AND($G38=99,$H38=99),DX$22*$D38*(1+$L38)^(DX$20)/((1+$I38)^(DX$20)),IF(AND($H38=99,DX$20>=$G38,DX$20<=$D$20),$D38*(1+$L38)^(DX$20)/((1+$I38)^(DX$20)),IF(AND($G38=99,DX$20<=$H38,DX$20>=$D$18),$D38*(1+$L38)^(DX$20)/((1+$I38)^(DX$20)),IF(AND(DX$20<=$H38,DX$20>=$G38,$G38<>99,$H38<>99),$D38*(1+$L38)^(DX$20)/((1+$I38)^(DX$20)),0)))) -> 0 | DZ38: =C38 -> XX in €/Jahr | EA38: =IF(AND($G38=99,$H38=99),EA$22*$F38*(1+$N38)^(EA$20)/((1+$K38)^(EA$20)),IF(AND($H38=99,EA$20>=$G38,EA$20<=$F$20),$F38*(1+$N38)^(EA$20)/((1+$K38)^(EA$20)),IF(AND($G38=99,EA$20<=$H38,EA$20>=$F$18),$F38*(1+$N38)^(EA$20)/((1+$K38)^(EA$20)),IF(AND(EA$20<=$H38,EA$20>=$G38,$G38<>99,$H38<>99),$F38*(1+$N38)^(EA$20)/((1+$K38)^(EA$20)),0)))) -> 0 | EB38: =IF(AND($G38=99,$H38=99),EB$22*$F38*(1+$N38)^(EB$20)/((1+$K38)^(EB$20)),IF(AND($H38=99,EB$20>=$G38,EB$20<=$F$20),$F38*(1+$N38)^(EB$20)/((1+$K38)^(EB$20)),IF(AND($G38=99,EB$20<=$H38,EB$20>=$F$18),$F38*(1+$N38)^(EB$20)/((1+$K38)^(EB$20)),IF(AND(EB$20<=$H38,EB$20>=$G38,$G38<>99,$H38<>99),$F38*(1+$N38)^(EB$20)/((1+$K38)^(EB$20)),0)))) -> 0 | EC38: =IF(AND($G38=99,$H38=99),EC$22*$F38*(1+$N38)^(EC$20)/((1+$K38)^(EC$20)),IF(AND($H38=99,EC$20>=$G38,EC$20<=$F$20),$F38*(1+$N38)^(EC$20)/((1+$K38)^(EC$20)),IF(AND($G38=99,EC$20<=$H38,EC$20>=$F$18),$F38*(1+$N38)^(EC$20)/((1+$K38)^(EC$20)),IF(AND(EC$20<=$H38,EC$20>=$G38,$G38<>99,$H38<>99),$F38*(1+$N38)^(EC$20)/((1+$K38)^(EC$20)),0)))) -> 0 | ED38: =IF(AND($G38=99,$H38=99),ED$22*$F38*(1+$N38)^(ED$20)/((1+$K38)^(ED$20)),IF(AND($H38=99,ED$20>=$G38,ED$20<=$F$20),$F38*(1+$N38)^(ED$20)/((1+$K38)^(ED$20)),IF(AND($G38=99,ED$20<=$H38,ED$20>=$F$18),$F38*(1+$N38)^(ED$20)/((1+$K38)^(ED$20)),IF(AND(ED$20<=$H38,ED$20>=$G38,$G38<>99,$H38<>99),$F38*(1+$N38)^(ED$20)/((1+$K38)^(ED$20)),0)))) -> 0 | EE38: =IF(AND($G38=99,$H38=99),EE$22*$F38*(1+$N38)^(EE$20)/((1+$K38)^(EE$20)),IF(AND($H38=99,EE$20>=$G38,EE$20<=$F$20),$F38*(1+$N38)^(EE$20)/((1+$K38)^(EE$20)),IF(AND($G38=99,EE$20<=$H38,EE$20>=$F$18),$F38*(1+$N38)^(EE$20)/((1+$K38)^(EE$20)),IF(AND(EE$20<=$H38,EE$20>=$G38,$G38<>99,$H38<>99),$F38*(1+$N38)^(EE$20)/((1+$K38)^(EE$20)),0)))) -> 0 | EF38: =IF(AND($G38=99,$H38=99),EF$22*$F38*(1+$N38)^(EF$20)/((1+$K38)^(EF$20)),IF(AND($H38=99,EF$20>=$G38,EF$20<=$F$20),$F38*(1+$N38)^(EF$20)/((1+$K38)^(EF$20)),IF(AND($G38=99,EF$20<=$H38,EF$20>=$F$18),$F38*(1+$N38)^(EF$20)/((1+$K38)^(EF$20)),IF(AND(EF$20<=$H38,EF$20>=$G38,$G38<>99,$H38<>99),$F38*(1+$N38)^(EF$20)/((1+$K38)^(EF$20)),0)))) -> 0 | EG38: =IF(AND($G38=99,$H38=99),EG$22*$F38*(1+$N38)^(EG$20)/((1+$K38)^(EG$20)),IF(AND($H38=99,EG$20>=$G38,EG$20<=$F$20),$F38*(1+$N38)^(EG$20)/((1+$K38)^(EG$20)),IF(AND($G38=99,EG$20<=$H38,EG$20>=$F$18),$F38*(1+$N38)^(EG$20)/((1+$K38)^(EG$20)),IF(AND(EG$20<=$H38,EG$20>=$G38,$G38<>99,$H38<>99),$F38*(1+$N38)^(EG$20)/((1+$K38)^(EG$20)),0)))) -> 0 | EH38: =IF(AND($G38=99,$H38=99),EH$22*$F38*(1+$N38)^(EH$20)/((1+$K38)^(EH$20)),IF(AND($H38=99,EH$20>=$G38,EH$20<=$F$20),$F38*(1+$N38)^(EH$20)/((1+$K38)^(EH$20)),IF(AND($G38=99,EH$20<=$H38,EH$20>=$F$18),$F38*(1+$N38)^(EH$20)/((1+$K38)^(EH$20)),IF(AND(EH$20<=$H38,EH$20>=$G38,$G38<>99,$H38<>99),$F38*(1+$N38)^(EH$20)/((1+$K38)^(EH$20)),0)))) -> 0 | ... GB38: =IF(AND($G38=99,$H38=99),GB$22*$F38*(1+$N38)^(GB$20)/((1+$K38)^(GB$20)),IF(AND($H38=99,GB$20>=$G38,GB$20<=$F$20),$F38*(1+$N38)^(GB$20)/((1+$K38)^(GB$20)),IF(AND($G38=99,GB$20<=$H38,GB$20>=$F$18),$F38*(1+$N38)^(GB$20)/((1+$K38)^(GB$20)),IF(AND(GB$20<=$H38,GB$20>=$G38,$G38<>99,$H38<>99),$F38*(1+$N38)^(GB$20)/((1+$K38)^(GB$20)),0)))) -> 0
B39: Lasten | C39: Mehrverbrauch Strom in % | D39: {=IFERROR(_xlfn.IFS(D11>=G11,0,D11=0,1),(G11-D11)/D11)} -> 0 | E39: {=IFERROR(_xlfn.IFS(E11>=H11,0,E11=0,1),(H11-E11)/E11)} -> 0 | F39: {=IFERROR(_xlfn.IFS(F11>=I11,0,F11=0,1),(I11-F11)/F11)} -> 0 | G39: 99 | H39: 99 | I39: 0 | J39: 0 | K39: 0 | L39: ='Allgemeine Unternehmensdaten'!$E$8 -> 0.04 | M39: ='Allgemeine Unternehmensdaten'!$F$8 -> 0.03 | N39: ='Allgemeine Unternehmensdaten'!$G$8 -> 0.02 | R39: =C39 -> Mehrverbrauch Strom in % | S39: =IF(AND($E39=1,$E11=0),'Allgemeine Unternehmensdaten'!$F$7*S22*$H11*($M39+1)^(S20)*((1+$J39)^(S$20)),'Allgemeine Unternehmensdaten'!$F$7*S22*$E11*$E39*($M39+1)^(S20)*((1+$J39)^(S$20))) -> 0 | T39: =IF(AND($E39=1,$E11=0),'Allgemeine Unternehmensdaten'!$F$7*T22*$H11*($M39+1)^(T20)*((1+$J39)^(T$20)),'Allgemeine Unternehmensdaten'!$F$7*T22*$E11*$E39*($M39+1)^(T20)*((1+$J39)^(T$20))) -> 0 | U39: =IF(AND($E39=1,$E11=0),'Allgemeine Unternehmensdaten'!$F$7*U22*$H11*($M39+1)^(U20)*((1+$J39)^(U$20)),'Allgemeine Unternehmensdaten'!$F$7*U22*$E11*$E39*($M39+1)^(U20)*((1+$J39)^(U$20))) -> 0 | V39: =IF(AND($E39=1,$E11=0),'Allgemeine Unternehmensdaten'!$F$7*V22*$H11*($M39+1)^(V20)*((1+$J39)^(V$20)),'Allgemeine Unternehmensdaten'!$F$7*V22*$E11*$E39*($M39+1)^(V20)*((1+$J39)^(V$20))) -> 0 | W39: =IF(AND($E39=1,$E11=0),'Allgemeine Unternehmensdaten'!$F$7*W22*$H11*($M39+1)^(W20)*((1+$J39)^(W$20)),'Allgemeine Unternehmensdaten'!$F$7*W22*$E11*$E39*($M39+1)^(W20)*((1+$J39)^(W$20))) -> 0 | X39: =IF(AND($E39=1,$E11=0),'Allgemeine Unternehmensdaten'!$F$7*X22*$H11*($M39+1)^(X20)*((1+$J39)^(X$20)),'Allgemeine Unternehmensdaten'!$F$7*X22*$E11*$E39*($M39+1)^(X20)*((1+$J39)^(X$20))) -> 0 | Y39: =IF(AND($E39=1,$E11=0),'Allgemeine Unternehmensdaten'!$F$7*Y22*$H11*($M39+1)^(Y20)*((1+$J39)^(Y$20)),'Allgemeine Unternehmensdaten'!$F$7*Y22*$E11*$E39*($M39+1)^(Y20)*((1+$J39)^(Y$20))) -> 0 | Z39: =IF(AND($E39=1,$E11=0),'Allgemeine Unternehmensdaten'!$F$7*Z22*$H11*($M39+1)^(Z20)*((1+$J39)^(Z$20)),'Allgemeine Unternehmensdaten'!$F$7*Z22*$E11*$E39*($M39+1)^(Z20)*((1+$J39)^(Z$20))) -> 0 | ... BT39: =IF(AND($E39=1,$E11=0),'Allgemeine Unternehmensdaten'!$F$7*BT22*$H11*($M39+1)^(BT20)*((1+$J39)^(BT$20)),'Allgemeine Unternehmensdaten'!$F$7*BT22*$E11*$E39*($M39+1)^(BT20)*((1+$J39)^(BT$20))) -> 0 | BV39: =C39 -> Mehrverbrauch Strom in % | BW39: =IF(AND($D39=1,$D11=0),'Allgemeine Unternehmensdaten'!$E$7*BW22*$G11*($L39+1)^(BW20)*((1+$I39)^(BW$20)),'Allgemeine Unternehmensdaten'!$E$7*BW22*$D11*$D39*($L39+1)^(BW20)*((1+$I39)^(BW$20))) -> 0 | BX39: =IF(AND($D39=1,$D11=0),'Allgemeine Unternehmensdaten'!$E$7*BX22*$G11*($L39+1)^(BX20)*((1+$I39)^(BX$20)),'Allgemeine Unternehmensdaten'!$E$7*BX22*$D11*$D39*($L39+1)^(BX20)*((1+$I39)^(BX$20))) -> 0 | BY39: =IF(AND($D39=1,$D11=0),'Allgemeine Unternehmensdaten'!$E$7*BY22*$G11*($L39+1)^(BY20)*((1+$I39)^(BY$20)),'Allgemeine Unternehmensdaten'!$E$7*BY22*$D11*$D39*($L39+1)^(BY20)*((1+$I39)^(BY$20))) -> 0 | BZ39: =IF(AND($D39=1,$D11=0),'Allgemeine Unternehmensdaten'!$E$7*BZ22*$G11*($L39+1)^(BZ20)*((1+$I39)^(BZ$20)),'Allgemeine Unternehmensdaten'!$E$7*BZ22*$D11*$D39*($L39+1)^(BZ20)*((1+$I39)^(BZ$20))) -> 0 | CA39: =IF(AND($D39=1,$D11=0),'Allgemeine Unternehmensdaten'!$E$7*CA22*$G11*($L39+1)^(CA20)*((1+$I39)^(CA$20)),'Allgemeine Unternehmensdaten'!$E$7*CA22*$D11*$D39*($L39+1)^(CA20)*((1+$I39)^(CA$20))) -> 0 | CB39: =IF(AND($D39=1,$D11=0),'Allgemeine Unternehmensdaten'!$E$7*CB22*$G11*($L39+1)^(CB20)*((1+$I39)^(CB$20)),'Allgemeine Unternehmensdaten'!$E$7*CB22*$D11*$D39*($L39+1)^(CB20)*((1+$I39)^(CB$20))) -> 0 | CC39: =IF(AND($D39=1,$D11=0),'Allgemeine Unternehmensdaten'!$E$7*CC22*$G11*($L39+1)^(CC20)*((1+$I39)^(CC$20)),'Allgemeine Unternehmensdaten'!$E$7*CC22*$D11*$D39*($L39+1)^(CC20)*((1+$I39)^(CC$20))) -> 0 | CD39: =IF(AND($D39=1,$D11=0),'Allgemeine Unternehmensdaten'!$E$7*CD22*$G11*($L39+1)^(CD20)*((1+$I39)^(CD$20)),'Allgemeine Unternehmensdaten'!$E$7*CD22*$D11*$D39*($L39+1)^(CD20)*((1+$I39)^(CD$20))) -> 0 | ... DX39: =IF(AND($D39=1,$D11=0),'Allgemeine Unternehmensdaten'!$E$7*DX22*$G11*($L39+1)^(DX20)*((1+$I39)^(DX$20)),'Allgemeine Unternehmensdaten'!$E$7*DX22*$D11*$D39*($L39+1)^(DX20)*((1+$I39)^(DX$20))) -> 0 | DZ39: =C39 -> Mehrverbrauch Strom in % | EA39: =IF(AND($F39=1,$F11=0),'Allgemeine Unternehmensdaten'!$G$7*EA22*$I11*($N39+1)^(EA20)*((1+$K39)^(EA$20)),'Allgemeine Unternehmensdaten'!$G$7*EA22*$F11*$F39*($N39+1)^(EA20)*((1+$K39)^(EA$20))) -> 0 | EB39: =IF(AND($F39=1,$F11=0),'Allgemeine Unternehmensdaten'!$G$7*EB22*$I11*($N39+1)^(EB20)*((1+$K39)^(EB$20)),'Allgemeine Unternehmensdaten'!$G$7*EB22*$F11*$F39*($N39+1)^(EB20)*((1+$K39)^(EB$20))) -> 0 | EC39: =IF(AND($F39=1,$F11=0),'Allgemeine Unternehmensdaten'!$G$7*EC22*$I11*($N39+1)^(EC20)*((1+$K39)^(EC$20)),'Allgemeine Unternehmensdaten'!$G$7*EC22*$F11*$F39*($N39+1)^(EC20)*((1+$K39)^(EC$20))) -> 0 | ED39: =IF(AND($F39=1,$F11=0),'Allgemeine Unternehmensdaten'!$G$7*ED22*$I11*($N39+1)^(ED20)*((1+$K39)^(ED$20)),'Allgemeine Unternehmensdaten'!$G$7*ED22*$F11*$F39*($N39+1)^(ED20)*((1+$K39)^(ED$20))) -> 0 | EE39: =IF(AND($F39=1,$F11=0),'Allgemeine Unternehmensdaten'!$G$7*EE22*$I11*($N39+1)^(EE20)*((1+$K39)^(EE$20)),'Allgemeine Unternehmensdaten'!$G$7*EE22*$F11*$F39*($N39+1)^(EE20)*((1+$K39)^(EE$20))) -> 0 | EF39: =IF(AND($F39=1,$F11=0),'Allgemeine Unternehmensdaten'!$G$7*EF22*$I11*($N39+1)^(EF20)*((1+$K39)^(EF$20)),'Allgemeine Unternehmensdaten'!$G$7*EF22*$F11*$F39*($N39+1)^(EF20)*((1+$K39)^(EF$20))) -> 0 | EG39: =IF(AND($F39=1,$F11=0),'Allgemeine Unternehmensdaten'!$G$7*EG22*$I11*($N39+1)^(EG20)*((1+$K39)^(EG$20)),'Allgemeine Unternehmensdaten'!$G$7*EG22*$F11*$F39*($N39+1)^(EG20)*((1+$K39)^(EG$20))) -> 0 | EH39: =IF(AND($F39=1,$F11=0),'Allgemeine Unternehmensdaten'!$G$7*EH22*$I11*($N39+1)^(EH20)*((1+$K39)^(EH$20)),'Allgemeine Unternehmensdaten'!$G$7*EH22*$F11*$F39*($N39+1)^(EH20)*((1+$K39)^(EH$20))) -> 0 | ... GB39: =IF(AND($F39=1,$F11=0),'Allgemeine Unternehmensdaten'!$G$7*GB22*$I11*($N39+1)^(GB20)*((1+$K39)^(GB$20)),'Allgemeine Unternehmensdaten'!$G$7*GB22*$F11*$F39*($N39+1)^(GB20)*((1+$K39)^(GB$20))) -> 0
C40: Mehrverbrauch Gas in % | D40: {=IFERROR(_xlfn.IFS(D12>=G12,0,D12=0,1),(G12-D12)/D12)} -> 0 | E40: {=IFERROR(_xlfn.IFS(E12>=H12,0,E12=0,1),(H12-E12)/E12)} -> 0 | F40: {=IFERROR(_xlfn.IFS(F12>=I12,0,F12=0,1),(I12-F12)/F12)} -> 0 | G40: 99 | H40: 99 | I40: 0 | J40: 0 | K40: 0 | L40: ='Allgemeine Unternehmensdaten'!$E$14 -> 0.04 | M40: ='Allgemeine Unternehmensdaten'!$F$14 -> 0.03 | N40: ='Allgemeine Unternehmensdaten'!$G$14 -> 0.02 | R40: =C40 -> Mehrverbrauch Gas in % | S40: =IF(AND($E40=1,$E12=0),'Allgemeine Unternehmensdaten'!$F$13*S$22*$H12*($M40+1)^(S$20)*((1+$J40)^(S$20)),'Allgemeine Unternehmensdaten'!$F$13*S22*$E12*$E40*($M40+1)^(S$20)*((1+$J40)^(S$20))) -> 0 | T40: =IF(AND($E40=1,$E12=0),'Allgemeine Unternehmensdaten'!$F$13*T$22*$H12*($M40+1)^(T$20)*((1+$J40)^(T$20)),'Allgemeine Unternehmensdaten'!$F$13*T22*$E12*$E40*($M40+1)^(T$20)*((1+$J40)^(T$20))) -> 0 | U40: =IF(AND($E40=1,$E12=0),'Allgemeine Unternehmensdaten'!$F$13*U$22*$H12*($M40+1)^(U$20)*((1+$J40)^(U$20)),'Allgemeine Unternehmensdaten'!$F$13*U22*$E12*$E40*($M40+1)^(U$20)*((1+$J40)^(U$20))) -> 0 | V40: =IF(AND($E40=1,$E12=0),'Allgemeine Unternehmensdaten'!$F$13*V$22*$H12*($M40+1)^(V$20)*((1+$J40)^(V$20)),'Allgemeine Unternehmensdaten'!$F$13*V22*$E12*$E40*($M40+1)^(V$20)*((1+$J40)^(V$20))) -> 0 | W40: =IF(AND($E40=1,$E12=0),'Allgemeine Unternehmensdaten'!$F$13*W$22*$H12*($M40+1)^(W$20)*((1+$J40)^(W$20)),'Allgemeine Unternehmensdaten'!$F$13*W22*$E12*$E40*($M40+1)^(W$20)*((1+$J40)^(W$20))) -> 0 | X40: =IF(AND($E40=1,$E12=0),'Allgemeine Unternehmensdaten'!$F$13*X$22*$H12*($M40+1)^(X$20)*((1+$J40)^(X$20)),'Allgemeine Unternehmensdaten'!$F$13*X22*$E12*$E40*($M40+1)^(X$20)*((1+$J40)^(X$20))) -> 0 | Y40: =IF(AND($E40=1,$E12=0),'Allgemeine Unternehmensdaten'!$F$13*Y$22*$H12*($M40+1)^(Y$20)*((1+$J40)^(Y$20)),'Allgemeine Unternehmensdaten'!$F$13*Y22*$E12*$E40*($M40+1)^(Y$20)*((1+$J40)^(Y$20))) -> 0 | Z40: =IF(AND($E40=1,$E12=0),'Allgemeine Unternehmensdaten'!$F$13*Z$22*$H12*($M40+1)^(Z$20)*((1+$J40)^(Z$20)),'Allgemeine Unternehmensdaten'!$F$13*Z22*$E12*$E40*($M40+1)^(Z$20)*((1+$J40)^(Z$20))) -> 0 | ... BT40: =IF(AND($E40=1,$E12=0),'Allgemeine Unternehmensdaten'!$F$13*BT$22*$H12*($M40+1)^(BT$20)*((1+$J40)^(BT$20)),'Allgemeine Unternehmensdaten'!$F$13*BT22*$E12*$E40*($M40+1)^(BT$20)*((1+$J40)^(BT$20))) -> 0 | BV40: =C40 -> Mehrverbrauch Gas in % | BW40: =IF(AND($D40=1,$D12=0),'Allgemeine Unternehmensdaten'!$E$13*BW$22*$G12*($L40+1)^(BW$20)*((1+$I40)^(BW$20)),'Allgemeine Unternehmensdaten'!$E$13*BW22*$D12*$D40*($L40+1)^(BW$20)*((1+$I40)^(BW$20))) -> 0 | BX40: =IF(AND($D40=1,$D12=0),'Allgemeine Unternehmensdaten'!$E$13*BX$22*$G12*($L40+1)^(BX$20)*((1+$I40)^(BX$20)),'Allgemeine Unternehmensdaten'!$E$13*BX22*$D12*$D40*($L40+1)^(BX$20)*((1+$I40)^(BX$20))) -> 0 | BY40: =IF(AND($D40=1,$D12=0),'Allgemeine Unternehmensdaten'!$E$13*BY$22*$G12*($L40+1)^(BY$20)*((1+$I40)^(BY$20)),'Allgemeine Unternehmensdaten'!$E$13*BY22*$D12*$D40*($L40+1)^(BY$20)*((1+$I40)^(BY$20))) -> 0 | BZ40: =IF(AND($D40=1,$D12=0),'Allgemeine Unternehmensdaten'!$E$13*BZ$22*$G12*($L40+1)^(BZ$20)*((1+$I40)^(BZ$20)),'Allgemeine Unternehmensdaten'!$E$13*BZ22*$D12*$D40*($L40+1)^(BZ$20)*((1+$I40)^(BZ$20))) -> 0 | CA40: =IF(AND($D40=1,$D12=0),'Allgemeine Unternehmensdaten'!$E$13*CA$22*$G12*($L40+1)^(CA$20)*((1+$I40)^(CA$20)),'Allgemeine Unternehmensdaten'!$E$13*CA22*$D12*$D40*($L40+1)^(CA$20)*((1+$I40)^(CA$20))) -> 0 | CB40: =IF(AND($D40=1,$D12=0),'Allgemeine Unternehmensdaten'!$E$13*CB$22*$G12*($L40+1)^(CB$20)*((1+$I40)^(CB$20)),'Allgemeine Unternehmensdaten'!$E$13*CB22*$D12*$D40*($L40+1)^(CB$20)*((1+$I40)^(CB$20))) -> 0 | CC40: =IF(AND($D40=1,$D12=0),'Allgemeine Unternehmensdaten'!$E$13*CC$22*$G12*($L40+1)^(CC$20)*((1+$I40)^(CC$20)),'Allgemeine Unternehmensdaten'!$E$13*CC22*$D12*$D40*($L40+1)^(CC$20)*((1+$I40)^(CC$20))) -> 0 | CD40: =IF(AND($D40=1,$D12=0),'Allgemeine Unternehmensdaten'!$E$13*CD$22*$G12*($L40+1)^(CD$20)*((1+$I40)^(CD$20)),'Allgemeine Unternehmensdaten'!$E$13*CD22*$D12*$D40*($L40+1)^(CD$20)*((1+$I40)^(CD$20))) -> 0 | ... DX40: =IF(AND($D40=1,$D12=0),'Allgemeine Unternehmensdaten'!$E$13*DX$22*$G12*($L40+1)^(DX$20)*((1+$I40)^(DX$20)),'Allgemeine Unternehmensdaten'!$E$13*DX22*$D12*$D40*($L40+1)^(DX$20)*((1+$I40)^(DX$20))) -> 0 | DZ40: =C40 -> Mehrverbrauch Gas in % | EA40: =IF(AND($F40=1,$F12=0),'Allgemeine Unternehmensdaten'!$G$13*EA$22*$I12*($N40+1)^(EA$20)*((1+$K40)^(EA$20)),'Allgemeine Unternehmensdaten'!$G$13*EA22*$F12*$F40*($N40+1)^(EA$20)*((1+$K40)^(EA$20))) -> 0 | EB40: =IF(AND($F40=1,$F12=0),'Allgemeine Unternehmensdaten'!$G$13*EB$22*$I12*($N40+1)^(EB$20)*((1+$K40)^(EB$20)),'Allgemeine Unternehmensdaten'!$G$13*EB22*$F12*$F40*($N40+1)^(EB$20)*((1+$K40)^(EB$20))) -> 0 | EC40: =IF(AND($F40=1,$F12=0),'Allgemeine Unternehmensdaten'!$G$13*EC$22*$I12*($N40+1)^(EC$20)*((1+$K40)^(EC$20)),'Allgemeine Unternehmensdaten'!$G$13*EC22*$F12*$F40*($N40+1)^(EC$20)*((1+$K40)^(EC$20))) -> 0 | ED40: =IF(AND($F40=1,$F12=0),'Allgemeine Unternehmensdaten'!$G$13*ED$22*$I12*($N40+1)^(ED$20)*((1+$K40)^(ED$20)),'Allgemeine Unternehmensdaten'!$G$13*ED22*$F12*$F40*($N40+1)^(ED$20)*((1+$K40)^(ED$20))) -> 0 | EE40: =IF(AND($F40=1,$F12=0),'Allgemeine Unternehmensdaten'!$G$13*EE$22*$I12*($N40+1)^(EE$20)*((1+$K40)^(EE$20)),'Allgemeine Unternehmensdaten'!$G$13*EE22*$F12*$F40*($N40+1)^(EE$20)*((1+$K40)^(EE$20))) -> 0 | EF40: =IF(AND($F40=1,$F12=0),'Allgemeine Unternehmensdaten'!$G$13*EF$22*$I12*($N40+1)^(EF$20)*((1+$K40)^(EF$20)),'Allgemeine Unternehmensdaten'!$G$13*EF22*$F12*$F40*($N40+1)^(EF$20)*((1+$K40)^(EF$20))) -> 0 | EG40: =IF(AND($F40=1,$F12=0),'Allgemeine Unternehmensdaten'!$G$13*EG$22*$I12*($N40+1)^(EG$20)*((1+$K40)^(EG$20)),'Allgemeine Unternehmensdaten'!$G$13*EG22*$F12*$F40*($N40+1)^(EG$20)*((1+$K40)^(EG$20))) -> 0 | EH40: =IF(AND($F40=1,$F12=0),'Allgemeine Unternehmensdaten'!$G$13*EH$22*$I12*($N40+1)^(EH$20)*((1+$K40)^(EH$20)),'Allgemeine Unternehmensdaten'!$G$13*EH22*$F12*$F40*($N40+1)^(EH$20)*((1+$K40)^(EH$20))) -> 0 | ... GB40: =IF(AND($F40=1,$F12=0),'Allgemeine Unternehmensdaten'!$G$13*GB$22*$I12*($N40+1)^(GB$20)*((1+$K40)^(GB$20)),'Allgemeine Unternehmensdaten'!$G$13*GB22*$F12*$F40*($N40+1)^(GB$20)*((1+$K40)^(GB$20))) -> 0
C41: ="Mehrverbrauch "&'Allgemeine Unternehmensdaten'!C30&" in %" -> Mehrverbrauch Flexibler Kostenfaktor in % | D41: {=IFERROR(_xlfn.IFS(D13>=G13,0,D13=0,1),(G13-D13)/D13)} -> 0 | E41: {=IFERROR(_xlfn.IFS(E13>=H13,0,E13=0,1),(H13-E13)/E13)} -> 0 | F41: {=IFERROR(_xlfn.IFS(F13>=I13,0,F13=0,1),(I13-F13)/F13)} -> 0 | G41: 99 | H41: 99 | I41: 0 | J41: 0 | K41: 0 | L41: ='Allgemeine Unternehmensdaten'!$E$8 -> 0.04 | M41: =$E$7 -> 0.03 | N41: =$F$7 -> 0.05 | R41: =C41 -> Mehrverbrauch Flexibler Kostenfaktor in % | S41: =IF(AND($E41=1,$E13=0),'Allgemeine Unternehmensdaten'!$E$30*S$22*$H13*($M41+1)^(S20)*((1+$J41)^(S$20)),'Allgemeine Unternehmensdaten'!$E$30*S22*$E13*$E41*($M41+1)^(S20)*((1+$J41)^(S$20))) -> 0 | T41: =IF(AND($E41=1,$E13=0),'Allgemeine Unternehmensdaten'!$E$30*T$22*$H13*($M41+1)^(T20)*((1+$J41)^(T$20)),'Allgemeine Unternehmensdaten'!$E$30*T22*$E13*$E41*($M41+1)^(T20)*((1+$J41)^(T$20))) -> 0 | U41: =IF(AND($E41=1,$E13=0),'Allgemeine Unternehmensdaten'!$E$30*U$22*$H13*($M41+1)^(U20)*((1+$J41)^(U$20)),'Allgemeine Unternehmensdaten'!$E$30*U22*$E13*$E41*($M41+1)^(U20)*((1+$J41)^(U$20))) -> 0 | V41: =IF(AND($E41=1,$E13=0),'Allgemeine Unternehmensdaten'!$E$30*V$22*$H13*($M41+1)^(V20)*((1+$J41)^(V$20)),'Allgemeine Unternehmensdaten'!$E$30*V22*$E13*$E41*($M41+1)^(V20)*((1+$J41)^(V$20))) -> 0 | W41: =IF(AND($E41=1,$E13=0),'Allgemeine Unternehmensdaten'!$E$30*W$22*$H13*($M41+1)^(W20)*((1+$J41)^(W$20)),'Allgemeine Unternehmensdaten'!$E$30*W22*$E13*$E41*($M41+1)^(W20)*((1+$J41)^(W$20))) -> 0 | X41: =IF(AND($E41=1,$E13=0),'Allgemeine Unternehmensdaten'!$E$30*X$22*$H13*($M41+1)^(X20)*((1+$J41)^(X$20)),'Allgemeine Unternehmensdaten'!$E$30*X22*$E13*$E41*($M41+1)^(X20)*((1+$J41)^(X$20))) -> 0 | Y41: =IF(AND($E41=1,$E13=0),'Allgemeine Unternehmensdaten'!$E$30*Y$22*$H13*($M41+1)^(Y20)*((1+$J41)^(Y$20)),'Allgemeine Unternehmensdaten'!$E$30*Y22*$E13*$E41*($M41+1)^(Y20)*((1+$J41)^(Y$20))) -> 0 | Z41: =IF(AND($E41=1,$E13=0),'Allgemeine Unternehmensdaten'!$E$30*Z$22*$H13*($M41+1)^(Z20)*((1+$J41)^(Z$20)),'Allgemeine Unternehmensdaten'!$E$30*Z22*$E13*$E41*($M41+1)^(Z20)*((1+$J41)^(Z$20))) -> 0 | ... BT41: =IF(AND($E41=1,$E13=0),'Allgemeine Unternehmensdaten'!$E$30*BT$22*$H13*($M41+1)^(BT20)*((1+$J41)^(BT$20)),'Allgemeine Unternehmensdaten'!$E$30*BT22*$E13*$E41*($M41+1)^(BT20)*((1+$J41)^(BT$20))) -> 0 | BV41: =C41 -> Mehrverbrauch Flexibler Kostenfaktor in % | BW41: =IF(AND($D41=1,$D13=0),'Allgemeine Unternehmensdaten'!$E$30*BW$22*$G13*($L41+1)^(BW20)*((1+$I41)^(BW$20)),'Allgemeine Unternehmensdaten'!$E$30*BW22*$D13*$D41*($L41+1)^(BW20)*((1+$I41)^(BW$20))) -> 0 | BX41: =IF(AND($D41=1,$D13=0),'Allgemeine Unternehmensdaten'!$E$30*BX$22*$G13*($L41+1)^(BX20)*((1+$I41)^(BX$20)),'Allgemeine Unternehmensdaten'!$E$30*BX22*$D13*$D41*($L41+1)^(BX20)*((1+$I41)^(BX$20))) -> 0 | BY41: =IF(AND($D41=1,$D13=0),'Allgemeine Unternehmensdaten'!$E$30*BY$22*$G13*($L41+1)^(BY20)*((1+$I41)^(BY$20)),'Allgemeine Unternehmensdaten'!$E$30*BY22*$D13*$D41*($L41+1)^(BY20)*((1+$I41)^(BY$20))) -> 0 | BZ41: =IF(AND($D41=1,$D13=0),'Allgemeine Unternehmensdaten'!$E$30*BZ$22*$G13*($L41+1)^(BZ20)*((1+$I41)^(BZ$20)),'Allgemeine Unternehmensdaten'!$E$30*BZ22*$D13*$D41*($L41+1)^(BZ20)*((1+$I41)^(BZ$20))) -> 0 | CA41: =IF(AND($D41=1,$D13=0),'Allgemeine Unternehmensdaten'!$E$30*CA$22*$G13*($L41+1)^(CA20)*((1+$I41)^(CA$20)),'Allgemeine Unternehmensdaten'!$E$30*CA22*$D13*$D41*($L41+1)^(CA20)*((1+$I41)^(CA$20))) -> 0 | CB41: =IF(AND($D41=1,$D13=0),'Allgemeine Unternehmensdaten'!$E$30*CB$22*$G13*($L41+1)^(CB20)*((1+$I41)^(CB$20)),'Allgemeine Unternehmensdaten'!$E$30*CB22*$D13*$D41*($L41+1)^(CB20)*((1+$I41)^(CB$20))) -> 0 | CC41: =IF(AND($D41=1,$D13=0),'Allgemeine Unternehmensdaten'!$E$30*CC$22*$G13*($L41+1)^(CC20)*((1+$I41)^(CC$20)),'Allgemeine Unternehmensdaten'!$E$30*CC22*$D13*$D41*($L41+1)^(CC20)*((1+$I41)^(CC$20))) -> 0 | CD41: =IF(AND($D41=1,$D13=0),'Allgemeine Unternehmensdaten'!$E$30*CD$22*$G13*($L41+1)^(CD20)*((1+$I41)^(CD$20)),'Allgemeine Unternehmensdaten'!$E$30*CD22*$D13*$D41*($L41+1)^(CD20)*((1+$I41)^(CD$20))) -> 0 | ... DX41: =IF(AND($D41=1,$D13=0),'Allgemeine Unternehmensdaten'!$E$30*DX$22*$G13*($L41+1)^(DX20)*((1+$I41)^(DX$20)),'Allgemeine Unternehmensdaten'!$E$30*DX22*$D13*$D41*($L41+1)^(DX20)*((1+$I41)^(DX$20))) -> 0 | DZ41: =C41 -> Mehrverbrauch Flexibler Kostenfaktor in % | EA41: =IF(AND($F41=1,$F13=0),'Allgemeine Unternehmensdaten'!$E$30*EA$22*$I13*($N41+1)^(EA20)*((1+$K41)^(EA$20)),'Allgemeine Unternehmensdaten'!$E$30*EA22*$F13*$F41*($N41+1)^(EA20)*((1+$K41)^(EA$20))) -> 0 | EB41: =IF(AND($F41=1,$F13=0),'Allgemeine Unternehmensdaten'!$E$30*EB$22*$I13*($N41+1)^(EB20)*((1+$K41)^(EB$20)),'Allgemeine Unternehmensdaten'!$E$30*EB22*$F13*$F41*($N41+1)^(EB20)*((1+$K41)^(EB$20))) -> 0 | EC41: =IF(AND($F41=1,$F13=0),'Allgemeine Unternehmensdaten'!$E$30*EC$22*$I13*($N41+1)^(EC20)*((1+$K41)^(EC$20)),'Allgemeine Unternehmensdaten'!$E$30*EC22*$F13*$F41*($N41+1)^(EC20)*((1+$K41)^(EC$20))) -> 0 | ED41: =IF(AND($F41=1,$F13=0),'Allgemeine Unternehmensdaten'!$E$30*ED$22*$I13*($N41+1)^(ED20)*((1+$K41)^(ED$20)),'Allgemeine Unternehmensdaten'!$E$30*ED22*$F13*$F41*($N41+1)^(ED20)*((1+$K41)^(ED$20))) -> 0 | EE41: =IF(AND($F41=1,$F13=0),'Allgemeine Unternehmensdaten'!$E$30*EE$22*$I13*($N41+1)^(EE20)*((1+$K41)^(EE$20)),'Allgemeine Unternehmensdaten'!$E$30*EE22*$F13*$F41*($N41+1)^(EE20)*((1+$K41)^(EE$20))) -> 0 | EF41: =IF(AND($F41=1,$F13=0),'Allgemeine Unternehmensdaten'!$E$30*EF$22*$I13*($N41+1)^(EF20)*((1+$K41)^(EF$20)),'Allgemeine Unternehmensdaten'!$E$30*EF22*$F13*$F41*($N41+1)^(EF20)*((1+$K41)^(EF$20))) -> 0 | EG41: =IF(AND($F41=1,$F13=0),'Allgemeine Unternehmensdaten'!$E$30*EG$22*$I13*($N41+1)^(EG20)*((1+$K41)^(EG$20)),'Allgemeine Unternehmensdaten'!$E$30*EG22*$F13*$F41*($N41+1)^(EG20)*((1+$K41)^(EG$20))) -> 0 | EH41: =IF(AND($F41=1,$F13=0),'Allgemeine Unternehmensdaten'!$E$30*EH$22*$I13*($N41+1)^(EH20)*((1+$K41)^(EH$20)),'Allgemeine Unternehmensdaten'!$E$30*EH22*$F13*$F41*($N41+1)^(EH20)*((1+$K41)^(EH$20))) -> 0 | ... GB41: =IF(AND($F41=1,$F13=0),'Allgemeine Unternehmensdaten'!$E$30*GB$22*$I13*($N41+1)^(GB20)*((1+$K41)^(GB$20)),'Allgemeine Unternehmensdaten'!$E$30*GB22*$F13*$F41*($N41+1)^(GB20)*((1+$K41)^(GB$20))) -> 0
C42: Entsorgungskosten in € | G42: 99 | H42: 99 | I42: 0 | J42: 0 | K42: 0 | L42: =$D$7 -> 0.02 | M42: =$E$7 -> 0.03 | N42: =$F$7 -> 0.05 | R42: =C42 -> Entsorgungskosten in € | S42: =IF(S21+T21=1,$E$42*(1+$M$42)^(S20)*((1+$J42)^(S$20)),0) -> 0 | T42: =IF(T21+U21=1,$E$42*(1+$M$42)^(T20)*((1+$J42)^(T$20)),0) -> 0 | U42: =IF(U21+V21=1,$E$42*(1+$M$42)^(U20)*((1+$J42)^(U$20)),0) -> 0 | V42: =IF(V21+W21=1,$E$42*(1+$M$42)^(V20)*((1+$J42)^(V$20)),0) -> 0 | W42: =IF(W21+X21=1,$E$42*(1+$M$42)^(W20)*((1+$J42)^(W$20)),0) -> 0 | X42: =IF(X21+Y21=1,$E$42*(1+$M$42)^(X20)*((1+$J42)^(X$20)),0) -> 0 | Y42: =IF(Y21+Z21=1,$E$42*(1+$M$42)^(Y20)*((1+$J42)^(Y$20)),0) -> 0 | Z42: =IF(Z21+AA21=1,$E$42*(1+$M$42)^(Z20)*((1+$J42)^(Z$20)),0) -> 0 | ... BT42: =IF(BT21+BU21=1,$E$42*(1+$M$42)^(BT20)*((1+$J42)^(BT$20)),0) -> 0 | BV42: =C42 -> Entsorgungskosten in € | BW42: =IF(BW21+BX21=1,$D$42*(1+$L$42)^(BW20)*((1+$I42)^(BW$20)),0) -> 0 | BX42: =IF(BX21+BY21=1,$D$42*(1+$L$42)^(BX20)*((1+$I42)^(BX$20)),0) -> 0 | BY42: =IF(BY21+BZ21=1,$D$42*(1+$L$42)^(BY20)*((1+$I42)^(BY$20)),0) -> 0 | BZ42: =IF(BZ21+CA21=1,$D$42*(1+$L$42)^(BZ20)*((1+$I42)^(BZ$20)),0) -> 0 | CA42: =IF(CA21+CB21=1,$D$42*(1+$L$42)^(CA20)*((1+$I42)^(CA$20)),0) -> 0 | CB42: =IF(CB21+CC21=1,$D$42*(1+$L$42)^(CB20)*((1+$I42)^(CB$20)),0) -> 0 | CC42: =IF(CC21+CD21=1,$D$42*(1+$L$42)^(CC20)*((1+$I42)^(CC$20)),0) -> 0 | CD42: =IF(CD21+CE21=1,$D$42*(1+$L$42)^(CD20)*((1+$I42)^(CD$20)),0) -> 0 | ... DX42: =IF(DX21+DY21=1,$D$42*(1+$L$42)^(DX20)*((1+$I42)^(DX$20)),0) -> 0 | DZ42: =C42 -> Entsorgungskosten in € | EA42: =IF(EA21+EB21=1,$F$42*(1+$N$42)^(EA20)*((1+$K42)^(EA$20)),0) -> 0 | EB42: =IF(EB21+EC21=1,$F$42*(1+$N$42)^(EB20)*((1+$K42)^(EB$20)),0) -> 0 | EC42: =IF(EC21+ED21=1,$F$42*(1+$N$42)^(EC20)*((1+$K42)^(EC$20)),0) -> 0 | ED42: =IF(ED21+EE21=1,$F$42*(1+$N$42)^(ED20)*((1+$K42)^(ED$20)),0) -> 0 | EE42: =IF(EE21+EF21=1,$F$42*(1+$N$42)^(EE20)*((1+$K42)^(EE$20)),0) -> 0 | EF42: =IF(EF21+EG21=1,$F$42*(1+$N$42)^(EF20)*((1+$K42)^(EF$20)),0) -> 0 | EG42: =IF(EG21+EH21=1,$F$42*(1+$N$42)^(EG20)*((1+$K42)^(EG$20)),0) -> 0 | EH42: =IF(EH21+EI21=1,$F$42*(1+$N$42)^(EH20)*((1+$K42)^(EH$20)),0) -> 0 | ... GB42: =IF(GB21+GC21=1,$F$42*(1+$N$42)^(GB20)*((1+$K42)^(GB$20)),0) -> 0
C43: Jahresbetriebskosten in €/Jahr | G43: 99 | H43: 99 | I43: 0 | J43: 0 | K43: 0 | L43: =$D$7 -> 0.02 | M43: =$E$7 -> 0.03 | N43: =$F$7 -> 0.05 | R43: =C43 -> Jahresbetriebskosten in €/Jahr | S43: =IF(AND($G43=99,$H43=99),S$22*$E43*(1+$M43)^(S$20)*((1+$J43)^(S$20)),IF(AND($H43=99,S$20>=$G43,S$20<=$E$20),$E43*(1+$M43)^(S$20)*((1+$J43)^(S$20)),IF(AND($G43=99,S$20<=$H43,S$20>=$E$18),$E43*(1+$M43)^(S$20)*((1+$J43)^(S$20)),IF(AND(S$20<=$H43,S$20>=$G43,$G43<>99,$H43<>99),$E43*(1+$M43)^(S$20)*((1+$J43)^(S$20)),0)))) -> 0 | T43: =IF(AND($G43=99,$H43=99),T$22*$E43*(1+$M43)^(T$20)*((1+$J43)^(T$20)),IF(AND($H43=99,T$20>=$G43,T$20<=$E$20),$E43*(1+$M43)^(T$20)*((1+$J43)^(T$20)),IF(AND($G43=99,T$20<=$H43,T$20>=$E$18),$E43*(1+$M43)^(T$20)*((1+$J43)^(T$20)),IF(AND(T$20<=$H43,T$20>=$G43,$G43<>99,$H43<>99),$E43*(1+$M43)^(T$20)*((1+$J43)^(T$20)),0)))) -> 0 | U43: =IF(AND($G43=99,$H43=99),U$22*$E43*(1+$M43)^(U$20)*((1+$J43)^(U$20)),IF(AND($H43=99,U$20>=$G43,U$20<=$E$20),$E43*(1+$M43)^(U$20)*((1+$J43)^(U$20)),IF(AND($G43=99,U$20<=$H43,U$20>=$E$18),$E43*(1+$M43)^(U$20)*((1+$J43)^(U$20)),IF(AND(U$20<=$H43,U$20>=$G43,$G43<>99,$H43<>99),$E43*(1+$M43)^(U$20)*((1+$J43)^(U$20)),0)))) -> 0 | V43: =IF(AND($G43=99,$H43=99),V$22*$E43*(1+$M43)^(V$20)*((1+$J43)^(V$20)),IF(AND($H43=99,V$20>=$G43,V$20<=$E$20),$E43*(1+$M43)^(V$20)*((1+$J43)^(V$20)),IF(AND($G43=99,V$20<=$H43,V$20>=$E$18),$E43*(1+$M43)^(V$20)*((1+$J43)^(V$20)),IF(AND(V$20<=$H43,V$20>=$G43,$G43<>99,$H43<>99),$E43*(1+$M43)^(V$20)*((1+$J43)^(V$20)),0)))) -> 0 | W43: =IF(AND($G43=99,$H43=99),W$22*$E43*(1+$M43)^(W$20)*((1+$J43)^(W$20)),IF(AND($H43=99,W$20>=$G43,W$20<=$E$20),$E43*(1+$M43)^(W$20)*((1+$J43)^(W$20)),IF(AND($G43=99,W$20<=$H43,W$20>=$E$18),$E43*(1+$M43)^(W$20)*((1+$J43)^(W$20)),IF(AND(W$20<=$H43,W$20>=$G43,$G43<>99,$H43<>99),$E43*(1+$M43)^(W$20)*((1+$J43)^(W$20)),0)))) -> 0 | X43: =IF(AND($G43=99,$H43=99),X$22*$E43*(1+$M43)^(X$20)*((1+$J43)^(X$20)),IF(AND($H43=99,X$20>=$G43,X$20<=$E$20),$E43*(1+$M43)^(X$20)*((1+$J43)^(X$20)),IF(AND($G43=99,X$20<=$H43,X$20>=$E$18),$E43*(1+$M43)^(X$20)*((1+$J43)^(X$20)),IF(AND(X$20<=$H43,X$20>=$G43,$G43<>99,$H43<>99),$E43*(1+$M43)^(X$20)*((1+$J43)^(X$20)),0)))) -> 0 | Y43: =IF(AND($G43=99,$H43=99),Y$22*$E43*(1+$M43)^(Y$20)*((1+$J43)^(Y$20)),IF(AND($H43=99,Y$20>=$G43,Y$20<=$E$20),$E43*(1+$M43)^(Y$20)*((1+$J43)^(Y$20)),IF(AND($G43=99,Y$20<=$H43,Y$20>=$E$18),$E43*(1+$M43)^(Y$20)*((1+$J43)^(Y$20)),IF(AND(Y$20<=$H43,Y$20>=$G43,$G43<>99,$H43<>99),$E43*(1+$M43)^(Y$20)*((1+$J43)^(Y$20)),0)))) -> 0 | Z43: =IF(AND($G43=99,$H43=99),Z$22*$E43*(1+$M43)^(Z$20)*((1+$J43)^(Z$20)),IF(AND($H43=99,Z$20>=$G43,Z$20<=$E$20),$E43*(1+$M43)^(Z$20)*((1+$J43)^(Z$20)),IF(AND($G43=99,Z$20<=$H43,Z$20>=$E$18),$E43*(1+$M43)^(Z$20)*((1+$J43)^(Z$20)),IF(AND(Z$20<=$H43,Z$20>=$G43,$G43<>99,$H43<>99),$E43*(1+$M43)^(Z$20)*((1+$J43)^(Z$20)),0)))) -> 0 | ... BT43: =IF(AND($G43=99,$H43=99),BT$22*$E43*(1+$M43)^(BT$20)*((1+$J43)^(BT$20)),IF(AND($H43=99,BT$20>=$G43,BT$20<=$E$20),$E43*(1+$M43)^(BT$20)*((1+$J43)^(BT$20)),IF(AND($G43=99,BT$20<=$H43,BT$20>=$E$18),$E43*(1+$M43)^(BT$20)*((1+$J43)^(BT$20)),IF(AND(BT$20<=$H43,BT$20>=$G43,$G43<>99,$H43<>99),$E43*(1+$M43)^(BT$20)*((1+$J43)^(BT$20)),0)))) -> 0 | BV43: =C43 -> Jahresbetriebskosten in €/Jahr | BW43: =IF(AND($G43=99,$H43=99),BW$22*$D43*(1+$L43)^(BW$20)*((1+$I43)^(BW$20)),IF(AND($H43=99,BW$20>=$G43,BW$20<=$D$20),$D43*(1+$L43)^(BW$20)*((1+$I43)^(BW$20)),IF(AND($G43=99,BW$20<=$H43,BW$20>=$D$18),$D43*(1+$L43)^(BW$20)*((1+$I43)^(BW$20)),IF(AND(BW$20<=$H43,BW$20>=$G43,$G43<>99,$H43<>99),$D43*(1+$L43)^(BW$20)*((1+$I43)^(BW$20)),0)))) -> 0 | BX43: =IF(AND($G43=99,$H43=99),BX$22*$D43*(1+$L43)^(BX$20)*((1+$I43)^(BX$20)),IF(AND($H43=99,BX$20>=$G43,BX$20<=$D$20),$D43*(1+$L43)^(BX$20)*((1+$I43)^(BX$20)),IF(AND($G43=99,BX$20<=$H43,BX$20>=$D$18),$D43*(1+$L43)^(BX$20)*((1+$I43)^(BX$20)),IF(AND(BX$20<=$H43,BX$20>=$G43,$G43<>99,$H43<>99),$D43*(1+$L43)^(BX$20)*((1+$I43)^(BX$20)),0)))) -> 0 | BY43: =IF(AND($G43=99,$H43=99),BY$22*$D43*(1+$L43)^(BY$20)*((1+$I43)^(BY$20)),IF(AND($H43=99,BY$20>=$G43,BY$20<=$D$20),$D43*(1+$L43)^(BY$20)*((1+$I43)^(BY$20)),IF(AND($G43=99,BY$20<=$H43,BY$20>=$D$18),$D43*(1+$L43)^(BY$20)*((1+$I43)^(BY$20)),IF(AND(BY$20<=$H43,BY$20>=$G43,$G43<>99,$H43<>99),$D43*(1+$L43)^(BY$20)*((1+$I43)^(BY$20)),0)))) -> 0 | BZ43: =IF(AND($G43=99,$H43=99),BZ$22*$D43*(1+$L43)^(BZ$20)*((1+$I43)^(BZ$20)),IF(AND($H43=99,BZ$20>=$G43,BZ$20<=$D$20),$D43*(1+$L43)^(BZ$20)*((1+$I43)^(BZ$20)),IF(AND($G43=99,BZ$20<=$H43,BZ$20>=$D$18),$D43*(1+$L43)^(BZ$20)*((1+$I43)^(BZ$20)),IF(AND(BZ$20<=$H43,BZ$20>=$G43,$G43<>99,$H43<>99),$D43*(1+$L43)^(BZ$20)*((1+$I43)^(BZ$20)),0)))) -> 0 | CA43: =IF(AND($G43=99,$H43=99),CA$22*$D43*(1+$L43)^(CA$20)*((1+$I43)^(CA$20)),IF(AND($H43=99,CA$20>=$G43,CA$20<=$D$20),$D43*(1+$L43)^(CA$20)*((1+$I43)^(CA$20)),IF(AND($G43=99,CA$20<=$H43,CA$20>=$D$18),$D43*(1+$L43)^(CA$20)*((1+$I43)^(CA$20)),IF(AND(CA$20<=$H43,CA$20>=$G43,$G43<>99,$H43<>99),$D43*(1+$L43)^(CA$20)*((1+$I43)^(CA$20)),0)))) -> 0 | CB43: =IF(AND($G43=99,$H43=99),CB$22*$D43*(1+$L43)^(CB$20)*((1+$I43)^(CB$20)),IF(AND($H43=99,CB$20>=$G43,CB$20<=$D$20),$D43*(1+$L43)^(CB$20)*((1+$I43)^(CB$20)),IF(AND($G43=99,CB$20<=$H43,CB$20>=$D$18),$D43*(1+$L43)^(CB$20)*((1+$I43)^(CB$20)),IF(AND(CB$20<=$H43,CB$20>=$G43,$G43<>99,$H43<>99),$D43*(1+$L43)^(CB$20)*((1+$I43)^(CB$20)),0)))) -> 0 | CC43: =IF(AND($G43=99,$H43=99),CC$22*$D43*(1+$L43)^(CC$20)*((1+$I43)^(CC$20)),IF(AND($H43=99,CC$20>=$G43,CC$20<=$D$20),$D43*(1+$L43)^(CC$20)*((1+$I43)^(CC$20)),IF(AND($G43=99,CC$20<=$H43,CC$20>=$D$18),$D43*(1+$L43)^(CC$20)*((1+$I43)^(CC$20)),IF(AND(CC$20<=$H43,CC$20>=$G43,$G43<>99,$H43<>99),$D43*(1+$L43)^(CC$20)*((1+$I43)^(CC$20)),0)))) -> 0 | CD43: =IF(AND($G43=99,$H43=99),CD$22*$D43*(1+$L43)^(CD$20)*((1+$I43)^(CD$20)),IF(AND($H43=99,CD$20>=$G43,CD$20<=$D$20),$D43*(1+$L43)^(CD$20)*((1+$I43)^(CD$20)),IF(AND($G43=99,CD$20<=$H43,CD$20>=$D$18),$D43*(1+$L43)^(CD$20)*((1+$I43)^(CD$20)),IF(AND(CD$20<=$H43,CD$20>=$G43,$G43<>99,$H43<>99),$D43*(1+$L43)^(CD$20)*((1+$I43)^(CD$20)),0)))) -> 0 | ... DX43: =IF(AND($G43=99,$H43=99),DX$22*$D43*(1+$L43)^(DX$20)*((1+$I43)^(DX$20)),IF(AND($H43=99,DX$20>=$G43,DX$20<=$D$20),$D43*(1+$L43)^(DX$20)*((1+$I43)^(DX$20)),IF(AND($G43=99,DX$20<=$H43,DX$20>=$D$18),$D43*(1+$L43)^(DX$20)*((1+$I43)^(DX$20)),IF(AND(DX$20<=$H43,DX$20>=$G43,$G43<>99,$H43<>99),$D43*(1+$L43)^(DX$20)*((1+$I43)^(DX$20)),0)))) -> 0 | DZ43: =C43 -> Jahresbetriebskosten in €/Jahr | EA43: =IF(AND($G43=99,$H43=99),EA$22*$F43*(1+$N43)^(EA$20)*((1+$K43)^(EA$20)),IF(AND($H43=99,EA$20>=$G43,EA$20<=$F$20),$F43*(1+$N43)^(EA$20)*((1+$K43)^(EA$20)),IF(AND($G43=99,EA$20<=$H43,EA$20>=$F$18),$F43*(1+$N43)^(EA$20)*((1+$K43)^(EA$20)),IF(AND(EA$20<=$H43,EA$20>=$G43,$G43<>99,$H43<>99),$F43*(1+$N43)^(EA$20)*((1+$K43)^(EA$20)),0)))) -> 0 | EB43: =IF(AND($G43=99,$H43=99),EB$22*$F43*(1+$N43)^(EB$20)*((1+$K43)^(EB$20)),IF(AND($H43=99,EB$20>=$G43,EB$20<=$F$20),$F43*(1+$N43)^(EB$20)*((1+$K43)^(EB$20)),IF(AND($G43=99,EB$20<=$H43,EB$20>=$F$18),$F43*(1+$N43)^(EB$20)*((1+$K43)^(EB$20)),IF(AND(EB$20<=$H43,EB$20>=$G43,$G43<>99,$H43<>99),$F43*(1+$N43)^(EB$20)*((1+$K43)^(EB$20)),0)))) -> 0 | EC43: =IF(AND($G43=99,$H43=99),EC$22*$F43*(1+$N43)^(EC$20)*((1+$K43)^(EC$20)),IF(AND($H43=99,EC$20>=$G43,EC$20<=$F$20),$F43*(1+$N43)^(EC$20)*((1+$K43)^(EC$20)),IF(AND($G43=99,EC$20<=$H43,EC$20>=$F$18),$F43*(1+$N43)^(EC$20)*((1+$K43)^(EC$20)),IF(AND(EC$20<=$H43,EC$20>=$G43,$G43<>99,$H43<>99),$F43*(1+$N43)^(EC$20)*((1+$K43)^(EC$20)),0)))) -> 0 | ED43: =IF(AND($G43=99,$H43=99),ED$22*$F43*(1+$N43)^(ED$20)*((1+$K43)^(ED$20)),IF(AND($H43=99,ED$20>=$G43,ED$20<=$F$20),$F43*(1+$N43)^(ED$20)*((1+$K43)^(ED$20)),IF(AND($G43=99,ED$20<=$H43,ED$20>=$F$18),$F43*(1+$N43)^(ED$20)*((1+$K43)^(ED$20)),IF(AND(ED$20<=$H43,ED$20>=$G43,$G43<>99,$H43<>99),$F43*(1+$N43)^(ED$20)*((1+$K43)^(ED$20)),0)))) -> 0 | EE43: =IF(AND($G43=99,$H43=99),EE$22*$F43*(1+$N43)^(EE$20)*((1+$K43)^(EE$20)),IF(AND($H43=99,EE$20>=$G43,EE$20<=$F$20),$F43*(1+$N43)^(EE$20)*((1+$K43)^(EE$20)),IF(AND($G43=99,EE$20<=$H43,EE$20>=$F$18),$F43*(1+$N43)^(EE$20)*((1+$K43)^(EE$20)),IF(AND(EE$20<=$H43,EE$20>=$G43,$G43<>99,$H43<>99),$F43*(1+$N43)^(EE$20)*((1+$K43)^(EE$20)),0)))) -> 0 | EF43: =IF(AND($G43=99,$H43=99),EF$22*$F43*(1+$N43)^(EF$20)*((1+$K43)^(EF$20)),IF(AND($H43=99,EF$20>=$G43,EF$20<=$F$20),$F43*(1+$N43)^(EF$20)*((1+$K43)^(EF$20)),IF(AND($G43=99,EF$20<=$H43,EF$20>=$F$18),$F43*(1+$N43)^(EF$20)*((1+$K43)^(EF$20)),IF(AND(EF$20<=$H43,EF$20>=$G43,$G43<>99,$H43<>99),$F43*(1+$N43)^(EF$20)*((1+$K43)^(EF$20)),0)))) -> 0 | EG43: =IF(AND($G43=99,$H43=99),EG$22*$F43*(1+$N43)^(EG$20)*((1+$K43)^(EG$20)),IF(AND($H43=99,EG$20>=$G43,EG$20<=$F$20),$F43*(1+$N43)^(EG$20)*((1+$K43)^(EG$20)),IF(AND($G43=99,EG$20<=$H43,EG$20>=$F$18),$F43*(1+$N43)^(EG$20)*((1+$K43)^(EG$20)),IF(AND(EG$20<=$H43,EG$20>=$G43,$G43<>99,$H43<>99),$F43*(1+$N43)^(EG$20)*((1+$K43)^(EG$20)),0)))) -> 0 | EH43: =IF(AND($G43=99,$H43=99),EH$22*$F43*(1+$N43)^(EH$20)*((1+$K43)^(EH$20)),IF(AND($H43=99,EH$20>=$G43,EH$20<=$F$20),$F43*(1+$N43)^(EH$20)*((1+$K43)^(EH$20)),IF(AND($G43=99,EH$20<=$H43,EH$20>=$F$18),$F43*(1+$N43)^(EH$20)*((1+$K43)^(EH$20)),IF(AND(EH$20<=$H43,EH$20>=$G43,$G43<>99,$H43<>99),$F43*(1+$N43)^(EH$20)*((1+$K43)^(EH$20)),0)))) -> 0 | ... GB43: =IF(AND($G43=99,$H43=99),GB$22*$F43*(1+$N43)^(GB$20)*((1+$K43)^(GB$20)),IF(AND($H43=99,GB$20>=$G43,GB$20<=$F$20),$F43*(1+$N43)^(GB$20)*((1+$K43)^(GB$20)),IF(AND($G43=99,GB$20<=$H43,GB$20>=$F$18),$F43*(1+$N43)^(GB$20)*((1+$K43)^(GB$20)),IF(AND(GB$20<=$H43,GB$20>=$G43,$G43<>99,$H43<>99),$F43*(1+$N43)^(GB$20)*((1+$K43)^(GB$20)),0)))) -> 0
C44: Investitionskosten Zeitpunkt t in € | D44: =E44*1.3 -> 6500 | E44: 5000 | F44: =E44*0.75 -> 3750 | G44: 0 | H44: 0 | I44: 0 | J44: 0 | K44: 0 | L44: =$D$7 -> 0.02 | M44: =$E$7 -> 0.03 | N44: =$F$7 -> 0.05 | R44: =C44 -> Investitionskosten Zeitpunkt t in € | S44: =IF(AND($G44=99,$H44=99),S$22*$E44*(1+$M44)^(S$20)*((1+$J44)^(S$20)),IF(AND($H44=99,S$20>=$G44,S$20<=$E$20),$E44*(1+$M44)^(S$20)*((1+$J44)^(S$20)),IF(AND($G44=99,S$20<=$H44,S$20>=$E$18),$E44*(1+$M44)^(S$20)*((1+$J44)^(S$20)),IF(AND(S$20<=$H44,S$20>=$G44,$G44<>99,$H44<>99),$E44*(1+$M44)^(S$20)*((1+$J44)^(S$20)),0)))) -> 5000 | T44: =IF(AND($G44=99,$H44=99),T$22*$E44*(1+$M44)^(T$20)*((1+$J44)^(T$20)),IF(AND($H44=99,T$20>=$G44,T$20<=$E$20),$E44*(1+$M44)^(T$20)*((1+$J44)^(T$20)),IF(AND($G44=99,T$20<=$H44,T$20>=$E$18),$E44*(1+$M44)^(T$20)*((1+$J44)^(T$20)),IF(AND(T$20<=$H44,T$20>=$G44,$G44<>99,$H44<>99),$E44*(1+$M44)^(T$20)*((1+$J44)^(T$20)),0)))) -> 0 | U44: =IF(AND($G44=99,$H44=99),U$22*$E44*(1+$M44)^(U$20)*((1+$J44)^(U$20)),IF(AND($H44=99,U$20>=$G44,U$20<=$E$20),$E44*(1+$M44)^(U$20)*((1+$J44)^(U$20)),IF(AND($G44=99,U$20<=$H44,U$20>=$E$18),$E44*(1+$M44)^(U$20)*((1+$J44)^(U$20)),IF(AND(U$20<=$H44,U$20>=$G44,$G44<>99,$H44<>99),$E44*(1+$M44)^(U$20)*((1+$J44)^(U$20)),0)))) -> 0 | V44: =IF(AND($G44=99,$H44=99),V$22*$E44*(1+$M44)^(V$20)*((1+$J44)^(V$20)),IF(AND($H44=99,V$20>=$G44,V$20<=$E$20),$E44*(1+$M44)^(V$20)*((1+$J44)^(V$20)),IF(AND($G44=99,V$20<=$H44,V$20>=$E$18),$E44*(1+$M44)^(V$20)*((1+$J44)^(V$20)),IF(AND(V$20<=$H44,V$20>=$G44,$G44<>99,$H44<>99),$E44*(1+$M44)^(V$20)*((1+$J44)^(V$20)),0)))) -> 0 | W44: =IF(AND($G44=99,$H44=99),W$22*$E44*(1+$M44)^(W$20)*((1+$J44)^(W$20)),IF(AND($H44=99,W$20>=$G44,W$20<=$E$20),$E44*(1+$M44)^(W$20)*((1+$J44)^(W$20)),IF(AND($G44=99,W$20<=$H44,W$20>=$E$18),$E44*(1+$M44)^(W$20)*((1+$J44)^(W$20)),IF(AND(W$20<=$H44,W$20>=$G44,$G44<>99,$H44<>99),$E44*(1+$M44)^(W$20)*((1+$J44)^(W$20)),0)))) -> 0 | X44: =IF(AND($G44=99,$H44=99),X$22*$E44*(1+$M44)^(X$20)*((1+$J44)^(X$20)),IF(AND($H44=99,X$20>=$G44,X$20<=$E$20),$E44*(1+$M44)^(X$20)*((1+$J44)^(X$20)),IF(AND($G44=99,X$20<=$H44,X$20>=$E$18),$E44*(1+$M44)^(X$20)*((1+$J44)^(X$20)),IF(AND(X$20<=$H44,X$20>=$G44,$G44<>99,$H44<>99),$E44*(1+$M44)^(X$20)*((1+$J44)^(X$20)),0)))) -> 0 | Y44: =IF(AND($G44=99,$H44=99),Y$22*$E44*(1+$M44)^(Y$20)*((1+$J44)^(Y$20)),IF(AND($H44=99,Y$20>=$G44,Y$20<=$E$20),$E44*(1+$M44)^(Y$20)*((1+$J44)^(Y$20)),IF(AND($G44=99,Y$20<=$H44,Y$20>=$E$18),$E44*(1+$M44)^(Y$20)*((1+$J44)^(Y$20)),IF(AND(Y$20<=$H44,Y$20>=$G44,$G44<>99,$H44<>99),$E44*(1+$M44)^(Y$20)*((1+$J44)^(Y$20)),0)))) -> 0 | Z44: =IF(AND($G44=99,$H44=99),Z$22*$E44*(1+$M44)^(Z$20)*((1+$J44)^(Z$20)),IF(AND($H44=99,Z$20>=$G44,Z$20<=$E$20),$E44*(1+$M44)^(Z$20)*((1+$J44)^(Z$20)),IF(AND($G44=99,Z$20<=$H44,Z$20>=$E$18),$E44*(1+$M44)^(Z$20)*((1+$J44)^(Z$20)),IF(AND(Z$20<=$H44,Z$20>=$G44,$G44<>99,$H44<>99),$E44*(1+$M44)^(Z$20)*((1+$J44)^(Z$20)),0)))) -> 0 | ... BT44: =IF(AND($G44=99,$H44=99),BT$22*$E44*(1+$M44)^(BT$20)*((1+$J44)^(BT$20)),IF(AND($H44=99,BT$20>=$G44,BT$20<=$E$20),$E44*(1+$M44)^(BT$20)*((1+$J44)^(BT$20)),IF(AND($G44=99,BT$20<=$H44,BT$20>=$E$18),$E44*(1+$M44)^(BT$20)*((1+$J44)^(BT$20)),IF(AND(BT$20<=$H44,BT$20>=$G44,$G44<>99,$H44<>99),$E44*(1+$M44)^(BT$20)*((1+$J44)^(BT$20)),0)))) -> 0 | BV44: =C44 -> Investitionskosten Zeitpunkt t in € | BW44: =IF(AND($G44=99,$H44=99),BW$22*$D44*(1+$L44)^(BW$20)*((1+$I44)^(BW$20)),IF(AND($H44=99,BW$20>=$G44,BW$20<=$D$20),$D44*(1+$L44)^(BW$20)*((1+$I44)^(BW$20)),IF(AND($G44=99,BW$20<=$H44,BW$20>=$D$18),$D44*(1+$L44)^(BW$20)*((1+$I44)^(BW$20)),IF(AND(BW$20<=$H44,BW$20>=$G44,$G44<>99,$H44<>99),$D44*(1+$L44)^(BW$20)*((1+$I44)^(BW$20)),0)))) -> 6500 | BX44: =IF(AND($G44=99,$H44=99),BX$22*$D44*(1+$L44)^(BX$20)*((1+$I44)^(BX$20)),IF(AND($H44=99,BX$20>=$G44,BX$20<=$D$20),$D44*(1+$L44)^(BX$20)*((1+$I44)^(BX$20)),IF(AND($G44=99,BX$20<=$H44,BX$20>=$D$18),$D44*(1+$L44)^(BX$20)*((1+$I44)^(BX$20)),IF(AND(BX$20<=$H44,BX$20>=$G44,$G44<>99,$H44<>99),$D44*(1+$L44)^(BX$20)*((1+$I44)^(BX$20)),0)))) -> 0 | BY44: =IF(AND($G44=99,$H44=99),BY$22*$D44*(1+$L44)^(BY$20)*((1+$I44)^(BY$20)),IF(AND($H44=99,BY$20>=$G44,BY$20<=$D$20),$D44*(1+$L44)^(BY$20)*((1+$I44)^(BY$20)),IF(AND($G44=99,BY$20<=$H44,BY$20>=$D$18),$D44*(1+$L44)^(BY$20)*((1+$I44)^(BY$20)),IF(AND(BY$20<=$H44,BY$20>=$G44,$G44<>99,$H44<>99),$D44*(1+$L44)^(BY$20)*((1+$I44)^(BY$20)),0)))) -> 0 | BZ44: =IF(AND($G44=99,$H44=99),BZ$22*$D44*(1+$L44)^(BZ$20)*((1+$I44)^(BZ$20)),IF(AND($H44=99,BZ$20>=$G44,BZ$20<=$D$20),$D44*(1+$L44)^(BZ$20)*((1+$I44)^(BZ$20)),IF(AND($G44=99,BZ$20<=$H44,BZ$20>=$D$18),$D44*(1+$L44)^(BZ$20)*((1+$I44)^(BZ$20)),IF(AND(BZ$20<=$H44,BZ$20>=$G44,$G44<>99,$H44<>99),$D44*(1+$L44)^(BZ$20)*((1+$I44)^(BZ$20)),0)))) -> 0 | CA44: =IF(AND($G44=99,$H44=99),CA$22*$D44*(1+$L44)^(CA$20)*((1+$I44)^(CA$20)),IF(AND($H44=99,CA$20>=$G44,CA$20<=$D$20),$D44*(1+$L44)^(CA$20)*((1+$I44)^(CA$20)),IF(AND($G44=99,CA$20<=$H44,CA$20>=$D$18),$D44*(1+$L44)^(CA$20)*((1+$I44)^(CA$20)),IF(AND(CA$20<=$H44,CA$20>=$G44,$G44<>99,$H44<>99),$D44*(1+$L44)^(CA$20)*((1+$I44)^(CA$20)),0)))) -> 0 | CB44: =IF(AND($G44=99,$H44=99),CB$22*$D44*(1+$L44)^(CB$20)*((1+$I44)^(CB$20)),IF(AND($H44=99,CB$20>=$G44,CB$20<=$D$20),$D44*(1+$L44)^(CB$20)*((1+$I44)^(CB$20)),IF(AND($G44=99,CB$20<=$H44,CB$20>=$D$18),$D44*(1+$L44)^(CB$20)*((1+$I44)^(CB$20)),IF(AND(CB$20<=$H44,CB$20>=$G44,$G44<>99,$H44<>99),$D44*(1+$L44)^(CB$20)*((1+$I44)^(CB$20)),0)))) -> 0 | CC44: =IF(AND($G44=99,$H44=99),CC$22*$D44*(1+$L44)^(CC$20)*((1+$I44)^(CC$20)),IF(AND($H44=99,CC$20>=$G44,CC$20<=$D$20),$D44*(1+$L44)^(CC$20)*((1+$I44)^(CC$20)),IF(AND($G44=99,CC$20<=$H44,CC$20>=$D$18),$D44*(1+$L44)^(CC$20)*((1+$I44)^(CC$20)),IF(AND(CC$20<=$H44,CC$20>=$G44,$G44<>99,$H44<>99),$D44*(1+$L44)^(CC$20)*((1+$I44)^(CC$20)),0)))) -> 0 | CD44: =IF(AND($G44=99,$H44=99),CD$22*$D44*(1+$L44)^(CD$20)*((1+$I44)^(CD$20)),IF(AND($H44=99,CD$20>=$G44,CD$20<=$D$20),$D44*(1+$L44)^(CD$20)*((1+$I44)^(CD$20)),IF(AND($G44=99,CD$20<=$H44,CD$20>=$D$18),$D44*(1+$L44)^(CD$20)*((1+$I44)^(CD$20)),IF(AND(CD$20<=$H44,CD$20>=$G44,$G44<>99,$H44<>99),$D44*(1+$L44)^(CD$20)*((1+$I44)^(CD$20)),0)))) -> 0 | ... DX44: =IF(AND($G44=99,$H44=99),DX$22*$D44*(1+$L44)^(DX$20)*((1+$I44)^(DX$20)),IF(AND($H44=99,DX$20>=$G44,DX$20<=$D$20),$D44*(1+$L44)^(DX$20)*((1+$I44)^(DX$20)),IF(AND($G44=99,DX$20<=$H44,DX$20>=$D$18),$D44*(1+$L44)^(DX$20)*((1+$I44)^(DX$20)),IF(AND(DX$20<=$H44,DX$20>=$G44,$G44<>99,$H44<>99),$D44*(1+$L44)^(DX$20)*((1+$I44)^(DX$20)),0)))) -> 0 | DZ44: =C44 -> Investitionskosten Zeitpunkt t in € | EA44: =IF(AND($G44=99,$H44=99),EA$22*$F44*(1+$N44)^(EA$20)*((1+$K44)^(EA$20)),IF(AND($H44=99,EA$20>=$G44,EA$20<=$F$20),$F44*(1+$N44)^(EA$20)*((1+$K44)^(EA$20)),IF(AND($G44=99,EA$20<=$H44,EA$20>=$F$18),$F44*(1+$N44)^(EA$20)*((1+$K44)^(EA$20)),IF(AND(EA$20<=$H44,EA$20>=$G44,$G44<>99,$H44<>99),$F44*(1+$N44)^(EA$20)*((1+$K44)^(EA$20)),0)))) -> 3750 | EB44: =IF(AND($G44=99,$H44=99),EB$22*$F44*(1+$N44)^(EB$20)*((1+$K44)^(EB$20)),IF(AND($H44=99,EB$20>=$G44,EB$20<=$F$20),$F44*(1+$N44)^(EB$20)*((1+$K44)^(EB$20)),IF(AND($G44=99,EB$20<=$H44,EB$20>=$F$18),$F44*(1+$N44)^(EB$20)*((1+$K44)^(EB$20)),IF(AND(EB$20<=$H44,EB$20>=$G44,$G44<>99,$H44<>99),$F44*(1+$N44)^(EB$20)*((1+$K44)^(EB$20)),0)))) -> 0 | EC44: =IF(AND($G44=99,$H44=99),EC$22*$F44*(1+$N44)^(EC$20)*((1+$K44)^(EC$20)),IF(AND($H44=99,EC$20>=$G44,EC$20<=$F$20),$F44*(1+$N44)^(EC$20)*((1+$K44)^(EC$20)),IF(AND($G44=99,EC$20<=$H44,EC$20>=$F$18),$F44*(1+$N44)^(EC$20)*((1+$K44)^(EC$20)),IF(AND(EC$20<=$H44,EC$20>=$G44,$G44<>99,$H44<>99),$F44*(1+$N44)^(EC$20)*((1+$K44)^(EC$20)),0)))) -> 0 | ED44: =IF(AND($G44=99,$H44=99),ED$22*$F44*(1+$N44)^(ED$20)*((1+$K44)^(ED$20)),IF(AND($H44=99,ED$20>=$G44,ED$20<=$F$20),$F44*(1+$N44)^(ED$20)*((1+$K44)^(ED$20)),IF(AND($G44=99,ED$20<=$H44,ED$20>=$F$18),$F44*(1+$N44)^(ED$20)*((1+$K44)^(ED$20)),IF(AND(ED$20<=$H44,ED$20>=$G44,$G44<>99,$H44<>99),$F44*(1+$N44)^(ED$20)*((1+$K44)^(ED$20)),0)))) -> 0 | EE44: =IF(AND($G44=99,$H44=99),EE$22*$F44*(1+$N44)^(EE$20)*((1+$K44)^(EE$20)),IF(AND($H44=99,EE$20>=$G44,EE$20<=$F$20),$F44*(1+$N44)^(EE$20)*((1+$K44)^(EE$20)),IF(AND($G44=99,EE$20<=$H44,EE$20>=$F$18),$F44*(1+$N44)^(EE$20)*((1+$K44)^(EE$20)),IF(AND(EE$20<=$H44,EE$20>=$G44,$G44<>99,$H44<>99),$F44*(1+$N44)^(EE$20)*((1+$K44)^(EE$20)),0)))) -> 0 | EF44: =IF(AND($G44=99,$H44=99),EF$22*$F44*(1+$N44)^(EF$20)*((1+$K44)^(EF$20)),IF(AND($H44=99,EF$20>=$G44,EF$20<=$F$20),$F44*(1+$N44)^(EF$20)*((1+$K44)^(EF$20)),IF(AND($G44=99,EF$20<=$H44,EF$20>=$F$18),$F44*(1+$N44)^(EF$20)*((1+$K44)^(EF$20)),IF(AND(EF$20<=$H44,EF$20>=$G44,$G44<>99,$H44<>99),$F44*(1+$N44)^(EF$20)*((1+$K44)^(EF$20)),0)))) -> 0 | EG44: =IF(AND($G44=99,$H44=99),EG$22*$F44*(1+$N44)^(EG$20)*((1+$K44)^(EG$20)),IF(AND($H44=99,EG$20>=$G44,EG$20<=$F$20),$F44*(1+$N44)^(EG$20)*((1+$K44)^(EG$20)),IF(AND($G44=99,EG$20<=$H44,EG$20>=$F$18),$F44*(1+$N44)^(EG$20)*((1+$K44)^(EG$20)),IF(AND(EG$20<=$H44,EG$20>=$G44,$G44<>99,$H44<>99),$F44*(1+$N44)^(EG$20)*((1+$K44)^(EG$20)),0)))) -> 0 | EH44: =IF(AND($G44=99,$H44=99),EH$22*$F44*(1+$N44)^(EH$20)*((1+$K44)^(EH$20)),IF(AND($H44=99,EH$20>=$G44,EH$20<=$F$20),$F44*(1+$N44)^(EH$20)*((1+$K44)^(EH$20)),IF(AND($G44=99,EH$20<=$H44,EH$20>=$F$18),$F44*(1+$N44)^(EH$20)*((1+$K44)^(EH$20)),IF(AND(EH$20<=$H44,EH$20>=$G44,$G44<>99,$H44<>99),$F44*(1+$N44)^(EH$20)*((1+$K44)^(EH$20)),0)))) -> 0 | ... GB44: =IF(AND($G44=99,$H44=99),GB$22*$F44*(1+$N44)^(GB$20)*((1+$K44)^(GB$20)),IF(AND($H44=99,GB$20>=$G44,GB$20<=$F$20),$F44*(1+$N44)^(GB$20)*((1+$K44)^(GB$20)),IF(AND($G44=99,GB$20<=$H44,GB$20>=$F$18),$F44*(1+$N44)^(GB$20)*((1+$K44)^(GB$20)),IF(AND(GB$20<=$H44,GB$20>=$G44,$G44<>99,$H44<>99),$F44*(1+$N44)^(GB$20)*((1+$K44)^(GB$20)),0)))) -> 0
C45: Abzahlung in €/Jahr (ALTERNATIVE zu Zeile 44 – nicht zusätzlich!) | D45: 0 | E45: 0 | F45: 0 | G45: 99 | H45: 99 | I45: 0 | J45: 0 | K45: 0 | L45: 0 | M45: 0 | N45: 0 | O45: Nur befüllen, wenn Zeile 44 leer bleibt. Sonst wird die Investition doppelt gezählt. | R45: =C45 -> Abzahlung in €/Jahr (ALTERNATIVE zu Zeile 44 – nicht zusätzlich!) | S45: =IF(AND($G45=99,$H45=99),S$22*$E45*(1+$M45)^(S$20)*((1+$J45)^(S$20)),IF(AND($H45=99,S$20>=$G45,S$20<=$E$20),$E45*(1+$M45)^(S$20)*((1+$J45)^(S$20)),IF(AND($G45=99,S$20<=$H45,S$20>=$E$18),$E45*(1+$M45)^(S$20)*((1+$J45)^(S$20)),IF(AND(S$20<=$H45,S$20>=$G45,$G45<>99,$H45<>99),$E45*(1+$M45)^(S$20)*((1+$J45)^(S$20)),0)))) -> 0 | T45: =IF(AND($G45=99,$H45=99),T$22*$E45*(1+$M45)^(T$20)*((1+$J45)^(T$20)),IF(AND($H45=99,T$20>=$G45,T$20<=$E$20),$E45*(1+$M45)^(T$20)*((1+$J45)^(T$20)),IF(AND($G45=99,T$20<=$H45,T$20>=$E$18),$E45*(1+$M45)^(T$20)*((1+$J45)^(T$20)),IF(AND(T$20<=$H45,T$20>=$G45,$G45<>99,$H45<>99),$E45*(1+$M45)^(T$20)*((1+$J45)^(T$20)),0)))) -> 0 | U45: =IF(AND($G45=99,$H45=99),U$22*$E45*(1+$M45)^(U$20)*((1+$J45)^(U$20)),IF(AND($H45=99,U$20>=$G45,U$20<=$E$20),$E45*(1+$M45)^(U$20)*((1+$J45)^(U$20)),IF(AND($G45=99,U$20<=$H45,U$20>=$E$18),$E45*(1+$M45)^(U$20)*((1+$J45)^(U$20)),IF(AND(U$20<=$H45,U$20>=$G45,$G45<>99,$H45<>99),$E45*(1+$M45)^(U$20)*((1+$J45)^(U$20)),0)))) -> 0 | V45: =IF(AND($G45=99,$H45=99),V$22*$E45*(1+$M45)^(V$20)*((1+$J45)^(V$20)),IF(AND($H45=99,V$20>=$G45,V$20<=$E$20),$E45*(1+$M45)^(V$20)*((1+$J45)^(V$20)),IF(AND($G45=99,V$20<=$H45,V$20>=$E$18),$E45*(1+$M45)^(V$20)*((1+$J45)^(V$20)),IF(AND(V$20<=$H45,V$20>=$G45,$G45<>99,$H45<>99),$E45*(1+$M45)^(V$20)*((1+$J45)^(V$20)),0)))) -> 0 | W45: =IF(AND($G45=99,$H45=99),W$22*$E45*(1+$M45)^(W$20)*((1+$J45)^(W$20)),IF(AND($H45=99,W$20>=$G45,W$20<=$E$20),$E45*(1+$M45)^(W$20)*((1+$J45)^(W$20)),IF(AND($G45=99,W$20<=$H45,W$20>=$E$18),$E45*(1+$M45)^(W$20)*((1+$J45)^(W$20)),IF(AND(W$20<=$H45,W$20>=$G45,$G45<>99,$H45<>99),$E45*(1+$M45)^(W$20)*((1+$J45)^(W$20)),0)))) -> 0 | X45: =IF(AND($G45=99,$H45=99),X$22*$E45*(1+$M45)^(X$20)*((1+$J45)^(X$20)),IF(AND($H45=99,X$20>=$G45,X$20<=$E$20),$E45*(1+$M45)^(X$20)*((1+$J45)^(X$20)),IF(AND($G45=99,X$20<=$H45,X$20>=$E$18),$E45*(1+$M45)^(X$20)*((1+$J45)^(X$20)),IF(AND(X$20<=$H45,X$20>=$G45,$G45<>99,$H45<>99),$E45*(1+$M45)^(X$20)*((1+$J45)^(X$20)),0)))) -> 0 | Y45: =IF(AND($G45=99,$H45=99),Y$22*$E45*(1+$M45)^(Y$20)*((1+$J45)^(Y$20)),IF(AND($H45=99,Y$20>=$G45,Y$20<=$E$20),$E45*(1+$M45)^(Y$20)*((1+$J45)^(Y$20)),IF(AND($G45=99,Y$20<=$H45,Y$20>=$E$18),$E45*(1+$M45)^(Y$20)*((1+$J45)^(Y$20)),IF(AND(Y$20<=$H45,Y$20>=$G45,$G45<>99,$H45<>99),$E45*(1+$M45)^(Y$20)*((1+$J45)^(Y$20)),0)))) -> 0 | Z45: =IF(AND($G45=99,$H45=99),Z$22*$E45*(1+$M45)^(Z$20)*((1+$J45)^(Z$20)),IF(AND($H45=99,Z$20>=$G45,Z$20<=$E$20),$E45*(1+$M45)^(Z$20)*((1+$J45)^(Z$20)),IF(AND($G45=99,Z$20<=$H45,Z$20>=$E$18),$E45*(1+$M45)^(Z$20)*((1+$J45)^(Z$20)),IF(AND(Z$20<=$H45,Z$20>=$G45,$G45<>99,$H45<>99),$E45*(1+$M45)^(Z$20)*((1+$J45)^(Z$20)),0)))) -> 0 | ... BT45: =IF(AND($G45=99,$H45=99),BT$22*$E45*(1+$M45)^(BT$20)*((1+$J45)^(BT$20)),IF(AND($H45=99,BT$20>=$G45,BT$20<=$E$20),$E45*(1+$M45)^(BT$20)*((1+$J45)^(BT$20)),IF(AND($G45=99,BT$20<=$H45,BT$20>=$E$18),$E45*(1+$M45)^(BT$20)*((1+$J45)^(BT$20)),IF(AND(BT$20<=$H45,BT$20>=$G45,$G45<>99,$H45<>99),$E45*(1+$M45)^(BT$20)*((1+$J45)^(BT$20)),0)))) -> 0 | BV45: =C45 -> Abzahlung in €/Jahr (ALTERNATIVE zu Zeile 44 – nicht zusätzlich!) | BW45: =IF(AND($G45=99,$H45=99),BW$22*$D45*(1+$L45)^(BW$20)*((1+$I45)^(BW$20)),IF(AND($H45=99,BW$20>=$G45,BW$20<=$D$20),$D45*(1+$L45)^(BW$20)*((1+$I45)^(BW$20)),IF(AND($G45=99,BW$20<=$H45,BW$20>=$D$18),$D45*(1+$L45)^(BW$20)*((1+$I45)^(BW$20)),IF(AND(BW$20<=$H45,BW$20>=$G45,$G45<>99,$H45<>99),$D45*(1+$L45)^(BW$20)*((1+$I45)^(BW$20)),0)))) -> 0 | BX45: =IF(AND($G45=99,$H45=99),BX$22*$D45*(1+$L45)^(BX$20)*((1+$I45)^(BX$20)),IF(AND($H45=99,BX$20>=$G45,BX$20<=$D$20),$D45*(1+$L45)^(BX$20)*((1+$I45)^(BX$20)),IF(AND($G45=99,BX$20<=$H45,BX$20>=$D$18),$D45*(1+$L45)^(BX$20)*((1+$I45)^(BX$20)),IF(AND(BX$20<=$H45,BX$20>=$G45,$G45<>99,$H45<>99),$D45*(1+$L45)^(BX$20)*((1+$I45)^(BX$20)),0)))) -> 0 | BY45: =IF(AND($G45=99,$H45=99),BY$22*$D45*(1+$L45)^(BY$20)*((1+$I45)^(BY$20)),IF(AND($H45=99,BY$20>=$G45,BY$20<=$D$20),$D45*(1+$L45)^(BY$20)*((1+$I45)^(BY$20)),IF(AND($G45=99,BY$20<=$H45,BY$20>=$D$18),$D45*(1+$L45)^(BY$20)*((1+$I45)^(BY$20)),IF(AND(BY$20<=$H45,BY$20>=$G45,$G45<>99,$H45<>99),$D45*(1+$L45)^(BY$20)*((1+$I45)^(BY$20)),0)))) -> 0 | BZ45: =IF(AND($G45=99,$H45=99),BZ$22*$D45*(1+$L45)^(BZ$20)*((1+$I45)^(BZ$20)),IF(AND($H45=99,BZ$20>=$G45,BZ$20<=$D$20),$D45*(1+$L45)^(BZ$20)*((1+$I45)^(BZ$20)),IF(AND($G45=99,BZ$20<=$H45,BZ$20>=$D$18),$D45*(1+$L45)^(BZ$20)*((1+$I45)^(BZ$20)),IF(AND(BZ$20<=$H45,BZ$20>=$G45,$G45<>99,$H45<>99),$D45*(1+$L45)^(BZ$20)*((1+$I45)^(BZ$20)),0)))) -> 0 | CA45: =IF(AND($G45=99,$H45=99),CA$22*$D45*(1+$L45)^(CA$20)*((1+$I45)^(CA$20)),IF(AND($H45=99,CA$20>=$G45,CA$20<=$D$20),$D45*(1+$L45)^(CA$20)*((1+$I45)^(CA$20)),IF(AND($G45=99,CA$20<=$H45,CA$20>=$D$18),$D45*(1+$L45)^(CA$20)*((1+$I45)^(CA$20)),IF(AND(CA$20<=$H45,CA$20>=$G45,$G45<>99,$H45<>99),$D45*(1+$L45)^(CA$20)*((1+$I45)^(CA$20)),0)))) -> 0 | CB45: =IF(AND($G45=99,$H45=99),CB$22*$D45*(1+$L45)^(CB$20)*((1+$I45)^(CB$20)),IF(AND($H45=99,CB$20>=$G45,CB$20<=$D$20),$D45*(1+$L45)^(CB$20)*((1+$I45)^(CB$20)),IF(AND($G45=99,CB$20<=$H45,CB$20>=$D$18),$D45*(1+$L45)^(CB$20)*((1+$I45)^(CB$20)),IF(AND(CB$20<=$H45,CB$20>=$G45,$G45<>99,$H45<>99),$D45*(1+$L45)^(CB$20)*((1+$I45)^(CB$20)),0)))) -> 0 | CC45: =IF(AND($G45=99,$H45=99),CC$22*$D45*(1+$L45)^(CC$20)*((1+$I45)^(CC$20)),IF(AND($H45=99,CC$20>=$G45,CC$20<=$D$20),$D45*(1+$L45)^(CC$20)*((1+$I45)^(CC$20)),IF(AND($G45=99,CC$20<=$H45,CC$20>=$D$18),$D45*(1+$L45)^(CC$20)*((1+$I45)^(CC$20)),IF(AND(CC$20<=$H45,CC$20>=$G45,$G45<>99,$H45<>99),$D45*(1+$L45)^(CC$20)*((1+$I45)^(CC$20)),0)))) -> 0 | CD45: =IF(AND($G45=99,$H45=99),CD$22*$D45*(1+$L45)^(CD$20)*((1+$I45)^(CD$20)),IF(AND($H45=99,CD$20>=$G45,CD$20<=$D$20),$D45*(1+$L45)^(CD$20)*((1+$I45)^(CD$20)),IF(AND($G45=99,CD$20<=$H45,CD$20>=$D$18),$D45*(1+$L45)^(CD$20)*((1+$I45)^(CD$20)),IF(AND(CD$20<=$H45,CD$20>=$G45,$G45<>99,$H45<>99),$D45*(1+$L45)^(CD$20)*((1+$I45)^(CD$20)),0)))) -> 0 | ... DX45: =IF(AND($G45=99,$H45=99),DX$22*$D45*(1+$L45)^(DX$20)*((1+$I45)^(DX$20)),IF(AND($H45=99,DX$20>=$G45,DX$20<=$D$20),$D45*(1+$L45)^(DX$20)*((1+$I45)^(DX$20)),IF(AND($G45=99,DX$20<=$H45,DX$20>=$D$18),$D45*(1+$L45)^(DX$20)*((1+$I45)^(DX$20)),IF(AND(DX$20<=$H45,DX$20>=$G45,$G45<>99,$H45<>99),$D45*(1+$L45)^(DX$20)*((1+$I45)^(DX$20)),0)))) -> 0 | DZ45: =C45 -> Abzahlung in €/Jahr (ALTERNATIVE zu Zeile 44 – nicht zusätzlich!) | EA45: =IF(AND($G45=99,$H45=99),EA$22*$F45*(1+$N45)^(EA$20)*((1+$K45)^(EA$20)),IF(AND($H45=99,EA$20>=$G45,EA$20<=$F$20),$F45*(1+$N45)^(EA$20)*((1+$K45)^(EA$20)),IF(AND($G45=99,EA$20<=$H45,EA$20>=$F$18),$F45*(1+$N45)^(EA$20)*((1+$K45)^(EA$20)),IF(AND(EA$20<=$H45,EA$20>=$G45,$G45<>99,$H45<>99),$F45*(1+$N45)^(EA$20)*((1+$K45)^(EA$20)),0)))) -> 0 | EB45: =IF(AND($G45=99,$H45=99),EB$22*$F45*(1+$N45)^(EB$20)*((1+$K45)^(EB$20)),IF(AND($H45=99,EB$20>=$G45,EB$20<=$F$20),$F45*(1+$N45)^(EB$20)*((1+$K45)^(EB$20)),IF(AND($G45=99,EB$20<=$H45,EB$20>=$F$18),$F45*(1+$N45)^(EB$20)*((1+$K45)^(EB$20)),IF(AND(EB$20<=$H45,EB$20>=$G45,$G45<>99,$H45<>99),$F45*(1+$N45)^(EB$20)*((1+$K45)^(EB$20)),0)))) -> 0 | EC45: =IF(AND($G45=99,$H45=99),EC$22*$F45*(1+$N45)^(EC$20)*((1+$K45)^(EC$20)),IF(AND($H45=99,EC$20>=$G45,EC$20<=$F$20),$F45*(1+$N45)^(EC$20)*((1+$K45)^(EC$20)),IF(AND($G45=99,EC$20<=$H45,EC$20>=$F$18),$F45*(1+$N45)^(EC$20)*((1+$K45)^(EC$20)),IF(AND(EC$20<=$H45,EC$20>=$G45,$G45<>99,$H45<>99),$F45*(1+$N45)^(EC$20)*((1+$K45)^(EC$20)),0)))) -> 0 | ED45: =IF(AND($G45=99,$H45=99),ED$22*$F45*(1+$N45)^(ED$20)*((1+$K45)^(ED$20)),IF(AND($H45=99,ED$20>=$G45,ED$20<=$F$20),$F45*(1+$N45)^(ED$20)*((1+$K45)^(ED$20)),IF(AND($G45=99,ED$20<=$H45,ED$20>=$F$18),$F45*(1+$N45)^(ED$20)*((1+$K45)^(ED$20)),IF(AND(ED$20<=$H45,ED$20>=$G45,$G45<>99,$H45<>99),$F45*(1+$N45)^(ED$20)*((1+$K45)^(ED$20)),0)))) -> 0 | EE45: =IF(AND($G45=99,$H45=99),EE$22*$F45*(1+$N45)^(EE$20)*((1+$K45)^(EE$20)),IF(AND($H45=99,EE$20>=$G45,EE$20<=$F$20),$F45*(1+$N45)^(EE$20)*((1+$K45)^(EE$20)),IF(AND($G45=99,EE$20<=$H45,EE$20>=$F$18),$F45*(1+$N45)^(EE$20)*((1+$K45)^(EE$20)),IF(AND(EE$20<=$H45,EE$20>=$G45,$G45<>99,$H45<>99),$F45*(1+$N45)^(EE$20)*((1+$K45)^(EE$20)),0)))) -> 0 | EF45: =IF(AND($G45=99,$H45=99),EF$22*$F45*(1+$N45)^(EF$20)*((1+$K45)^(EF$20)),IF(AND($H45=99,EF$20>=$G45,EF$20<=$F$20),$F45*(1+$N45)^(EF$20)*((1+$K45)^(EF$20)),IF(AND($G45=99,EF$20<=$H45,EF$20>=$F$18),$F45*(1+$N45)^(EF$20)*((1+$K45)^(EF$20)),IF(AND(EF$20<=$H45,EF$20>=$G45,$G45<>99,$H45<>99),$F45*(1+$N45)^(EF$20)*((1+$K45)^(EF$20)),0)))) -> 0 | EG45: =IF(AND($G45=99,$H45=99),EG$22*$F45*(1+$N45)^(EG$20)*((1+$K45)^(EG$20)),IF(AND($H45=99,EG$20>=$G45,EG$20<=$F$20),$F45*(1+$N45)^(EG$20)*((1+$K45)^(EG$20)),IF(AND($G45=99,EG$20<=$H45,EG$20>=$F$18),$F45*(1+$N45)^(EG$20)*((1+$K45)^(EG$20)),IF(AND(EG$20<=$H45,EG$20>=$G45,$G45<>99,$H45<>99),$F45*(1+$N45)^(EG$20)*((1+$K45)^(EG$20)),0)))) -> 0 | EH45: =IF(AND($G45=99,$H45=99),EH$22*$F45*(1+$N45)^(EH$20)*((1+$K45)^(EH$20)),IF(AND($H45=99,EH$20>=$G45,EH$20<=$F$20),$F45*(1+$N45)^(EH$20)*((1+$K45)^(EH$20)),IF(AND($G45=99,EH$20<=$H45,EH$20>=$F$18),$F45*(1+$N45)^(EH$20)*((1+$K45)^(EH$20)),IF(AND(EH$20<=$H45,EH$20>=$G45,$G45<>99,$H45<>99),$F45*(1+$N45)^(EH$20)*((1+$K45)^(EH$20)),0)))) -> 0 | ... GB45: =IF(AND($G45=99,$H45=99),GB$22*$F45*(1+$N45)^(GB$20)*((1+$K45)^(GB$20)),IF(AND($H45=99,GB$20>=$G45,GB$20<=$F$20),$F45*(1+$N45)^(GB$20)*((1+$K45)^(GB$20)),IF(AND($G45=99,GB$20<=$H45,GB$20>=$F$18),$F45*(1+$N45)^(GB$20)*((1+$K45)^(GB$20)),IF(AND(GB$20<=$H45,GB$20>=$G45,$G45<>99,$H45<>99),$F45*(1+$N45)^(GB$20)*((1+$K45)^(GB$20)),0)))) -> 0
C46: Zusätzliche Arbeitskraft in €/Jahr | I46: 0 | J46: 0 | K46: 0 | L46: =$D$7 -> 0.02 | M46: =$E$7 -> 0.03 | N46: =$F$7 -> 0.05 | R46: =C46 -> Zusätzliche Arbeitskraft in €/Jahr | S46: =IF(AND($G46=99,$H46=99),S$22*$E46*(1+$M46)^(S$20)*((1+$J46)^(S$20)),IF(AND($H46=99,S$20>=$G46,S$20<=$E$20),$E46*(1+$M46)^(S$20)*((1+$J46)^(S$20)),IF(AND($G46=99,S$20<=$H46,S$20>=$E$18),$E46*(1+$M46)^(S$20)*((1+$J46)^(S$20)),IF(AND(S$20<=$H46,S$20>=$G46,$G46<>99,$H46<>99),$E46*(1+$M46)^(S$20)*((1+$J46)^(S$20)),0)))) -> 0 | T46: =IF(AND($G46=99,$H46=99),T$22*$E46*(1+$M46)^(T$20)*((1+$J46)^(T$20)),IF(AND($H46=99,T$20>=$G46,T$20<=$E$20),$E46*(1+$M46)^(T$20)*((1+$J46)^(T$20)),IF(AND($G46=99,T$20<=$H46,T$20>=$E$18),$E46*(1+$M46)^(T$20)*((1+$J46)^(T$20)),IF(AND(T$20<=$H46,T$20>=$G46,$G46<>99,$H46<>99),$E46*(1+$M46)^(T$20)*((1+$J46)^(T$20)),0)))) -> 0 | U46: =IF(AND($G46=99,$H46=99),U$22*$E46*(1+$M46)^(U$20)*((1+$J46)^(U$20)),IF(AND($H46=99,U$20>=$G46,U$20<=$E$20),$E46*(1+$M46)^(U$20)*((1+$J46)^(U$20)),IF(AND($G46=99,U$20<=$H46,U$20>=$E$18),$E46*(1+$M46)^(U$20)*((1+$J46)^(U$20)),IF(AND(U$20<=$H46,U$20>=$G46,$G46<>99,$H46<>99),$E46*(1+$M46)^(U$20)*((1+$J46)^(U$20)),0)))) -> 0 | V46: =IF(AND($G46=99,$H46=99),V$22*$E46*(1+$M46)^(V$20)*((1+$J46)^(V$20)),IF(AND($H46=99,V$20>=$G46,V$20<=$E$20),$E46*(1+$M46)^(V$20)*((1+$J46)^(V$20)),IF(AND($G46=99,V$20<=$H46,V$20>=$E$18),$E46*(1+$M46)^(V$20)*((1+$J46)^(V$20)),IF(AND(V$20<=$H46,V$20>=$G46,$G46<>99,$H46<>99),$E46*(1+$M46)^(V$20)*((1+$J46)^(V$20)),0)))) -> 0 | W46: =IF(AND($G46=99,$H46=99),W$22*$E46*(1+$M46)^(W$20)*((1+$J46)^(W$20)),IF(AND($H46=99,W$20>=$G46,W$20<=$E$20),$E46*(1+$M46)^(W$20)*((1+$J46)^(W$20)),IF(AND($G46=99,W$20<=$H46,W$20>=$E$18),$E46*(1+$M46)^(W$20)*((1+$J46)^(W$20)),IF(AND(W$20<=$H46,W$20>=$G46,$G46<>99,$H46<>99),$E46*(1+$M46)^(W$20)*((1+$J46)^(W$20)),0)))) -> 0 | X46: =IF(AND($G46=99,$H46=99),X$22*$E46*(1+$M46)^(X$20)*((1+$J46)^(X$20)),IF(AND($H46=99,X$20>=$G46,X$20<=$E$20),$E46*(1+$M46)^(X$20)*((1+$J46)^(X$20)),IF(AND($G46=99,X$20<=$H46,X$20>=$E$18),$E46*(1+$M46)^(X$20)*((1+$J46)^(X$20)),IF(AND(X$20<=$H46,X$20>=$G46,$G46<>99,$H46<>99),$E46*(1+$M46)^(X$20)*((1+$J46)^(X$20)),0)))) -> 0 | Y46: =IF(AND($G46=99,$H46=99),Y$22*$E46*(1+$M46)^(Y$20)*((1+$J46)^(Y$20)),IF(AND($H46=99,Y$20>=$G46,Y$20<=$E$20),$E46*(1+$M46)^(Y$20)*((1+$J46)^(Y$20)),IF(AND($G46=99,Y$20<=$H46,Y$20>=$E$18),$E46*(1+$M46)^(Y$20)*((1+$J46)^(Y$20)),IF(AND(Y$20<=$H46,Y$20>=$G46,$G46<>99,$H46<>99),$E46*(1+$M46)^(Y$20)*((1+$J46)^(Y$20)),0)))) -> 0 | Z46: =IF(AND($G46=99,$H46=99),Z$22*$E46*(1+$M46)^(Z$20)*((1+$J46)^(Z$20)),IF(AND($H46=99,Z$20>=$G46,Z$20<=$E$20),$E46*(1+$M46)^(Z$20)*((1+$J46)^(Z$20)),IF(AND($G46=99,Z$20<=$H46,Z$20>=$E$18),$E46*(1+$M46)^(Z$20)*((1+$J46)^(Z$20)),IF(AND(Z$20<=$H46,Z$20>=$G46,$G46<>99,$H46<>99),$E46*(1+$M46)^(Z$20)*((1+$J46)^(Z$20)),0)))) -> 0 | ... BT46: =IF(AND($G46=99,$H46=99),BT$22*$E46*(1+$M46)^(BT$20)*((1+$J46)^(BT$20)),IF(AND($H46=99,BT$20>=$G46,BT$20<=$E$20),$E46*(1+$M46)^(BT$20)*((1+$J46)^(BT$20)),IF(AND($G46=99,BT$20<=$H46,BT$20>=$E$18),$E46*(1+$M46)^(BT$20)*((1+$J46)^(BT$20)),IF(AND(BT$20<=$H46,BT$20>=$G46,$G46<>99,$H46<>99),$E46*(1+$M46)^(BT$20)*((1+$J46)^(BT$20)),0)))) -> 0 | BV46: =C46 -> Zusätzliche Arbeitskraft in €/Jahr | BW46: =IF(AND($G46=99,$H46=99),BW$22*$D46*(1+$L46)^(BW$20)*((1+$I46)^(BW$20)),IF(AND($H46=99,BW$20>=$G46,BW$20<=$D$20),$D46*(1+$L46)^(BW$20)*((1+$I46)^(BW$20)),IF(AND($G46=99,BW$20<=$H46,BW$20>=$D$18),$D46*(1+$L46)^(BW$20)*((1+$I46)^(BW$20)),IF(AND(BW$20<=$H46,BW$20>=$G46,$G46<>99,$H46<>99),$D46*(1+$L46)^(BW$20)*((1+$I46)^(BW$20)),0)))) -> 0 | BX46: =IF(AND($G46=99,$H46=99),BX$22*$D46*(1+$L46)^(BX$20)*((1+$I46)^(BX$20)),IF(AND($H46=99,BX$20>=$G46,BX$20<=$D$20),$D46*(1+$L46)^(BX$20)*((1+$I46)^(BX$20)),IF(AND($G46=99,BX$20<=$H46,BX$20>=$D$18),$D46*(1+$L46)^(BX$20)*((1+$I46)^(BX$20)),IF(AND(BX$20<=$H46,BX$20>=$G46,$G46<>99,$H46<>99),$D46*(1+$L46)^(BX$20)*((1+$I46)^(BX$20)),0)))) -> 0 | BY46: =IF(AND($G46=99,$H46=99),BY$22*$D46*(1+$L46)^(BY$20)*((1+$I46)^(BY$20)),IF(AND($H46=99,BY$20>=$G46,BY$20<=$D$20),$D46*(1+$L46)^(BY$20)*((1+$I46)^(BY$20)),IF(AND($G46=99,BY$20<=$H46,BY$20>=$D$18),$D46*(1+$L46)^(BY$20)*((1+$I46)^(BY$20)),IF(AND(BY$20<=$H46,BY$20>=$G46,$G46<>99,$H46<>99),$D46*(1+$L46)^(BY$20)*((1+$I46)^(BY$20)),0)))) -> 0 | BZ46: =IF(AND($G46=99,$H46=99),BZ$22*$D46*(1+$L46)^(BZ$20)*((1+$I46)^(BZ$20)),IF(AND($H46=99,BZ$20>=$G46,BZ$20<=$D$20),$D46*(1+$L46)^(BZ$20)*((1+$I46)^(BZ$20)),IF(AND($G46=99,BZ$20<=$H46,BZ$20>=$D$18),$D46*(1+$L46)^(BZ$20)*((1+$I46)^(BZ$20)),IF(AND(BZ$20<=$H46,BZ$20>=$G46,$G46<>99,$H46<>99),$D46*(1+$L46)^(BZ$20)*((1+$I46)^(BZ$20)),0)))) -> 0 | CA46: =IF(AND($G46=99,$H46=99),CA$22*$D46*(1+$L46)^(CA$20)*((1+$I46)^(CA$20)),IF(AND($H46=99,CA$20>=$G46,CA$20<=$D$20),$D46*(1+$L46)^(CA$20)*((1+$I46)^(CA$20)),IF(AND($G46=99,CA$20<=$H46,CA$20>=$D$18),$D46*(1+$L46)^(CA$20)*((1+$I46)^(CA$20)),IF(AND(CA$20<=$H46,CA$20>=$G46,$G46<>99,$H46<>99),$D46*(1+$L46)^(CA$20)*((1+$I46)^(CA$20)),0)))) -> 0 | CB46: =IF(AND($G46=99,$H46=99),CB$22*$D46*(1+$L46)^(CB$20)*((1+$I46)^(CB$20)),IF(AND($H46=99,CB$20>=$G46,CB$20<=$D$20),$D46*(1+$L46)^(CB$20)*((1+$I46)^(CB$20)),IF(AND($G46=99,CB$20<=$H46,CB$20>=$D$18),$D46*(1+$L46)^(CB$20)*((1+$I46)^(CB$20)),IF(AND(CB$20<=$H46,CB$20>=$G46,$G46<>99,$H46<>99),$D46*(1+$L46)^(CB$20)*((1+$I46)^(CB$20)),0)))) -> 0 | CC46: =IF(AND($G46=99,$H46=99),CC$22*$D46*(1+$L46)^(CC$20)*((1+$I46)^(CC$20)),IF(AND($H46=99,CC$20>=$G46,CC$20<=$D$20),$D46*(1+$L46)^(CC$20)*((1+$I46)^(CC$20)),IF(AND($G46=99,CC$20<=$H46,CC$20>=$D$18),$D46*(1+$L46)^(CC$20)*((1+$I46)^(CC$20)),IF(AND(CC$20<=$H46,CC$20>=$G46,$G46<>99,$H46<>99),$D46*(1+$L46)^(CC$20)*((1+$I46)^(CC$20)),0)))) -> 0 | CD46: =IF(AND($G46=99,$H46=99),CD$22*$D46*(1+$L46)^(CD$20)*((1+$I46)^(CD$20)),IF(AND($H46=99,CD$20>=$G46,CD$20<=$D$20),$D46*(1+$L46)^(CD$20)*((1+$I46)^(CD$20)),IF(AND($G46=99,CD$20<=$H46,CD$20>=$D$18),$D46*(1+$L46)^(CD$20)*((1+$I46)^(CD$20)),IF(AND(CD$20<=$H46,CD$20>=$G46,$G46<>99,$H46<>99),$D46*(1+$L46)^(CD$20)*((1+$I46)^(CD$20)),0)))) -> 0 | ... DX46: =IF(AND($G46=99,$H46=99),DX$22*$D46*(1+$L46)^(DX$20)*((1+$I46)^(DX$20)),IF(AND($H46=99,DX$20>=$G46,DX$20<=$D$20),$D46*(1+$L46)^(DX$20)*((1+$I46)^(DX$20)),IF(AND($G46=99,DX$20<=$H46,DX$20>=$D$18),$D46*(1+$L46)^(DX$20)*((1+$I46)^(DX$20)),IF(AND(DX$20<=$H46,DX$20>=$G46,$G46<>99,$H46<>99),$D46*(1+$L46)^(DX$20)*((1+$I46)^(DX$20)),0)))) -> 0 | DZ46: =C46 -> Zusätzliche Arbeitskraft in €/Jahr | EA46: =IF(AND($G46=99,$H46=99),EA$22*$F46*(1+$N46)^(EA$20)*((1+$K46)^(EA$20)),IF(AND($H46=99,EA$20>=$G46,EA$20<=$F$20),$F46*(1+$N46)^(EA$20)*((1+$K46)^(EA$20)),IF(AND($G46=99,EA$20<=$H46,EA$20>=$F$18),$F46*(1+$N46)^(EA$20)*((1+$K46)^(EA$20)),IF(AND(EA$20<=$H46,EA$20>=$G46,$G46<>99,$H46<>99),$F46*(1+$N46)^(EA$20)*((1+$K46)^(EA$20)),0)))) -> 0 | EB46: =IF(AND($G46=99,$H46=99),EB$22*$F46*(1+$N46)^(EB$20)*((1+$K46)^(EB$20)),IF(AND($H46=99,EB$20>=$G46,EB$20<=$F$20),$F46*(1+$N46)^(EB$20)*((1+$K46)^(EB$20)),IF(AND($G46=99,EB$20<=$H46,EB$20>=$F$18),$F46*(1+$N46)^(EB$20)*((1+$K46)^(EB$20)),IF(AND(EB$20<=$H46,EB$20>=$G46,$G46<>99,$H46<>99),$F46*(1+$N46)^(EB$20)*((1+$K46)^(EB$20)),0)))) -> 0 | EC46: =IF(AND($G46=99,$H46=99),EC$22*$F46*(1+$N46)^(EC$20)*((1+$K46)^(EC$20)),IF(AND($H46=99,EC$20>=$G46,EC$20<=$F$20),$F46*(1+$N46)^(EC$20)*((1+$K46)^(EC$20)),IF(AND($G46=99,EC$20<=$H46,EC$20>=$F$18),$F46*(1+$N46)^(EC$20)*((1+$K46)^(EC$20)),IF(AND(EC$20<=$H46,EC$20>=$G46,$G46<>99,$H46<>99),$F46*(1+$N46)^(EC$20)*((1+$K46)^(EC$20)),0)))) -> 0 | ED46: =IF(AND($G46=99,$H46=99),ED$22*$F46*(1+$N46)^(ED$20)*((1+$K46)^(ED$20)),IF(AND($H46=99,ED$20>=$G46,ED$20<=$F$20),$F46*(1+$N46)^(ED$20)*((1+$K46)^(ED$20)),IF(AND($G46=99,ED$20<=$H46,ED$20>=$F$18),$F46*(1+$N46)^(ED$20)*((1+$K46)^(ED$20)),IF(AND(ED$20<=$H46,ED$20>=$G46,$G46<>99,$H46<>99),$F46*(1+$N46)^(ED$20)*((1+$K46)^(ED$20)),0)))) -> 0 | EE46: =IF(AND($G46=99,$H46=99),EE$22*$F46*(1+$N46)^(EE$20)*((1+$K46)^(EE$20)),IF(AND($H46=99,EE$20>=$G46,EE$20<=$F$20),$F46*(1+$N46)^(EE$20)*((1+$K46)^(EE$20)),IF(AND($G46=99,EE$20<=$H46,EE$20>=$F$18),$F46*(1+$N46)^(EE$20)*((1+$K46)^(EE$20)),IF(AND(EE$20<=$H46,EE$20>=$G46,$G46<>99,$H46<>99),$F46*(1+$N46)^(EE$20)*((1+$K46)^(EE$20)),0)))) -> 0 | EF46: =IF(AND($G46=99,$H46=99),EF$22*$F46*(1+$N46)^(EF$20)*((1+$K46)^(EF$20)),IF(AND($H46=99,EF$20>=$G46,EF$20<=$F$20),$F46*(1+$N46)^(EF$20)*((1+$K46)^(EF$20)),IF(AND($G46=99,EF$20<=$H46,EF$20>=$F$18),$F46*(1+$N46)^(EF$20)*((1+$K46)^(EF$20)),IF(AND(EF$20<=$H46,EF$20>=$G46,$G46<>99,$H46<>99),$F46*(1+$N46)^(EF$20)*((1+$K46)^(EF$20)),0)))) -> 0 | EG46: =IF(AND($G46=99,$H46=99),EG$22*$F46*(1+$N46)^(EG$20)*((1+$K46)^(EG$20)),IF(AND($H46=99,EG$20>=$G46,EG$20<=$F$20),$F46*(1+$N46)^(EG$20)*((1+$K46)^(EG$20)),IF(AND($G46=99,EG$20<=$H46,EG$20>=$F$18),$F46*(1+$N46)^(EG$20)*((1+$K46)^(EG$20)),IF(AND(EG$20<=$H46,EG$20>=$G46,$G46<>99,$H46<>99),$F46*(1+$N46)^(EG$20)*((1+$K46)^(EG$20)),0)))) -> 0 | EH46: =IF(AND($G46=99,$H46=99),EH$22*$F46*(1+$N46)^(EH$20)*((1+$K46)^(EH$20)),IF(AND($H46=99,EH$20>=$G46,EH$20<=$F$20),$F46*(1+$N46)^(EH$20)*((1+$K46)^(EH$20)),IF(AND($G46=99,EH$20<=$H46,EH$20>=$F$18),$F46*(1+$N46)^(EH$20)*((1+$K46)^(EH$20)),IF(AND(EH$20<=$H46,EH$20>=$G46,$G46<>99,$H46<>99),$F46*(1+$N46)^(EH$20)*((1+$K46)^(EH$20)),0)))) -> 0 | ... GB46: =IF(AND($G46=99,$H46=99),GB$22*$F46*(1+$N46)^(GB$20)*((1+$K46)^(GB$20)),IF(AND($H46=99,GB$20>=$G46,GB$20<=$F$20),$F46*(1+$N46)^(GB$20)*((1+$K46)^(GB$20)),IF(AND($G46=99,GB$20<=$H46,GB$20>=$F$18),$F46*(1+$N46)^(GB$20)*((1+$K46)^(GB$20)),IF(AND(GB$20<=$H46,GB$20>=$G46,$G46<>99,$H46<>99),$F46*(1+$N46)^(GB$20)*((1+$K46)^(GB$20)),0)))) -> 0
C47: Zusätzliche Arbeitskraft in €/Jahr | I47: 0 | J47: 0 | K47: 0 | L47: =$D$7 -> 0.02 | M47: =$E$7 -> 0.03 | N47: =$F$7 -> 0.05 | R47: =C47 -> Zusätzliche Arbeitskraft in €/Jahr | S47: =IF(AND($G47=99,$H47=99),S$22*$E47*(1+$M47)^(S$20)*((1+$J47)^(S$20)),IF(AND($H47=99,S$20>=$G47,S$20<=$E$20),$E47*(1+$M47)^(S$20)*((1+$J47)^(S$20)),IF(AND($G47=99,S$20<=$H47,S$20>=$E$18),$E47*(1+$M47)^(S$20)*((1+$J47)^(S$20)),IF(AND(S$20<=$H47,S$20>=$G47,$G47<>99,$H47<>99),$E47*(1+$M47)^(S$20)*((1+$J47)^(S$20)),0)))) -> 0 | T47: =IF(AND($G47=99,$H47=99),T$22*$E47*(1+$M47)^(T$20)*((1+$J47)^(T$20)),IF(AND($H47=99,T$20>=$G47,T$20<=$E$20),$E47*(1+$M47)^(T$20)*((1+$J47)^(T$20)),IF(AND($G47=99,T$20<=$H47,T$20>=$E$18),$E47*(1+$M47)^(T$20)*((1+$J47)^(T$20)),IF(AND(T$20<=$H47,T$20>=$G47,$G47<>99,$H47<>99),$E47*(1+$M47)^(T$20)*((1+$J47)^(T$20)),0)))) -> 0 | U47: =IF(AND($G47=99,$H47=99),U$22*$E47*(1+$M47)^(U$20)*((1+$J47)^(U$20)),IF(AND($H47=99,U$20>=$G47,U$20<=$E$20),$E47*(1+$M47)^(U$20)*((1+$J47)^(U$20)),IF(AND($G47=99,U$20<=$H47,U$20>=$E$18),$E47*(1+$M47)^(U$20)*((1+$J47)^(U$20)),IF(AND(U$20<=$H47,U$20>=$G47,$G47<>99,$H47<>99),$E47*(1+$M47)^(U$20)*((1+$J47)^(U$20)),0)))) -> 0 | V47: =IF(AND($G47=99,$H47=99),V$22*$E47*(1+$M47)^(V$20)*((1+$J47)^(V$20)),IF(AND($H47=99,V$20>=$G47,V$20<=$E$20),$E47*(1+$M47)^(V$20)*((1+$J47)^(V$20)),IF(AND($G47=99,V$20<=$H47,V$20>=$E$18),$E47*(1+$M47)^(V$20)*((1+$J47)^(V$20)),IF(AND(V$20<=$H47,V$20>=$G47,$G47<>99,$H47<>99),$E47*(1+$M47)^(V$20)*((1+$J47)^(V$20)),0)))) -> 0 | W47: =IF(AND($G47=99,$H47=99),W$22*$E47*(1+$M47)^(W$20)*((1+$J47)^(W$20)),IF(AND($H47=99,W$20>=$G47,W$20<=$E$20),$E47*(1+$M47)^(W$20)*((1+$J47)^(W$20)),IF(AND($G47=99,W$20<=$H47,W$20>=$E$18),$E47*(1+$M47)^(W$20)*((1+$J47)^(W$20)),IF(AND(W$20<=$H47,W$20>=$G47,$G47<>99,$H47<>99),$E47*(1+$M47)^(W$20)*((1+$J47)^(W$20)),0)))) -> 0 | X47: =IF(AND($G47=99,$H47=99),X$22*$E47*(1+$M47)^(X$20)*((1+$J47)^(X$20)),IF(AND($H47=99,X$20>=$G47,X$20<=$E$20),$E47*(1+$M47)^(X$20)*((1+$J47)^(X$20)),IF(AND($G47=99,X$20<=$H47,X$20>=$E$18),$E47*(1+$M47)^(X$20)*((1+$J47)^(X$20)),IF(AND(X$20<=$H47,X$20>=$G47,$G47<>99,$H47<>99),$E47*(1+$M47)^(X$20)*((1+$J47)^(X$20)),0)))) -> 0 | Y47: =IF(AND($G47=99,$H47=99),Y$22*$E47*(1+$M47)^(Y$20)*((1+$J47)^(Y$20)),IF(AND($H47=99,Y$20>=$G47,Y$20<=$E$20),$E47*(1+$M47)^(Y$20)*((1+$J47)^(Y$20)),IF(AND($G47=99,Y$20<=$H47,Y$20>=$E$18),$E47*(1+$M47)^(Y$20)*((1+$J47)^(Y$20)),IF(AND(Y$20<=$H47,Y$20>=$G47,$G47<>99,$H47<>99),$E47*(1+$M47)^(Y$20)*((1+$J47)^(Y$20)),0)))) -> 0 | Z47: =IF(AND($G47=99,$H47=99),Z$22*$E47*(1+$M47)^(Z$20)*((1+$J47)^(Z$20)),IF(AND($H47=99,Z$20>=$G47,Z$20<=$E$20),$E47*(1+$M47)^(Z$20)*((1+$J47)^(Z$20)),IF(AND($G47=99,Z$20<=$H47,Z$20>=$E$18),$E47*(1+$M47)^(Z$20)*((1+$J47)^(Z$20)),IF(AND(Z$20<=$H47,Z$20>=$G47,$G47<>99,$H47<>99),$E47*(1+$M47)^(Z$20)*((1+$J47)^(Z$20)),0)))) -> 0 | ... BT47: =IF(AND($G47=99,$H47=99),BT$22*$E47*(1+$M47)^(BT$20)*((1+$J47)^(BT$20)),IF(AND($H47=99,BT$20>=$G47,BT$20<=$E$20),$E47*(1+$M47)^(BT$20)*((1+$J47)^(BT$20)),IF(AND($G47=99,BT$20<=$H47,BT$20>=$E$18),$E47*(1+$M47)^(BT$20)*((1+$J47)^(BT$20)),IF(AND(BT$20<=$H47,BT$20>=$G47,$G47<>99,$H47<>99),$E47*(1+$M47)^(BT$20)*((1+$J47)^(BT$20)),0)))) -> 0 | BV47: =C47 -> Zusätzliche Arbeitskraft in €/Jahr | BW47: =IF(AND($G47=99,$H47=99),BW$22*$D47*(1+$L47)^(BW$20)*((1+$I47)^(BW$20)),IF(AND($H47=99,BW$20>=$G47,BW$20<=$D$20),$D47*(1+$L47)^(BW$20)*((1+$I47)^(BW$20)),IF(AND($G47=99,BW$20<=$H47,BW$20>=$D$18),$D47*(1+$L47)^(BW$20)*((1+$I47)^(BW$20)),IF(AND(BW$20<=$H47,BW$20>=$G47,$G47<>99,$H47<>99),$D47*(1+$L47)^(BW$20)*((1+$I47)^(BW$20)),0)))) -> 0 | BX47: =IF(AND($G47=99,$H47=99),BX$22*$D47*(1+$L47)^(BX$20)*((1+$I47)^(BX$20)),IF(AND($H47=99,BX$20>=$G47,BX$20<=$D$20),$D47*(1+$L47)^(BX$20)*((1+$I47)^(BX$20)),IF(AND($G47=99,BX$20<=$H47,BX$20>=$D$18),$D47*(1+$L47)^(BX$20)*((1+$I47)^(BX$20)),IF(AND(BX$20<=$H47,BX$20>=$G47,$G47<>99,$H47<>99),$D47*(1+$L47)^(BX$20)*((1+$I47)^(BX$20)),0)))) -> 0 | BY47: =IF(AND($G47=99,$H47=99),BY$22*$D47*(1+$L47)^(BY$20)*((1+$I47)^(BY$20)),IF(AND($H47=99,BY$20>=$G47,BY$20<=$D$20),$D47*(1+$L47)^(BY$20)*((1+$I47)^(BY$20)),IF(AND($G47=99,BY$20<=$H47,BY$20>=$D$18),$D47*(1+$L47)^(BY$20)*((1+$I47)^(BY$20)),IF(AND(BY$20<=$H47,BY$20>=$G47,$G47<>99,$H47<>99),$D47*(1+$L47)^(BY$20)*((1+$I47)^(BY$20)),0)))) -> 0 | BZ47: =IF(AND($G47=99,$H47=99),BZ$22*$D47*(1+$L47)^(BZ$20)*((1+$I47)^(BZ$20)),IF(AND($H47=99,BZ$20>=$G47,BZ$20<=$D$20),$D47*(1+$L47)^(BZ$20)*((1+$I47)^(BZ$20)),IF(AND($G47=99,BZ$20<=$H47,BZ$20>=$D$18),$D47*(1+$L47)^(BZ$20)*((1+$I47)^(BZ$20)),IF(AND(BZ$20<=$H47,BZ$20>=$G47,$G47<>99,$H47<>99),$D47*(1+$L47)^(BZ$20)*((1+$I47)^(BZ$20)),0)))) -> 0 | CA47: =IF(AND($G47=99,$H47=99),CA$22*$D47*(1+$L47)^(CA$20)*((1+$I47)^(CA$20)),IF(AND($H47=99,CA$20>=$G47,CA$20<=$D$20),$D47*(1+$L47)^(CA$20)*((1+$I47)^(CA$20)),IF(AND($G47=99,CA$20<=$H47,CA$20>=$D$18),$D47*(1+$L47)^(CA$20)*((1+$I47)^(CA$20)),IF(AND(CA$20<=$H47,CA$20>=$G47,$G47<>99,$H47<>99),$D47*(1+$L47)^(CA$20)*((1+$I47)^(CA$20)),0)))) -> 0 | CB47: =IF(AND($G47=99,$H47=99),CB$22*$D47*(1+$L47)^(CB$20)*((1+$I47)^(CB$20)),IF(AND($H47=99,CB$20>=$G47,CB$20<=$D$20),$D47*(1+$L47)^(CB$20)*((1+$I47)^(CB$20)),IF(AND($G47=99,CB$20<=$H47,CB$20>=$D$18),$D47*(1+$L47)^(CB$20)*((1+$I47)^(CB$20)),IF(AND(CB$20<=$H47,CB$20>=$G47,$G47<>99,$H47<>99),$D47*(1+$L47)^(CB$20)*((1+$I47)^(CB$20)),0)))) -> 0 | CC47: =IF(AND($G47=99,$H47=99),CC$22*$D47*(1+$L47)^(CC$20)*((1+$I47)^(CC$20)),IF(AND($H47=99,CC$20>=$G47,CC$20<=$D$20),$D47*(1+$L47)^(CC$20)*((1+$I47)^(CC$20)),IF(AND($G47=99,CC$20<=$H47,CC$20>=$D$18),$D47*(1+$L47)^(CC$20)*((1+$I47)^(CC$20)),IF(AND(CC$20<=$H47,CC$20>=$G47,$G47<>99,$H47<>99),$D47*(1+$L47)^(CC$20)*((1+$I47)^(CC$20)),0)))) -> 0 | CD47: =IF(AND($G47=99,$H47=99),CD$22*$D47*(1+$L47)^(CD$20)*((1+$I47)^(CD$20)),IF(AND($H47=99,CD$20>=$G47,CD$20<=$D$20),$D47*(1+$L47)^(CD$20)*((1+$I47)^(CD$20)),IF(AND($G47=99,CD$20<=$H47,CD$20>=$D$18),$D47*(1+$L47)^(CD$20)*((1+$I47)^(CD$20)),IF(AND(CD$20<=$H47,CD$20>=$G47,$G47<>99,$H47<>99),$D47*(1+$L47)^(CD$20)*((1+$I47)^(CD$20)),0)))) -> 0 | ... DX47: =IF(AND($G47=99,$H47=99),DX$22*$D47*(1+$L47)^(DX$20)*((1+$I47)^(DX$20)),IF(AND($H47=99,DX$20>=$G47,DX$20<=$D$20),$D47*(1+$L47)^(DX$20)*((1+$I47)^(DX$20)),IF(AND($G47=99,DX$20<=$H47,DX$20>=$D$18),$D47*(1+$L47)^(DX$20)*((1+$I47)^(DX$20)),IF(AND(DX$20<=$H47,DX$20>=$G47,$G47<>99,$H47<>99),$D47*(1+$L47)^(DX$20)*((1+$I47)^(DX$20)),0)))) -> 0 | DZ47: =C47 -> Zusätzliche Arbeitskraft in €/Jahr | EA47: =IF(AND($G47=99,$H47=99),EA$22*$F47*(1+$N47)^(EA$20)*((1+$K47)^(EA$20)),IF(AND($H47=99,EA$20>=$G47,EA$20<=$F$20),$F47*(1+$N47)^(EA$20)*((1+$K47)^(EA$20)),IF(AND($G47=99,EA$20<=$H47,EA$20>=$F$18),$F47*(1+$N47)^(EA$20)*((1+$K47)^(EA$20)),IF(AND(EA$20<=$H47,EA$20>=$G47,$G47<>99,$H47<>99),$F47*(1+$N47)^(EA$20)*((1+$K47)^(EA$20)),0)))) -> 0 | EB47: =IF(AND($G47=99,$H47=99),EB$22*$F47*(1+$N47)^(EB$20)*((1+$K47)^(EB$20)),IF(AND($H47=99,EB$20>=$G47,EB$20<=$F$20),$F47*(1+$N47)^(EB$20)*((1+$K47)^(EB$20)),IF(AND($G47=99,EB$20<=$H47,EB$20>=$F$18),$F47*(1+$N47)^(EB$20)*((1+$K47)^(EB$20)),IF(AND(EB$20<=$H47,EB$20>=$G47,$G47<>99,$H47<>99),$F47*(1+$N47)^(EB$20)*((1+$K47)^(EB$20)),0)))) -> 0 | EC47: =IF(AND($G47=99,$H47=99),EC$22*$F47*(1+$N47)^(EC$20)*((1+$K47)^(EC$20)),IF(AND($H47=99,EC$20>=$G47,EC$20<=$F$20),$F47*(1+$N47)^(EC$20)*((1+$K47)^(EC$20)),IF(AND($G47=99,EC$20<=$H47,EC$20>=$F$18),$F47*(1+$N47)^(EC$20)*((1+$K47)^(EC$20)),IF(AND(EC$20<=$H47,EC$20>=$G47,$G47<>99,$H47<>99),$F47*(1+$N47)^(EC$20)*((1+$K47)^(EC$20)),0)))) -> 0 | ED47: =IF(AND($G47=99,$H47=99),ED$22*$F47*(1+$N47)^(ED$20)*((1+$K47)^(ED$20)),IF(AND($H47=99,ED$20>=$G47,ED$20<=$F$20),$F47*(1+$N47)^(ED$20)*((1+$K47)^(ED$20)),IF(AND($G47=99,ED$20<=$H47,ED$20>=$F$18),$F47*(1+$N47)^(ED$20)*((1+$K47)^(ED$20)),IF(AND(ED$20<=$H47,ED$20>=$G47,$G47<>99,$H47<>99),$F47*(1+$N47)^(ED$20)*((1+$K47)^(ED$20)),0)))) -> 0 | EE47: =IF(AND($G47=99,$H47=99),EE$22*$F47*(1+$N47)^(EE$20)*((1+$K47)^(EE$20)),IF(AND($H47=99,EE$20>=$G47,EE$20<=$F$20),$F47*(1+$N47)^(EE$20)*((1+$K47)^(EE$20)),IF(AND($G47=99,EE$20<=$H47,EE$20>=$F$18),$F47*(1+$N47)^(EE$20)*((1+$K47)^(EE$20)),IF(AND(EE$20<=$H47,EE$20>=$G47,$G47<>99,$H47<>99),$F47*(1+$N47)^(EE$20)*((1+$K47)^(EE$20)),0)))) -> 0 | EF47: =IF(AND($G47=99,$H47=99),EF$22*$F47*(1+$N47)^(EF$20)*((1+$K47)^(EF$20)),IF(AND($H47=99,EF$20>=$G47,EF$20<=$F$20),$F47*(1+$N47)^(EF$20)*((1+$K47)^(EF$20)),IF(AND($G47=99,EF$20<=$H47,EF$20>=$F$18),$F47*(1+$N47)^(EF$20)*((1+$K47)^(EF$20)),IF(AND(EF$20<=$H47,EF$20>=$G47,$G47<>99,$H47<>99),$F47*(1+$N47)^(EF$20)*((1+$K47)^(EF$20)),0)))) -> 0 | EG47: =IF(AND($G47=99,$H47=99),EG$22*$F47*(1+$N47)^(EG$20)*((1+$K47)^(EG$20)),IF(AND($H47=99,EG$20>=$G47,EG$20<=$F$20),$F47*(1+$N47)^(EG$20)*((1+$K47)^(EG$20)),IF(AND($G47=99,EG$20<=$H47,EG$20>=$F$18),$F47*(1+$N47)^(EG$20)*((1+$K47)^(EG$20)),IF(AND(EG$20<=$H47,EG$20>=$G47,$G47<>99,$H47<>99),$F47*(1+$N47)^(EG$20)*((1+$K47)^(EG$20)),0)))) -> 0 | EH47: =IF(AND($G47=99,$H47=99),EH$22*$F47*(1+$N47)^(EH$20)*((1+$K47)^(EH$20)),IF(AND($H47=99,EH$20>=$G47,EH$20<=$F$20),$F47*(1+$N47)^(EH$20)*((1+$K47)^(EH$20)),IF(AND($G47=99,EH$20<=$H47,EH$20>=$F$18),$F47*(1+$N47)^(EH$20)*((1+$K47)^(EH$20)),IF(AND(EH$20<=$H47,EH$20>=$G47,$G47<>99,$H47<>99),$F47*(1+$N47)^(EH$20)*((1+$K47)^(EH$20)),0)))) -> 0 | ... GB47: =IF(AND($G47=99,$H47=99),GB$22*$F47*(1+$N47)^(GB$20)*((1+$K47)^(GB$20)),IF(AND($H47=99,GB$20>=$G47,GB$20<=$F$20),$F47*(1+$N47)^(GB$20)*((1+$K47)^(GB$20)),IF(AND($G47=99,GB$20<=$H47,GB$20>=$F$18),$F47*(1+$N47)^(GB$20)*((1+$K47)^(GB$20)),IF(AND(GB$20<=$H47,GB$20>=$G47,$G47<>99,$H47<>99),$F47*(1+$N47)^(GB$20)*((1+$K47)^(GB$20)),0)))) -> 0
